Workbook

Sheet Sheet1
A1: loan program | B1: promo_term | C1: platform | D1: tagging | E1: servicing_cost | F1: irr_support | G1: type | H1: late_percent | I1: recovery_percent | J1: modeled_purchase_price | K1: new_programs | L1: proposed_cdr_promo | M1: proposed_cdr_promo_old | N1: proposed_cdr | O1: proposed_cdr_old | P1: proposed_cpr | Q1: proposed_promo_cpr_percent | R1: constant_cpr | S1: constant_cpr_old | T1: cdr_promo | U1: cdr_promo_old | V1: cdr | W1: cdr_old | X1: yield | Y1: cpr | Z1: cpr_old | AA1: loan_term | AB1: coupon
A2: Unsec Std - 1049 - 132 | B2: 12 | C2: prime | D2: PRIME | E2: 0.0165 | F2: 0.0115 | G2: hybrid | H2: 2e-05 | I2: 0.15 | J2: 0.9825 | K2: TRUE | L2: =T2*1.3 -> 0.013044096 | M2: 0.013044096 | N2: =V2*1.3 -> 0.013044096 | O2: 0.013044096 | P2: =R2*1.15 -> 0.2645 | Q2: 1 | R2: 0.23 | S2: 0.23 | T2: 0.01003392 | U2: 0.01003392 | V2: 0.01003392 | W2: 0.01003392 | X2: 0.060852269 | Y2: 0.034087798153406;0.029131872311023;0.029131872311023;0.025455429050157;0.025455429050157;0.024935476432192;0.024935476432192;0.0330338174243784;0.0330338174243784;0.052503321664899;0.0723270250344311;0.115968664711763 | Z2: 0.034087798153406;0.029131872311023;0.029131872311023;0.025455429050157;0.025455429050157;0.024935476432192;0.024935476432192;0.0330338174243784;0.0330338174243784;0.052503321664899;0.0723270250344311;0.115968664711763 | AA2: 132 | AB2: 1049
A3: Unsec Std - 1049 - 186 | B3: 6 | C3: prime | D3: PRIME | E3: 0.0165 | F3: 0.0115 | G3: hybrid | H3: 2e-05 | I3: 0.15 | J3: 0.9925 | K3: TRUE | L3: =T3*1.3 -> 0.011628552 | M3: 0.011628552 | N3: =V3*1.3 -> 0.011628552 | O3: 0.011628552 | P3: =R3*1.15 -> 0.2645 | Q3: 1 | R3: 0.23 | S3: 0.23 | T3: 0.00894504 | U3: 0.00894504 | V3: 0.00894504 | W3: 0.00894504 | X3: 0.07753936 | Y3: 0.0489849142849816;0.0428030164624041;0.0419287220074737;0.0555459909257746;0.0882837424238861;0.116654180496246 | Z3: 0.0489849142849816;0.0428030164624041;0.0419287220074737;0.0555459909257746;0.0882837424238861;0.116654180496246 | AA3: 186 | AB3: 1049
A4: Unsec Std - 1049 - 63 | B4: 3 | C4: prime | D4: PRIME | E4: 0.0165 | F4: 0.0115 | G4: hybrid | H4: 2e-05 | I4: 0.15 | J4: 1.005 | K4: TRUE | L4: =T4*1.3 -> 0.014212224 | M4: 0.014212224 | N4: =V4*1.3 -> 0.014212224 | O4: 0.014212224 | P4: =R4*1.15 -> 0.2645 | Q4: 1 | R4: 0.23 | S4: 0.23 | T4: 0.01093248 | U4: 0.01093248 | V4: 0.01093248 | W4: 0.01093248 | X4: 0.076511354 | Y4: 0.0436711592742046;0.051181123470062;0.0613711445667025 | Z4: 0.0436711592742046;0.051181123470062;0.0613711445667025 | AA4: 63 | AB4: 1049
A5: Unsec Std - 1099 / 132 | B5: 12 | C5: prime | D5: PRIME | E5: 0.0165 | F5: 0.0115 | G5: hybrid | H5: 2e-05 | I5: 0.15 | J5: 0.9825 | K5: TRUE | L5: =T5*1.3 -> 0.013044096 | M5: 0.013044096 | N5: =V5*1.3 -> 0.013044096 | O5: 0.013044096 | P5: =R5*1.15 -> 0.2645 | Q5: 1 | R5: 0.23 | S5: 0.23 | T5: 0.01003392 | U5: 0.01003392 | V5: 0.01003392 | W5: 0.01003392 | X5: 0.063656481 | Y5: 0.034087798153406;0.029131872311023;0.029131872311023;0.025455429050157;0.025455429050157;0.024935476432192;0.024935476432192;0.0330338174243784;0.0330338174243784;0.052503321664899;0.0723270250344311;0.115968664711763 | Z5: 0.034087798153406;0.029131872311023;0.029131872311023;0.025455429050157;0.025455429050157;0.024935476432192;0.024935476432192;0.0330338174243784;0.0330338174243784;0.052503321664899;0.0723270250344311;0.115968664711763 | AA5: 132 | AB5: 1099
A6: Unsec Std - 1099 / 186 | B6: 6 | C6: prime | D6: PRIME | E6: 0.0165 | F6: 0.0115 | G6: hybrid | H6: 2e-05 | I6: 0.15 | J6: 0.9925 | K6: TRUE | L6: =T6*1.3 -> 0.011628552 | M6: 0.011628552 | N6: =V6*1.3 -> 0.011628552 | O6: 0.011628552 | P6: =R6*1.15 -> 0.2645 | Q6: 1 | R6: 0.23 | S6: 0.23 | T6: 0.00894504 | U6: 0.00894504 | V6: 0.00894504 | W6: 0.00894504 | X6: 0.081311552 | Y6: 0.0489849142849816;0.0428030164624041;0.0419287220074737;0.0555459909257746;0.0882837424238861;0.116654180496246 | Z6: 0.0489849142849816;0.0428030164624041;0.0419287220074737;0.0555459909257746;0.0882837424238861;0.116654180496246 | AA6: 186 | AB6: 1099
A7: Unsec Std - 1099 / 63 | B7: 3 | C7: prime | D7: PRIME | E7: 0.0165 | F7: 0.0115 | G7: hybrid | H7: 2e-05 | I7: 0.15 | J7: 1.005 | K7: TRUE | L7: =T7*1.3 -> 0.014212224 | M7: 0.014212224 | N7: =V7*1.3 -> 0.014212224 | O7: 0.014212224 | P7: =R7*1.15 -> 0.2645 | Q7: 1 | R7: 0.23 | S7: 0.23 | T7: 0.01093248 | U7: 0.01093248 | V7: 0.01093248 | W7: 0.01093248 | X7: 0.080697011 | Y7: 0.0436711592742046;0.051181123470062;0.0613711445667025 | Z7: 0.0436711592742046;0.051181123470062;0.0613711445667025 | AA7: 63 | AB7: 1099
A8: Unsec Std - 1149 - 132 | B8: 12 | C8: prime | D8: PRIME | E8: 0.0165 | F8: 0.0115 | G8: hybrid | H8: 2e-05 | I8: 0.15 | J8: 0.9825 | K8: TRUE | L8: =T8*1.3 -> 0.01872 | M8: 0.01872 | N8: =V8*1.3 -> 0.013044096 | O8: 0.013044096 | P8: =R8*1.15 -> 0.2645 | Q8: 1 | R8: 0.23 | S8: 0.23 | T8: 0.0144 | U8: 0.0144 | V8: 0.01003392 | W8: 0.01003392 | X8: 0.064808875 | Y8: 0.034087798153406;0.029131872311023;0.029131872311023;0.025455429050157;0.025455429050157;0.024935476432192;0.024935476432192;0.0330338174243784;0.0330338174243784;0.052503321664899;0.0723270250344311;0.115968664711763 | Z8: 0.034087798153406;0.029131872311023;0.029131872311023;0.025455429050157;0.025455429050157;0.024935476432192;0.024935476432192;0.0330338174243784;0.0330338174243784;0.052503321664899;0.0723270250344311;0.115968664711763 | AA8: 132 | AB8: 1149
A9: Unsec Std - 1149 - 186 | B9: 6 | C9: prime | D9: PRIME | E9: 0.0165 | F9: 0.0115 | G9: hybrid | H9: 2e-05 | I9: 0.15 | J9: 0.9925 | K9: TRUE | L9: =T9*1.3 -> 0.01703 | M9: 0.01703 | N9: =V9*1.3 -> 0.011628552 | O9: 0.011628552 | P9: =R9*1.15 -> 0.2645 | Q9: 1 | R9: 0.23 | S9: 0.23 | T9: 0.0131 | U9: 0.0131 | V9: 0.00894504 | W9: 0.00894504 | X9: 0.084249886 | Y9: 0.0489849142849816;0.0428030164624041;0.0419287220074737;0.0555459909257746;0.0882837424238861;0.116654180496246 | Z9: 0.0489849142849816;0.0428030164624041;0.0419287220074737;0.0555459909257746;0.0882837424238861;0.116654180496246 | AA9: 186 | AB9: 1149
A10: Unsec Std - 1149 - 63 | B10: 3 | C10: prime | D10: PRIME | E10: 0.0165 | F10: 0.0115 | G10: hybrid | H10: 2e-05 | I10: 0.15 | J10: 1.005 | K10: TRUE | L10: =T10*1.3 -> 0.02028 | M10: 0.02028 | N10: =V10*1.3 -> 0.014212224 | O10: 0.014212224 | P10: =R10*1.15 -> 0.2645 | Q10: 1 | R10: 0.23 | S10: 0.23 | T10: 0.0156 | U10: 0.0156 | V10: 0.01093248 | W10: 0.01093248 | X10: 0.08426103 | Y10: 0.0436711592742046;0.051181123470062;0.0613711445667025 | Z10: 0.0436711592742046;0.051181123470062;0.0613711445667025 | AA10: 63 | AB10: 1149
A11: Unsec Std - 1199 / 132 | B11: 12 | C11: prime | D11: PRIME | E11: 0.0165 | F11: 0.0115 | G11: hybrid | H11: 2e-05 | I11: 0.15 | J11: 0.9825 | K11: TRUE | L11: =T11*1.3 -> 0.012070656 | M11: 0.012070656 | N11: =V11*1.3 -> 0.012070656 | O11: 0.012070656 | P11: =R11*1.15 -> 0.2645 | Q11: 1 | R11: 0.23 | S11: 0.23 | T11: 0.00928512 | U11: 0.00928512 | V11: 0.00928512 | W11: 0.00928512 | X11: 0.069913491 | Y11: 0.034087798153406;0.029131872311023;0.029131872311023;0.025455429050157;0.025455429050157;0.024935476432192;0.024935476432192;0.0330338174243784;0.0330338174243784;0.052503321664899;0.0723270250344311;0.115968664711763 | Z11: 0.034087798153406;0.029131872311023;0.029131872311023;0.025455429050157;0.025455429050157;0.024935476432192;0.024935476432192;0.0330338174243784;0.0330338174243784;0.052503321664899;0.0723270250344311;0.115968664711763 | AA11: 132 | AB11: 1199
A12: Unsec Std - 1199 / 186 | B12: 6 | C12: prime | D12: PRIME | E12: 0.0165 | F12: 0.0115 | G12: hybrid | H12: 2e-05 | I12: 0.15 | J12: 0.9925 | K12: TRUE | L12: =T12*1.3 -> 0.011097216 | M12: 0.011097216 | N12: =V12*1.3 -> 0.011097216 | O12: 0.011097216 | P12: =R12*1.15 -> 0.2645 | Q12: 1 | R12: 0.23 | S12: 0.23 | T12: 0.00853632 | U12: 0.00853632 | V12: 0.00853632 | W12: 0.00853632 | X12: 0.089186274 | Y12: 0.0489849142849816;0.0428030164624041;0.0419287220074737;0.0555459909257746;0.0882837424238861;0.116654180496246 | Z12: 0.0489849142849816;0.0428030164624041;0.0419287220074737;0.0555459909257746;0.0882837424238861;0.116654180496246 | AA12: 186 | AB12: 1199
A13: Unsec Std - 1199 / 63 | B13: 3 | C13: prime | D13: PRIME | E13: 0.0165 | F13: 0.0115 | G13: hybrid | H13: 2e-05 | I13: 0.15 | J13: 1.005 | K13: TRUE | L13: =T13*1.3 -> 0.012265344 | M13: 0.012265344 | N13: =V13*1.3 -> 0.012265344 | O13: 0.012265344 | P13: =R13*1.15 -> 0.2645 | Q13: 1 | R13: 0.23 | S13: 0.23 | T13: 0.00943488 | U13: 0.00943488 | V13: 0.00943488 | W13: 0.00943488 | X13: 0.090397598 | Y13: 0.0436711592742046;0.051181123470062;0.0613711445667025 | Z13: 0.0436711592742046;0.051181123470062;0.0613711445667025 | AA13: 63 | AB13: 1199
... A26: Unsec Std - 1449 - 63 | B26: 3 | C26: prime | D26: PRIME | E26: 0.0165 | F26: 0.0115 | G26: hybrid | H26: 2e-05 | I26: 0.15 | J26: 1.005 | K26: TRUE | L26: =T26*1.3 -> 0.05434 | M26: 0.05434 | N26: =V26*1.3 -> 0.024950159 | O26: 0.024950159 | P26: =R26*1.15 -> 0.2645 | Q26: 1 | R26: 0.23 | S26: 0.23 | T26: 0.0418 | U26: 0.0418 | V26: 0.01919243 | W26: 0.01919243 | X26: 0.099288061 | Y26: 0.0436711592742046;0.051181123470062;0.0613711445667025 | Z26: 0.0436711592742046;0.051181123470062;0.0613711445667025 | AA26: 63 | AB26: 1449
A27: Unsec Std - 399 - 60 | B27: 0 | C27: prime | D27: PRIME | E27: 0.0165 | F27: 0.0115 | G27: standard | H27: 2e-05 | I27: 0.15 | J27: 0.93 | K27: TRUE | L27: =T27*1.3 -> 0 | M27: 0 | N27: =V27*1.3 -> 0.0182 | O27: 0.0182 | P27: =R27*1.15 -> 0.115 | Q27: 1 | R27: 0.1 | S27: 0.1 | T27: 0 | U27: 0 | V27: 0.014 | W27: 0.014 | X27: 0.04576961 | Y27: 0 | Z27: 0 | AA27: 60 | AB27: 399
A28: Unsec Std - 399 - 84 | B28: 0 | C28: prime | D28: PRIME | E28: 0.0165 | F28: 0.0115 | G28: standard | H28: 2e-05 | I28: 0.15 | J28: 0.92 | K28: TRUE | L28: =T28*1.3 -> 0 | M28: 0 | N28: =V28*1.3 -> 0.0182 | O28: 0.0182 | P28: =R28*1.15 -> 0.115 | Q28: 1 | R28: 0.1 | S28: 0.1 | T28: 0 | U28: 0 | V28: 0.014 | W28: 0.014 | X28: 0.041813838 | Y28: 0 | Z28: 0 | AA28: 84 | AB28: 399
A29: Unsec Std - 649 - 132 | B29: 12 | C29: prime | D29: PRIME | E29: 0.0165 | F29: 0.0115 | G29: hybrid | H29: 2e-05 | I29: 0.15 | J29: 0.9825 | K29: TRUE | L29: =T29*1.3 -> 0.00754 | M29: 0.00754 | N29: =V29*1.3 -> 0.0060032177 | O29: 0.0060032177 | P29: =R29*1.15 -> 0.2645 | Q29: 1 | R29: 0.23 | S29: 0.23 | T29: 0.0058 | U29: 0.0058 | V29: 0.0046178598 | W29: 0.0046178598 | X29: 0.042425322 | Y29: 0.034087798153406;0.029131872311023;0.029131872311023;0.025455429050157;0.025455429050157;0.024935476432192;0.024935476432192;0.0330338174243784;0.0330338174243784;0.052503321664899;0.0723270250344311;0.115968664711763 | Z29: 0.034087798153406;0.029131872311023;0.029131872311023;0.025455429050157;0.025455429050157;0.024935476432192;0.024935476432192;0.0330338174243784;0.0330338174243784;0.052503321664899;0.0723270250344311;0.115968664711763 | AA29: 132 | AB29: 649
A30: Unsec Std - 649 - 186 | B30: 6 | C30: prime | D30: PRIME | E30: 0.0165 | F30: 0.0115 | G30: hybrid | H30: 2e-05 | I30: 0.15 | J30: 0.9925 | K30: TRUE | L30: =T30*1.3 -> 0.0056784 | M30: 0.0056784 | N30: =V30*1.3 -> 0.0056784 | O30: 0.0056784 | P30: =R30*1.15 -> 0.2645 | Q30: 1 | R30: 0.23 | S30: 0.23 | T30: 0.004368 | U30: 0.004368 | V30: 0.004368 | W30: 0.004368 | X30: 0.050952089 | Y30: 0.0489849142849816;0.0428030164624041;0.0419287220074737;0.0555459909257746;0.0882837424238861;0.116654180496246 | Z30: 0.0489849142849816;0.0428030164624041;0.0419287220074737;0.0555459909257746;0.0882837424238861;0.116654180496246 | AA30: 186 | AB30: 649
A31: Unsec Std - 699 / 186 | B31: 6 | C31: prime | D31: PRIME | E31: 0.0165 | F31: 0.0115 | G31: hybrid | H31: 2e-05 | I31: 0.15 | J31: 0.9925 | K31: TRUE | L31: =T31*1.3 -> 0.0056784 | M31: 0.0056784 | N31: =V31*1.3 -> 0.0056784 | O31: 0.0056784 | P31: =R31*1.15 -> 0.2645 | Q31: 1 | R31: 0.23 | S31: 0.23 | T31: 0.004368 | U31: 0.004368 | V31: 0.004368 | W31: 0.004368 | X31: 0.054827875 | Y31: 0.0489849142849816;0.0428030164624041;0.0419287220074737;0.0555459909257746;0.0882837424238861;0.116654180496246 | Z31: 0.0489849142849816;0.0428030164624041;0.0419287220074737;0.0555459909257746;0.0882837424238861;0.116654180496246 | AA31: 186 | AB31: 699
A32: Unsec Std - 749 - 186 | B32: 6 | C32: prime | D32: PRIME | E32: 0.0165 | F32: 0.0115 | G32: hybrid | H32: 2e-05 | I32: 0.15 | J32: 0.9925 | K32: TRUE | L32: =T32*1.3 -> 0.00689 | M32: 0.00689 | N32: =V32*1.3 -> 0.0056784 | O32: 0.0056784 | P32: =R32*1.15 -> 0.2645 | Q32: 1 | R32: 0.23 | S32: 0.23 | T32: 0.0053 | U32: 0.0053 | V32: 0.004368 | W32: 0.004368 | X32: 0.058518074 | Y32: 0.0489849142849816;0.0428030164624041;0.0419287220074737;0.0555459909257746;0.0882837424238861;0.116654180496246 | Z32: 0.0489849142849816;0.0428030164624041;0.0419287220074737;0.0555459909257746;0.0882837424238861;0.116654180496246 | AA32: 186 | AB32: 749
A33: Unsec Std - 849 - 120 | B33: 0 | C33: prime | D33: PRIME | E33: 0.0165 | F33: 0.0115 | G33: standard | H33: 2e-05 | I33: 0.15 | J33: 0.9825 | K33: TRUE | L33: =T33*1.3 -> 0 | M33: 0 | N33: =V33*1.3 -> 0.0364 | O33: 0.0364 | P33: =R33*1.15 -> 0.138 | Q33: 1 | R33: 0.12 | S33: 0.12 | T33: 0 | U33: 0 | V33: 0.028 | W33: 0.028 | X33: 0.065878879 | Y33: 0 | Z33: 0 | AA33: 120 | AB33: 849
A34: Unsec Std - 849 - 132 | B34: 12 | C34: prime | D34: PRIME | E34: 0.0165 | F34: 0.0115 | G34: hybrid | H34: 2e-05 | I34: 0.15 | J34: 0.9825 | K34: TRUE | L34: =T34*1.3 -> 0.0060032177 | M34: 0.0060032177 | N34: =V34*1.3 -> 0.0060032177 | O34: 0.0060032177 | P34: =R34*1.15 -> 0.2645 | Q34: 1 | R34: 0.23 | S34: 0.23 | T34: 0.0046178598 | U34: 0.0046178598 | V34: 0.0046178598 | W34: 0.0046178598 | X34: 0.054357781 | Y34: 0.034087798153406;0.029131872311023;0.029131872311023;0.025455429050157;0.025455429050157;0.024935476432192;0.024935476432192;0.0330338174243784;0.0330338174243784;0.052503321664899;0.0723270250344311;0.115968664711763 | Z34: 0.034087798153406;0.029131872311023;0.029131872311023;0.025455429050157;0.025455429050157;0.024935476432192;0.024935476432192;0.0330338174243784;0.0330338174243784;0.052503321664899;0.0723270250344311;0.115968664711763 | AA34: 132 | AB34: 849
A35: Unsec Std - 849 - 180 | B35: 0 | C35: prime | D35: PRIME | E35: 0.0165 | F35: 0.0115 | G35: standard | H35: 2e-05 | I35: 0.15 | J35: 0.9825 | K35: TRUE | L35: =T35*1.3 -> 0 | M35: 0 | N35: =V35*1.3 -> 0.0364 | O35: 0.0364 | P35: =R35*1.15 -> 0.138 | Q35: 1 | R35: 0.12 | S35: 0.12 | T35: 0 | U35: 0 | V35: 0.028 | W35: 0.028 | X35: 0.064873162 | Y35: 0 | Z35: 0 | AA35: 180 | AB35: 849
A36: Unsec Std - 849 - 63 | B36: 3 | C36: prime | D36: PRIME | E36: 0.0165 | F36: 0.0115 | G36: hybrid | H36: 2e-05 | I36: 0.15 | J36: 1.005 | K36: TRUE | L36: =T36*1.3 -> 0.0053361935 | M36: 0.0053361935 | N36: =V36*1.3 -> 0.0053361935 | O36: 0.0053361935 | P36: =R36*1.15 -> 0.2645 | Q36: 1 | R36: 0.23 | S36: 0.23 | T36: 0.0041047642 | U36: 0.0041047642 | V36: 0.0041047642 | W36: 0.0041047642 | X36: 0.0657583 | Y36: 0.0436711592742046;0.051181123470062;0.0613711445667025 | Z36: 0.0436711592742046;0.051181123470062;0.0613711445667025 | AA36: 63 | AB36: 849
A37: Unsec Std - 899 / 120 | B37: 0 | C37: prime | D37: PRIME | E37: 0.0165 | F37: 0.0115 | G37: standard | H37: 2e-05 | I37: 0.15 | J37: 0.9825 | K37: TRUE | L37: =T37*1.3 -> 0 | M37: 0 | N37: =V37*1.3 -> 0.0416 | O37: 0.0416 | P37: =R37*1.15 -> 0.138 | Q37: 1 | R37: 0.12 | S37: 0.12 | T37: 0 | U37: 0 | V37: 0.032 | W37: 0.032 | X37: 0.050711555 | Y37: 0 | Z37: 0 | AA37: 120 | AB37: 899
A38: Unsec Std - 899 / 132 | B38: 12 | C38: prime | D38: PRIME | E38: 0.0165 | F38: 0.0115 | G38: hybrid | H38: 2e-05 | I38: 0.15 | J38: 0.9825 | K38: TRUE | L38: =T38*1.3 -> 0.0060032177 | M38: 0.0060032177 | N38: =V38*1.3 -> 0.0060032177 | O38: 0.0060032177 | P38: =R38*1.15 -> 0.2645 | Q38: 1 | R38: 0.23 | S38: 0.23 | T38: 0.0046178598 | U38: 0.0046178598 | V38: 0.0046178598 | W38: 0.0046178598 | X38: 0.057211783 | Y38: 0.034087798153406;0.029131872311023;0.029131872311023;0.025455429050157;0.025455429050157;0.024935476432192;0.024935476432192;0.0330338174243784;0.0330338174243784;0.052503321664899;0.0723270250344311;0.115968664711763 | Z38: 0.034087798153406;0.029131872311023;0.029131872311023;0.025455429050157;0.025455429050157;0.024935476432192;0.024935476432192;0.0330338174243784;0.0330338174243784;0.052503321664899;0.0723270250344311;0.115968664711763 | AA38: 132 | AB38: 899
A39: Unsec Std - 899 / 180 | B39: 0 | C39: prime | D39: PRIME | E39: 0.0165 | F39: 0.0115 | G39: standard | H39: 2e-05 | I39: 0.15 | J39: 0.9825 | K39: TRUE | L39: =T39*1.3 -> 0 | M39: 0 | N39: =V39*1.3 -> 0.0416 | O39: 0.0416 | P39: =R39*1.15 -> 0.138 | Q39: 1 | R39: 0.12 | S39: 0.12 | T39: 0 | U39: 0 | V39: 0.032 | W39: 0.032 | X39: 0.049700226 | Y39: 0 | Z39: 0 | AA39: 180 | AB39: 899
A40: Unsec Std - 899 / 63 | B40: 3 | C40: prime | D40: PRIME | E40: 0.0165 | F40: 0.0115 | G40: hybrid | H40: 2e-05 | I40: 0.15 | J40: 1.005 | K40: TRUE | L40: =T40*1.3 -> 0.0053361935 | M40: 0.0053361935 | N40: =V40*1.3 -> 0.0053361935 | O40: 0.0053361935 | P40: =R40*1.15 -> 0.2645 | Q40: 1 | R40: 0.23 | S40: 0.23 | T40: 0.0041047642 | U40: 0.0041047642 | V40: 0.0041047642 | W40: 0.0041047642 | X40: 0.069972552 | Y40: 0.0436711592742046;0.051181123470062;0.0613711445667025 | Z40: 0.0436711592742046;0.051181123470062;0.0613711445667025 | AA40: 63 | AB40: 899
A41: Unsec Std - 949 - 120 | B41: 0 | C41: prime | D41: PRIME | E41: 0.0165 | F41: 0.0115 | G41: standard | H41: 2e-05 | I41: 0.15 | J41: 0.9825 | K41: TRUE | L41: =T41*1.3 -> 0 | M41: 0 | N41: =V41*1.3 -> 0.0364 | O41: 0.0364 | P41: =R41*1.15 -> 0.138 | Q41: 1 | R41: 0.12 | S41: 0.12 | T41: 0 | U41: 0 | V41: 0.028 | W41: 0.028 | X41: 0.075865399 | Y41: 0 | Z41: 0 | AA41: 120 | AB41: 949
A42: Unsec Std - 949 - 132 | B42: 12 | C42: prime | D42: PRIME | E42: 0.0165 | F42: 0.0115 | G42: hybrid | H42: 2e-05 | I42: 0.15 | J42: 0.9825 | K42: TRUE | L42: =T42*1.3 -> 0.00754 | M42: 0.00754 | N42: =V42*1.3 -> 0.0060032177 | O42: 0.0060032177 | P42: =R42*1.15 -> 0.2645 | Q42: 1 | R42: 0.23 | S42: 0.23 | T42: 0.0058 | U42: 0.0058 | V42: 0.0046178598 | W42: 0.0046178598 | X42: 0.059621221 | Y42: 0.034087798153406;0.029131872311023;0.029131872311023;0.025455429050157;0.025455429050157;0.024935476432192;0.024935476432192;0.0330338174243784;0.0330338174243784;0.052503321664899;0.0723270250344311;0.115968664711763 | Z42: 0.034087798153406;0.029131872311023;0.029131872311023;0.025455429050157;0.025455429050157;0.024935476432192;0.024935476432192;0.0330338174243784;0.0330338174243784;0.052503321664899;0.0723270250344311;0.115968664711763 | AA42: 132 | AB42: 949
A43: Unsec Std - 949 - 63 | B43: 3 | C43: prime | D43: PRIME | E43: 0.0165 | F43: 0.0115 | G43: hybrid | H43: 2e-05 | I43: 0.15 | J43: 1.005 | K43: TRUE | L43: =T43*1.3 -> 0.00676 | M43: 0.00676 | N43: =V43*1.3 -> 0.0053361935 | O43: 0.0053361935 | P43: =R43*1.15 -> 0.2645 | Q43: 1 | R43: 0.23 | S43: 0.23 | T43: 0.0052 | U43: 0.0052 | V43: 0.0041047642 | W43: 0.0041047642 | X43: 0.074040846 | Y43: 0.0436711592742046;0.051181123470062;0.0613711445667025 | Z43: 0.0436711592742046;0.051181123470062;0.0613711445667025 | AA43: 63 | AB43: 949
A44: Unsec Std - EPNI 36 Mo | B44: 36 | C44: prime | D44: PRIME | E44: 0.0165 | F44: 0.0115 | G44: epni | H44: 2e-05 | I44: 0.15 | J44: 0.92 | K44: TRUE | L44: =T44*1.3 -> 0 | M44: 0 | N44: =V44*1.3 -> 0.014380391 | O44: 0.014380391 | P44: =R44*1.15 -> 0.2461 | Q44: 1 | R44: 0.214 | S44: 0.214 | T44: 0 | U44: 0 | V44: 0.011061839 | W44: 0.011061839 | X44: 0.059255891 | Y44: 0 | Z44: 0 | AA44: 36 | AB44: 0
A45: Unsec Std - EPNI 60 Mo | B45: 60 | C45: prime | D45: PRIME | E45: 0.0165 | F45: 0.0115 | G45: epni | H45: 2e-05 | I45: 0.15 | J45: 0.885 | K45: TRUE | L45: =T45*1.3 -> 0 | M45: 0 | N45: =V45*1.3 -> 0.013407174 | O45: 0.013407174 | P45: =R45*1.15 -> 0.15985 | Q45: 1 | R45: 0.139 | S45: 0.139 | T45: 0 | U45: 0 | V45: 0.010313211 | W45: 0.010313211 | X45: 0.05356764 | Y45: 0 | Z45: 0 | AA45: 60 | AB45: 0
A46: 6 Mth BD WPDI | B46: 6 | C46: sfy | D46: BD | E46: 0.02 | F46: 0.0125 | G46: wpdi_bd | H46: 2e-05 | I46: 0.15 | J46: 0.9135 | K46: TRUE | L46: =T46*1.3 -> 0.12532 | M46: 0.12532 | N46: =V46*1.3 -> 0.12532 | O46: 0.12532 | P46: =R46*1.15 -> 0.269675 | Q46: 1 | R46: 0.2345 | S46: 0.2345 | T46: 0.0964 | U46: 0.0964 | V46: 0.0964 | W46: 0.0964 | X46: 0.1578011 | Y46: 0.014038095;0.02807619;0.042114286;0.056152381;0.070190476;0.084228571 | Z46: 0.014038095;0.02807619;0.042114286;0.056152381;0.070190476;0.084228571 | AA46: 61 | AB46: 1599
A47: 6 Mth BD WPDI 12S | B47: 12 | C47: sfy | D47: BD | E47: 0.02 | F47: 0.0125 | G47: wpdi_bd | H47: 2e-05 | I47: 0.15 | J47: 0.9135 | K47: TRUE | L47: =T47*1.3 -> 0.12532 | M47: 0.12532 | N47: =V47*1.3 -> 0.12532 | O47: 0.12532 | P47: =R47*1.15 -> 0.27485 | Q47: 1 | R47: 0.239 | S47: 0.239 | T47: 0.0964 | U47: 0.0964 | V47: 0.0964 | W47: 0.0964 | X47: 0.12729977 | Y47: 0.006064103;0.012128205;0.018192308;0.02425641;0.030320513;0.036384615;0.042448718;0.048512821;0.054576923;0.060641026;0.066705128;0.072769231 | Z47: 0.006064103;0.012128205;0.018192308;0.02425641;0.030320513;0.036384615;0.042448718;0.048512821;0.054576923;0.060641026;0.066705128;0.072769231 | AA47: 63 | AB47: 1599
A48: Unsec Std - 1049 - 132 | B48: 12 | C48: sfy | D48: SFY | E48: 0.02 | F48: 0.0125 | G48: hybrid | H48: 2e-05 | I48: 0.15 | J48: 0.975 | K48: TRUE | L48: =T48*1.3 -> 0.027451008 | M48: 0.027451008 | N48: =V48*1.3 -> 0.027451008 | O48: 0.027451008 | P48: =R48*1.15 -> 0.2645 | Q48: 1 | R48: 0.23 | S48: 0.23 | T48: 0.02111616 | U48: 0.02111616 | V48: 0.02111616 | W48: 0.02111616 | X48: 0.054664883 | Y48: 0.034087798153406;0.029131872311023;0.029131872311023;0.025455429050157;0.025455429050157;0.024935476432192;0.024935476432192;0.0330338174243784;0.0330338174243784;0.052503321664899;0.0723270250344311;0.115968664711763 | Z48: 0.034087798153406;0.029131872311023;0.029131872311023;0.025455429050157;0.025455429050157;0.024935476432192;0.024935476432192;0.0330338174243784;0.0330338174243784;0.052503321664899;0.0723270250344311;0.115968664711763 | AA48: 132 | AB48: 1049
A49: Unsec Std - 1049 - 186 | B49: 6 | C49: sfy | D49: SFY | E49: 0.02 | F49: 0.0125 | G49: hybrid | H49: 2e-05 | I49: 0.15 | J49: 0.985 | K49: TRUE | L49: =T49*1.3 -> 0.023644452 | M49: 0.023644452 | N49: =V49*1.3 -> 0.023644452 | O49: 0.023644452 | P49: =R49*1.15 -> 0.2645 | Q49: 1 | R49: 0.23 | S49: 0.23 | T49: 0.01818804 | U49: 0.01818804 | V49: 0.01818804 | W49: 0.01818804 | X49: 0.073033018 | Y49: 0.0489849142849816;0.0428030164624041;0.0419287220074737;0.0555459909257746;0.0882837424238861;0.116654180496246 | Z49: 0.0489849142849816;0.0428030164624041;0.0419287220074737;0.0555459909257746;0.0882837424238861;0.116654180496246 | AA49: 186 | AB49: 1049
A50: Unsec Std - 1049 - 63 | B50: 3 | C50: sfy | D50: SFY | E50: 0.02 | F50: 0.0125 | G50: hybrid | H50: 2e-05 | I50: 0.15 | J50: 0.9975 | K50: TRUE | L50: =T50*1.3 -> 0.029738592 | M50: 0.029738592 | N50: =V50*1.3 -> 0.029738592 | O50: 0.029738592 | P50: =R50*1.15 -> 0.2645 | Q50: 1 | R50: 0.23 | S50: 0.23 | T50: 0.02287584 | U50: 0.02287584 | V50: 0.02287584 | W50: 0.02287584 | X50: 0.070468849 | Y50: 0.0436711592742046;0.051181123470062;0.0613711445667025 | Z50: 0.0436711592742046;0.051181123470062;0.0613711445667025 | AA50: 63 | AB50: 1049
A51: Unsec Std - 1099 - 120 | B51: 0 | C51: sfy | D51: SFY | E51: 0.02 | F51: 0.0125 | G51: standard | H51: 2e-05 | I51: 0.15 | J51: 0.8925 | K51: TRUE | L51: =T51*1.3 -> 0 | M51: 0 | N51: =V51*1.3 -> 0.12532 | O51: 0.12532 | P51: =R51*1.15 -> 0.18745 | Q51: 1 | R51: 0.163 | S51: 0.163 | T51: 0 | U51: 0 | V51: 0.0964 | W51: 0.0964 | X51: 0.067758858 | Y51: 0 | Z51: 0 | AA51: 120 | AB51: 1099
A52: Unsec Std - 1099 / 132 | B52: 12 | C52: sfy | D52: SFY | E52: 0.02 | F52: 0.0125 | G52: hybrid | H52: 2e-05 | I52: 0.15 | J52: 0.975 | K52: TRUE | L52: =T52*1.3 -> 0.027451008 | M52: 0.027451008 | N52: =V52*1.3 -> 0.027451008 | O52: 0.027451008 | P52: =R52*1.15 -> 0.2645 | Q52: 1 | R52: 0.23 | S52: 0.23 | T52: 0.02111616 | U52: 0.02111616 | V52: 0.02111616 | W52: 0.02111616 | X52: 0.057446902 | Y52: 0.034087798153406;0.029131872311023;0.029131872311023;0.025455429050157;0.025455429050157;0.024935476432192;0.024935476432192;0.0330338174243784;0.0330338174243784;0.052503321664899;0.0723270250344311;0.115968664711763 | Z52: 0.034087798153406;0.029131872311023;0.029131872311023;0.025455429050157;0.025455429050157;0.024935476432192;0.024935476432192;0.0330338174243784;0.0330338174243784;0.052503321664899;0.0723270250344311;0.115968664711763 | AA52: 132 | AB52: 1099
A53: Unsec Std - 1099 / 186 | B53: 6 | C53: sfy | D53: SFY | E53: 0.02 | F53: 0.0125 | G53: hybrid | H53: 2e-05 | I53: 0.15 | J53: 0.985 | K53: TRUE | L53: =T53*1.3 -> 0.023644452 | M53: 0.023644452 | N53: =V53*1.3 -> 0.023644452 | O53: 0.023644452 | P53: =R53*1.15 -> 0.2645 | Q53: 1 | R53: 0.23 | S53: 0.23 | T53: 0.01818804 | U53: 0.01818804 | V53: 0.01818804 | W53: 0.01818804 | X53: 0.076803138 | Y53: 0.0489849142849816;0.0428030164624041;0.0419287220074737;0.0555459909257746;0.0882837424238861;0.116654180496246 | Z53: 0.0489849142849816;0.0428030164624041;0.0419287220074737;0.0555459909257746;0.0882837424238861;0.116654180496246 | AA53: 186 | AB53: 1099
A54: Unsec Std - 1099 / 63 | B54: 3 | C54: sfy | D54: SFY | E54: 0.02 | F54: 0.0125 | G54: hybrid | H54: 2e-05 | I54: 0.15 | J54: 0.9975 | K54: TRUE | L54: =T54*1.3 -> 0.029738592 | M54: 0.029738592 | N54: =V54*1.3 -> 0.029738592 | O54: 0.029738592 | P54: =R54*1.15 -> 0.2645 | Q54: 1 | R54: 0.23 | S54: 0.23 | T54: 0.02287584 | U54: 0.02287584 | V54: 0.02287584 | W54: 0.02287584 | X54: 0.074645872 | Y54: 0.0436711592742046;0.051181123470062;0.0613711445667025 | Z54: 0.0436711592742046;0.051181123470062;0.0613711445667025 | AA54: 63 | AB54: 1099
A55: Unsec Std - 1149 - 132 | B55: 12 | C55: sfy | D55: SFY | E55: 0.02 | F55: 0.0125 | G55: hybrid | H55: 2e-05 | I55: 0.15 | J55: 0.975 | K55: TRUE | L55: =T55*1.3 -> 0.01872 | M55: 0.01872 | N55: =V55*1.3 -> 0.027451008 | O55: 0.027451008 | P55: =R55*1.15 -> 0.2645 | Q55: 1 | R55: 0.23 | S55: 0.23 | T55: 0.0144 | U55: 0.0144 | V55: 0.02111616 | W55: 0.02111616 | X55: 0.062764004 | Y55: 0.034087798153406;0.029131872311023;0.029131872311023;0.025455429050157;0.025455429050157;0.024935476432192;0.024935476432192;0.0330338174243784;0.0330338174243784;0.052503321664899;0.0723270250344311;0.115968664711763 | Z55: 0.034087798153406;0.029131872311023;0.029131872311023;0.025455429050157;0.025455429050157;0.024935476432192;0.024935476432192;0.0330338174243784;0.0330338174243784;0.052503321664899;0.0723270250344311;0.115968664711763 | AA55: 132 | AB55: 1149
A56: Unsec Std - 1149 - 186 | B56: 6 | C56: sfy | D56: SFY | E56: 0.02 | F56: 0.0125 | G56: hybrid | H56: 2e-05 | I56: 0.15 | J56: 0.985 | K56: TRUE | L56: =T56*1.3 -> 0.01703 | M56: 0.01703 | N56: =V56*1.3 -> 0.023644452 | O56: 0.023644452 | P56: =R56*1.15 -> 0.2645 | Q56: 1 | R56: 0.23 | S56: 0.23 | T56: 0.0131 | U56: 0.0131 | V56: 0.01818804 | W56: 0.01818804 | X56: 0.081576783 | Y56: 0.0489849142849816;0.0428030164624041;0.0419287220074737;0.0555459909257746;0.0882837424238861;0.116654180496246 | Z56: 0.0489849142849816;0.0428030164624041;0.0419287220074737;0.0555459909257746;0.0882837424238861;0.116654180496246 | AA56: 186 | AB56: 1149
A57: Unsec Std - 1149 - 63 | B57: 3 | C57: sfy | D57: SFY | E57: 0.02 | F57: 0.0125 | G57: hybrid | H57: 2e-05 | I57: 0.15 | J57: 0.9975 | K57: TRUE | L57: =T57*1.3 -> 0.02028 | M57: 0.02028 | N57: =V57*1.3 -> 0.029738592 | O57: 0.029738592 | P57: =R57*1.15 -> 0.2645 | Q57: 1 | R57: 0.23 | S57: 0.23 | T57: 0.0156 | U57: 0.0156 | V57: 0.02287584 | W57: 0.02287584 | X57: 0.079787006 | Y57: 0.0436711592742046;0.051181123470062;0.0613711445667025 | Z57: 0.0436711592742046;0.051181123470062;0.0613711445667025 | AA57: 63 | AB57: 1149
A58: Unsec Std - 1199 / 132 | B58: 12 | C58: sfy | D58: SFY | E58: 0.02 | F58: 0.0125 | G58: hybrid | H58: 2e-05 | I58: 0.15 | J58: 0.975 | K58: TRUE | L58: =T58*1.3 -> 0.026871 | M58: 0.026871 | N58: =V58*1.3 -> 0.026871 | O58: 0.026871 | P58: =R58*1.15 -> 0.2645 | Q58: 1 | R58: 0.23 | S58: 0.23 | T58: 0.02067 | U58: 0.02067 | V58: 0.02067 | W58: 0.02067 | X58: 0.063387707 | Y58: 0.034087798153406;0.029131872311023;0.029131872311023;0.025455429050157;0.025455429050157;0.024935476432192;0.024935476432192;0.0330338174243784;0.0330338174243784;0.052503321664899;0.0723270250344311;0.115968664711763 | Z58: 0.034087798153406;0.029131872311023;0.029131872311023;0.025455429050157;0.025455429050157;0.024935476432192;0.024935476432192;0.0330338174243784;0.0330338174243784;0.052503321664899;0.0723270250344311;0.115968664711763 | AA58: 132 | AB58: 1199
A59: Unsec Std - 1199 / 186 | B59: 6 | C59: sfy | D59: SFY | E59: 0.02 | F59: 0.0125 | G59: hybrid | H59: 2e-05 | I59: 0.15 | J59: 0.985 | K59: TRUE | L59: =T59*1.3 -> 0.02226744 | M59: 0.02226744 | N59: =V59*1.3 -> 0.02226744 | O59: 0.02226744 | P59: =R59*1.15 -> 0.2645 | Q59: 1 | R59: 0.23 | S59: 0.23 | T59: 0.0171288 | U59: 0.0171288 | V59: 0.0171288 | W59: 0.0171288 | X59: 0.0852633 | Y59: 0.0489849142849816;0.0428030164624041;0.0419287220074737;0.0555459909257746;0.0882837424238861;0.116654180496246 | Z59: 0.0489849142849816;0.0428030164624041;0.0419287220074737;0.0555459909257746;0.0882837424238861;0.116654180496246 | AA59: 186 | AB59: 1199
A60: Unsec Std - 1199 / 63 | B60: 3 | C60: sfy | D60: SFY | E60: 0.02 | F60: 0.0125 | G60: hybrid | H60: 2e-05 | I60: 0.15 | J60: 0.9975 | K60: TRUE | L60: =T60*1.3 -> 0.0272766 | M60: 0.0272766 | N60: =V60*1.3 -> 0.0272766 | O60: 0.0272766 | P60: =R60*1.15 -> 0.2645 | Q60: 1 | R60: 0.23 | S60: 0.23 | T60: 0.020982 | U60: 0.020982 | V60: 0.020982 | W60: 0.020982 | X60: 0.084693796 | Y60: 0.0436711592742046;0.051181123470062;0.0613711445667025 | Z60: 0.0436711592742046;0.051181123470062;0.0613711445667025 | AA60: 63 | AB60: 1199
A61: Unsec Std - 1249 - 132 | B61: 12 | C61: sfy | D61: SFY | E61: 0.02 | F61: 0.0125 | G61: hybrid | H61: 2e-05 | I61: 0.15 | J61: 0.975 | K61: TRUE | L61: =T61*1.3 -> 0.03445 | M61: 0.03445 | N61: =V61*1.3 -> 0.026871 | O61: 0.026871 | P61: =R61*1.15 -> 0.2645 | Q61: 1 | R61: 0.23 | S61: 0.23 | T61: 0.0265 | U61: 0.0265 | V61: 0.02067 | W61: 0.02067 | X61: 0.06390404 | Y61: 0.034087798153406;0.029131872311023;0.029131872311023;0.025455429050157;0.025455429050157;0.024935476432192;0.024935476432192;0.0330338174243784;0.0330338174243784;0.052503321664899;0.0723270250344311;0.115968664711763 | Z61: 0.034087798153406;0.029131872311023;0.029131872311023;0.025455429050157;0.025455429050157;0.024935476432192;0.024935476432192;0.0330338174243784;0.0330338174243784;0.052503321664899;0.0723270250344311;0.115968664711763 | AA61: 132 | AB61: 1249
A62: Unsec Std - 1249 - 186 | B62: 6 | C62: sfy | D62: SFY | E62: 0.02 | F62: 0.0125 | G62: hybrid | H62: 2e-05 | I62: 0.15 | J62: 0.985 | K62: TRUE | L62: =T62*1.3 -> 0.03172 | M62: 0.03172 | N62: =V62*1.3 -> 0.02226744 | O62: 0.02226744 | P62: =R62*1.15 -> 0.2645 | Q62: 1 | R62: 0.23 | S62: 0.23 | T62: 0.0244 | U62: 0.0244 | V62: 0.0171288 | W62: 0.0171288 | X62: 0.087522637 | Y62: 0.0489849142849816;0.0428030164624041;0.0419287220074737;0.0555459909257746;0.0882837424238861;0.116654180496246 | Z62: 0.0489849142849816;0.0428030164624041;0.0419287220074737;0.0555459909257746;0.0882837424238861;0.116654180496246 | AA62: 186 | AB62: 1249
A63: Unsec Std - 1249 - 63 | B63: 3 | C63: sfy | D63: SFY | E63: 0.02 | F63: 0.0125 | G63: hybrid | H63: 2e-05 | I63: 0.15 | J63: 0.9975 | K63: TRUE | L63: =T63*1.3 -> 0.03497 | M63: 0.03497 | N63: =V63*1.3 -> 0.0272766 | O63: 0.0272766 | P63: =R63*1.15 -> 0.2645 | Q63: 1 | R63: 0.23 | S63: 0.23 | T63: 0.0269 | U63: 0.0269 | V63: 0.020982 | W63: 0.020982 | X63: 0.088064199 | Y63: 0.0436711592742046;0.051181123470062;0.0613711445667025 | Z63: 0.0436711592742046;0.051181123470062;0.0613711445667025 | AA63: 63 | AB63: 1249
... A67: Unsec Std - 1349 - 63 | B67: 3 | C67: sfy | D67: SFY | E67: 0.02 | F67: 0.0125 | G67: hybrid | H67: 2e-05 | I67: 0.15 | J67: 0.9975 | K67: TRUE | L67: =T67*1.3 -> 0.057643872 | M67: 0.057643872 | N67: =V67*1.3 -> 0.057643872 | O67: 0.057643872 | P67: =R67*1.15 -> 0.2645 | Q67: 1 | R67: 0.23 | S67: 0.23 | T67: 0.04434144 | U67: 0.04434144 | V67: 0.04434144 | W67: 0.04434144 | X67: 0.075940043 | Y67: 0.0436711592742046;0.051181123470062;0.0613711445667025 | Z67: 0.0436711592742046;0.051181123470062;0.0613711445667025 | AA67: 63 | AB67: 1349
A68: Unsec Std - 1390 - 120 | B68: 0 | C68: sfy | D68: SFY | E68: 0.02 | F68: 0.0125 | G68: standard | H68: 2e-05 | I68: 0.15 | J68: 0.9625 | K68: TRUE | L68: =T68*1.3 -> 0 | M68: 0 | N68: =V68*1.3 -> 0.12532 | O68: 0.12532 | P68: =R68*1.15 -> 0.18745 | Q68: 1 | R68: 0.163 | S68: 0.163 | T68: 0 | U68: 0 | V68: 0.0964 | W68: 0.0964 | X68: 0.065834672 | Y68: 0 | Z68: 0 | AA68: 120 | AB68: 1390
A69: Unsec Std - 1399 / 132 | B69: 12 | C69: sfy | D69: SFY | E69: 0.02 | F69: 0.0125 | G69: hybrid | H69: 2e-05 | I69: 0.15 | J69: 0.975 | K69: TRUE | L69: =T69*1.3 -> 0.054885792 | M69: 0.054885792 | N69: =V69*1.3 -> 0.054885792 | O69: 0.054885792 | P69: =R69*1.15 -> 0.2645 | Q69: 1 | R69: 0.23 | S69: 0.23 | T69: 0.04221984 | U69: 0.04221984 | V69: 0.04221984 | W69: 0.04221984 | X69: 0.05451089 | Y69: 0.034087798153406;0.029131872311023;0.029131872311023;0.025455429050157;0.025455429050157;0.024935476432192;0.024935476432192;0.0330338174243784;0.0330338174243784;0.052503321664899;0.0723270250344311;0.115968664711763 | Z69: 0.034087798153406;0.029131872311023;0.029131872311023;0.025455429050157;0.025455429050157;0.024935476432192;0.024935476432192;0.0330338174243784;0.0330338174243784;0.052503321664899;0.0723270250344311;0.115968664711763 | AA69: 132 | AB69: 1399
A70: Unsec Std - 1399 / 186 | B70: 6 | C70: sfy | D70: SFY | E70: 0.02 | F70: 0.0125 | G70: hybrid | H70: 2e-05 | I70: 0.15 | J70: 0.985 | K70: TRUE | L70: =T70*1.3 -> 0.048128496 | M70: 0.048128496 | N70: =V70*1.3 -> 0.048128496 | O70: 0.048128496 | P70: =R70*1.15 -> 0.2645 | Q70: 1 | R70: 0.23 | S70: 0.23 | T70: 0.03702192 | U70: 0.03702192 | V70: 0.03702192 | W70: 0.03702192 | X70: 0.081951748 | Y70: 0.0489849142849816;0.0428030164624041;0.0419287220074737;0.0555459909257746;0.0882837424238861;0.116654180496246 | Z70: 0.0489849142849816;0.0428030164624041;0.0419287220074737;0.0555459909257746;0.0882837424238861;0.116654180496246 | AA70: 186 | AB70: 1399
A71: Unsec Std - 1399 / 63 | B71: 3 | C71: sfy | D71: SFY | E71: 0.02 | F71: 0.0125 | G71: hybrid | H71: 2e-05 | I71: 0.15 | J71: 0.9975 | K71: TRUE | L71: =T71*1.3 -> 0.057643872 | M71: 0.057643872 | N71: =V71*1.3 -> 0.057643872 | O71: 0.057643872 | P71: =R71*1.15 -> 0.2645 | Q71: 1 | R71: 0.23 | S71: 0.23 | T71: 0.04434144 | U71: 0.04434144 | V71: 0.04434144 | W71: 0.04434144 | X71: 0.080055138 | Y71: 0.0436711592742046;0.051181123470062;0.0613711445667025 | Z71: 0.0436711592742046;0.051181123470062;0.0613711445667025 | AA71: 63 | AB71: 1399
A72: Unsec Std - 1440 - 120 | B72: 0 | C72: sfy | D72: BD | E72: 0.02 | F72: 0.0125 | G72: standard_bd | H72: 2e-05 | I72: 0.15 | J72: 0.9625 | K72: TRUE | L72: =T72*1.3 -> 0 | M72: 0 | N72: =V72*1.3 -> 0.12532 | O72: 0.12532 | P72: =R72*1.15 -> 0.18745 | Q72: 1 | R72: 0.163 | S72: 0.163 | T72: 0 | U72: 0 | V72: 0.0964 | W72: 0.0964 | X72: 0.050693988 | Y72: 0 | Z72: 0 | AA72: 120 | AB72: 1440
A73: Unsec Std - 1449 - 132 | B73: 12 | C73: sfy | D73: SFY | E73: 0.02 | F73: 0.0125 | G73: hybrid | H73: 2e-05 | I73: 0.15 | J73: 0.975 | K73: TRUE | L73: =T73*1.3 -> 0.05174 | M73: 0.05174 | N73: =V73*1.3 -> 0.054885792 | O73: 0.054885792 | P73: =R73*1.15 -> 0.2645 | Q73: 1 | R73: 0.23 | S73: 0.23 | T73: 0.0398 | U73: 0.0398 | V73: 0.04221984 | W73: 0.04221984 | X73: 0.058137248 | Y73: 0.034087798153406;0.029131872311023;0.029131872311023;0.025455429050157;0.025455429050157;0.024935476432192;0.024935476432192;0.0330338174243784;0.0330338174243784;0.052503321664899;0.0723270250344311;0.115968664711763 | Z73: 0.034087798153406;0.029131872311023;0.029131872311023;0.025455429050157;0.025455429050157;0.024935476432192;0.024935476432192;0.0330338174243784;0.0330338174243784;0.052503321664899;0.0723270250344311;0.115968664711763 | AA73: 132 | AB73: 1449
A74: Unsec Std - 1449 - 186 | B74: 6 | C74: sfy | D74: SFY | E74: 0.02 | F74: 0.0125 | G74: hybrid | H74: 2e-05 | I74: 0.15 | J74: 0.985 | K74: TRUE | L74: =T74*1.3 -> 0.04537 | M74: 0.04537 | N74: =V74*1.3 -> 0.048128496 | O74: 0.048128496 | P74: =R74*1.15 -> 0.2645 | Q74: 1 | R74: 0.23 | S74: 0.23 | T74: 0.0349 | U74: 0.0349 | V74: 0.03702192 | W74: 0.03702192 | X74: 0.086046951 | Y74: 0.0489849142849816;0.0428030164624041;0.0419287220074737;0.0555459909257746;0.0882837424238861;0.116654180496246 | Z74: 0.0489849142849816;0.0428030164624041;0.0419287220074737;0.0555459909257746;0.0882837424238861;0.116654180496246 | AA74: 186 | AB74: 1449
A75: Unsec Std - 1449 - 63 | B75: 3 | C75: sfy | D75: SFY | E75: 0.02 | F75: 0.0125 | G75: hybrid | H75: 2e-05 | I75: 0.15 | J75: 0.9975 | K75: TRUE | L75: =T75*1.3 -> 0.05434 | M75: 0.05434 | N75: =V75*1.3 -> 0.057643872 | O75: 0.057643872 | P75: =R75*1.15 -> 0.2645 | Q75: 1 | R75: 0.23 | S75: 0.23 | T75: 0.0418 | U75: 0.0418 | V75: 0.04434144 | W75: 0.04434144 | X75: 0.084518154 | Y75: 0.0436711592742046;0.051181123470062;0.0613711445667025 | Z75: 0.0436711592742046;0.051181123470062;0.0613711445667025 | AA75: 63 | AB75: 1449
A76: Unsec Std - 1490 - 120 | B76: 0 | C76: sfy | D76: BD | E76: 0.02 | F76: 0.0125 | G76: standard_bd | H76: 2e-05 | I76: 0.15 | J76: 0.9625 | K76: TRUE | L76: =T76*1.3 -> 0 | M76: 0 | N76: =V76*1.3 -> 0.12532 | O76: 0.12532 | P76: =R76*1.15 -> 0.18745 | Q76: 1 | R76: 0.163 | S76: 0.163 | T76: 0 | U76: 0 | V76: 0.0964 | W76: 0.0964 | X76: 0.075692744 | Y76: 0 | Z76: 0 | AA76: 120 | AB76: 1490
A77: Unsec Std - 399 - 60 | B77: 0 | C77: sfy | D77: SFY | E77: 0.02 | F77: 0.0125 | G77: standard | H77: 2e-05 | I77: 0.15 | J77: 0.9225 | K77: TRUE | L77: =T77*1.3 -> 0 | M77: 0 | N77: =V77*1.3 -> 0.0416 | O77: 0.0416 | P77: =R77*1.15 -> 0.115 | Q77: 1 | R77: 0.1 | S77: 0.1 | T77: 0 | U77: 0 | V77: 0.032 | W77: 0.032 | X77: 0.03029318 | Y77: 0 | Z77: 0 | AA77: 60 | AB77: 399
A78: Unsec Std - 399 - 84 | B78: 0 | C78: sfy | D78: SFY | E78: 0.02 | F78: 0.0125 | G78: standard | H78: 2e-05 | I78: 0.15 | J78: 0.9125 | K78: TRUE | L78: =T78*1.3 -> 0 | M78: 0 | N78: =V78*1.3 -> 0.0416 | O78: 0.0416 | P78: =R78*1.15 -> 0.115 | Q78: 1 | R78: 0.1 | S78: 0.1 | T78: 0 | U78: 0 | V78: 0.032 | W78: 0.032 | X78: 0.025515495 | Y78: 0 | Z78: 0 | AA78: 84 | AB78: 399
A79: Unsec Std - 649 - 132 | B79: 12 | C79: sfy | D79: SFY | E79: 0.02 | F79: 0.0125 | G79: hybrid | H79: 2e-05 | I79: 0.15 | J79: 0.975 | K79: TRUE | L79: =T79*1.3 -> 0.00754 | M79: 0.00754 | N79: =V79*1.3 -> 0.01398603 | O79: 0.01398603 | P79: =R79*1.15 -> 0.2645 | Q79: 1 | R79: 0.23 | S79: 0.23 | T79: 0.0058 | U79: 0.0058 | V79: 0.010758485 | W79: 0.010758485 | X79: 0.043008322 | Y79: 0.034087798153406;0.029131872311023;0.029131872311023;0.025455429050157;0.025455429050157;0.024935476432192;0.024935476432192;0.0330338174243784;0.0330338174243784;0.052503321664899;0.0723270250344311;0.115968664711763 | Z79: 0.034087798153406;0.029131872311023;0.029131872311023;0.025455429050157;0.025455429050157;0.024935476432192;0.024935476432192;0.0330338174243784;0.0330338174243784;0.052503321664899;0.0723270250344311;0.115968664711763 | AA79: 132 | AB79: 649
A80: Unsec Std - 649 - 186 | B80: 6 | C80: sfy | D80: SFY | E80: 0.02 | F80: 0.0125 | G80: hybrid | H80: 2e-05 | I80: 0.15 | J80: 0.985 | K80: TRUE | L80: =T80*1.3 -> 0.012253176 | M80: 0.012253176 | N80: =V80*1.3 -> 0.012253176 | O80: 0.012253176 | P80: =R80*1.15 -> 0.2645 | Q80: 1 | R80: 0.23 | S80: 0.23 | T80: 0.00942552 | U80: 0.00942552 | V80: 0.00942552 | W80: 0.00942552 | X80: 0.050167019 | Y80: 0.0489849142849816;0.0428030164624041;0.0419287220074737;0.0555459909257746;0.0882837424238861;0.116654180496246 | Z80: 0.0489849142849816;0.0428030164624041;0.0419287220074737;0.0555459909257746;0.0882837424238861;0.116654180496246 | AA80: 186 | AB80: 649
A81: Unsec Std - 699 / 186 | B81: 6 | C81: sfy | D81: SFY | E81: 0.02 | F81: 0.0125 | G81: hybrid | H81: 2e-05 | I81: 0.15 | J81: 0.985 | K81: TRUE | L81: =T81*1.3 -> 0.012253176 | M81: 0.012253176 | N81: =V81*1.3 -> 0.012253176 | O81: 0.012253176 | P81: =R81*1.15 -> 0.2645 | Q81: 1 | R81: 0.23 | S81: 0.23 | T81: 0.00942552 | U81: 0.00942552 | V81: 0.00942552 | W81: 0.00942552 | X81: 0.054046359 | Y81: 0.0489849142849816;0.0428030164624041;0.0419287220074737;0.0555459909257746;0.0882837424238861;0.116654180496246 | Z81: 0.0489849142849816;0.0428030164624041;0.0419287220074737;0.0555459909257746;0.0882837424238861;0.116654180496246 | AA81: 186 | AB81: 699
A82: Unsec Std - 749 - 186 | B82: 6 | C82: sfy | D82: SFY | E82: 0.02 | F82: 0.0125 | G82: hybrid | H82: 2e-05 | I82: 0.15 | J82: 0.985 | K82: TRUE | L82: =T82*1.3 -> 0.00689 | M82: 0.00689 | N82: =V82*1.3 -> 0.012253176 | O82: 0.012253176 | P82: =R82*1.15 -> 0.2645 | Q82: 1 | R82: 0.23 | S82: 0.23 | T82: 0.0053 | U82: 0.0053 | V82: 0.00942552 | W82: 0.00942552 | X82: 0.058692561 | Y82: 0.0489849142849816;0.0428030164624041;0.0419287220074737;0.0555459909257746;0.0882837424238861;0.116654180496246 | Z82: 0.0489849142849816;0.0428030164624041;0.0419287220074737;0.0555459909257746;0.0882837424238861;0.116654180496246 | AA82: 186 | AB82: 749
A83: Unsec Std - 849 - 120 | B83: 0 | C83: sfy | D83: SFY | E83: 0.02 | F83: 0.0125 | G83: standard | H83: 2e-05 | I83: 0.15 | J83: 0.975 | K83: TRUE | L83: =T83*1.3 -> 0 | M83: 0 | N83: =V83*1.3 -> 0.0416 | O83: 0.0416 | P83: =R83*1.15 -> 0.138 | Q83: 1 | R83: 0.12 | S83: 0.12 | T83: 0 | U83: 0 | V83: 0.032 | W83: 0.032 | X83: 0.064864091 | Y83: 0 | Z83: 0 | AA83: 120 | AB83: 849
A84: Unsec Std - 849 - 132 | B84: 12 | C84: sfy | D84: SFY | E84: 0.02 | F84: 0.0125 | G84: hybrid | H84: 2e-05 | I84: 0.15 | J84: 0.975 | K84: TRUE | L84: =T84*1.3 -> 0.01398603 | M84: 0.01398603 | N84: =V84*1.3 -> 0.01398603 | O84: 0.01398603 | P84: =R84*1.15 -> 0.2645 | Q84: 1 | R84: 0.23 | S84: 0.23 | T84: 0.010758485 | U84: 0.010758485 | V84: 0.010758485 | W84: 0.010758485 | X84: 0.052671865 | Y84: 0.034087798153406;0.029131872311023;0.029131872311023;0.025455429050157;0.025455429050157;0.024935476432192;0.024935476432192;0.0330338174243784;0.0330338174243784;0.052503321664899;0.0723270250344311;0.115968664711763 | Z84: 0.034087798153406;0.029131872311023;0.029131872311023;0.025455429050157;0.025455429050157;0.024935476432192;0.024935476432192;0.0330338174243784;0.0330338174243784;0.052503321664899;0.0723270250344311;0.115968664711763 | AA84: 132 | AB84: 849
A85: Unsec Std - 849 - 180 | B85: 0 | C85: sfy | D85: SFY | E85: 0.02 | F85: 0.0125 | G85: standard | H85: 2e-05 | I85: 0.15 | J85: 0.975 | K85: TRUE | L85: =T85*1.3 -> 0 | M85: 0 | N85: =V85*1.3 -> 0.0416 | O85: 0.0416 | P85: =R85*1.15 -> 0.138 | Q85: 1 | R85: 0.12 | S85: 0.12 | T85: 0 | U85: 0 | V85: 0.032 | W85: 0.032 | X85: 0.063424106 | Y85: 0 | Z85: 0 | AA85: 180 | AB85: 849
A86: Unsec Std - 849 - 63 | B86: 3 | C86: sfy | D86: SFY | E86: 0.02 | F86: 0.0125 | G86: hybrid | H86: 2e-05 | I86: 0.15 | J86: 0.9975 | K86: TRUE | L86: =T86*1.3 -> 0.0125392 | M86: 0.0125392 | N86: =V86*1.3 -> 0.0125392 | O86: 0.0125392 | P86: =R86*1.15 -> 0.2645 | Q86: 1 | R86: 0.23 | S86: 0.23 | T86: 0.0096455382 | U86: 0.0096455382 | V86: 0.0096455382 | W86: 0.0096455382 | X86: 0.065451837 | Y86: 0.0436711592742046;0.051181123470062;0.0613711445667025 | Z86: 0.0436711592742046;0.051181123470062;0.0613711445667025 | AA86: 63 | AB86: 849
A87: Unsec Std - 899 / 120 | B87: 0 | C87: sfy | D87: SFY | E87: 0.02 | F87: 0.0125 | G87: standard | H87: 2e-05 | I87: 0.15 | J87: 0.975 | K87: TRUE | L87: =T87*1.3 -> 0 | M87: 0 | N87: =V87*1.3 -> 0.0416 | O87: 0.0416 | P87: =R87*1.15 -> 0.138 | Q87: 1 | R87: 0.12 | S87: 0.12 | T87: 0 | U87: 0 | V87: 0.032 | W87: 0.032 | X87: 0.049643393 | Y87: 0 | Z87: 0 | AA87: 120 | AB87: 899
A88: Unsec Std - 899 / 132 | B88: 12 | C88: sfy | D88: SFY | E88: 0.02 | F88: 0.0125 | G88: hybrid | H88: 2e-05 | I88: 0.15 | J88: 0.975 | K88: TRUE | L88: =T88*1.3 -> 0.01398603 | M88: 0.01398603 | N88: =V88*1.3 -> 0.01398603 | O88: 0.01398603 | P88: =R88*1.15 -> 0.2645 | Q88: 1 | R88: 0.23 | S88: 0.23 | T88: 0.010758485 | U88: 0.010758485 | V88: 0.010758485 | W88: 0.010758485 | X88: 0.055514016 | Y88: 0.034087798153406;0.029131872311023;0.029131872311023;0.025455429050157;0.025455429050157;0.024935476432192;0.024935476432192;0.0330338174243784;0.0330338174243784;0.052503321664899;0.0723270250344311;0.115968664711763 | Z88: 0.034087798153406;0.029131872311023;0.029131872311023;0.025455429050157;0.025455429050157;0.024935476432192;0.024935476432192;0.0330338174243784;0.0330338174243784;0.052503321664899;0.0723270250344311;0.115968664711763 | AA88: 132 | AB88: 899
A89: Unsec Std - 899 / 180 | B89: 0 | C89: sfy | D89: SFY | E89: 0.02 | F89: 0.0125 | G89: standard | H89: 2e-05 | I89: 0.15 | J89: 0.975 | K89: TRUE | L89: =T89*1.3 -> 0 | M89: 0 | N89: =V89*1.3 -> 0.0416 | O89: 0.0416 | P89: =R89*1.15 -> 0.138 | Q89: 1 | R89: 0.12 | S89: 0.12 | T89: 0 | U89: 0 | V89: 0.032 | W89: 0.032 | X89: 0.048187666 | Y89: 0 | Z89: 0 | AA89: 180 | AB89: 899
A90: Unsec Std - 899 / 63 | B90: 3 | C90: sfy | D90: SFY | E90: 0.02 | F90: 0.0125 | G90: hybrid | H90: 2e-05 | I90: 0.15 | J90: 0.9975 | K90: TRUE | L90: =T90*1.3 -> 0.0125392 | M90: 0.0125392 | N90: =V90*1.3 -> 0.0125392 | O90: 0.0125392 | P90: =R90*1.15 -> 0.2645 | Q90: 1 | R90: 0.23 | S90: 0.23 | T90: 0.0096455382 | U90: 0.0096455382 | V90: 0.0096455382 | W90: 0.0096455382 | X90: 0.069668314 | Y90: 0.0436711592742046;0.051181123470062;0.0613711445667025 | Z90: 0.0436711592742046;0.051181123470062;0.0613711445667025 | AA90: 63 | AB90: 899
A91: Unsec Std - 949 - 120 | B91: 0 | C91: sfy | D91: SFY | E91: 0.02 | F91: 0.0125 | G91: standard | H91: 2e-05 | I91: 0.15 | J91: 0.975 | K91: TRUE | L91: =T91*1.3 -> 0 | M91: 0 | N91: =V91*1.3 -> 0.0416 | O91: 0.0416 | P91: =R91*1.15 -> 0.138 | Q91: 1 | R91: 0.12 | S91: 0.12 | T91: 0 | U91: 0 | V91: 0.032 | W91: 0.032 | X91: 0.074875194 | Y91: 0 | Z91: 0 | AA91: 120 | AB91: 949
A92: Unsec Std - 949 - 132 | B92: 12 | C92: sfy | D92: SFY | E92: 0.02 | F92: 0.0125 | G92: hybrid | H92: 2e-05 | I92: 0.15 | J92: 0.975 | K92: TRUE | L92: =T92*1.3 -> 0.00754 | M92: 0.00754 | N92: =V92*1.3 -> 0.01398603 | O92: 0.01398603 | P92: =R92*1.15 -> 0.2645 | Q92: 1 | R92: 0.23 | S92: 0.23 | T92: 0.0058 | U92: 0.0058 | V92: 0.010758485 | W92: 0.010758485 | X92: 0.06018172 | Y92: 0.034087798153406;0.029131872311023;0.029131872311023;0.025455429050157;0.025455429050157;0.024935476432192;0.024935476432192;0.0330338174243784;0.0330338174243784;0.052503321664899;0.0723270250344311;0.115968664711763 | Z92: 0.034087798153406;0.029131872311023;0.029131872311023;0.025455429050157;0.025455429050157;0.024935476432192;0.024935476432192;0.0330338174243784;0.0330338174243784;0.052503321664899;0.0723270250344311;0.115968664711763 | AA92: 132 | AB92: 949
A93: Unsec Std - 949 - 63 | B93: 3 | C93: sfy | D93: SFY | E93: 0.02 | F93: 0.0125 | G93: hybrid | H93: 2e-05 | I93: 0.15 | J93: 0.9975 | K93: TRUE | L93: =T93*1.3 -> 0.00676 | M93: 0.00676 | N93: =V93*1.3 -> 0.0125392 | O93: 0.0125392 | P93: =R93*1.15 -> 0.2645 | Q93: 1 | R93: 0.23 | S93: 0.23 | T93: 0.0052 | U93: 0.0052 | V93: 0.0096455382 | W93: 0.0096455382 | X93: 0.074458816 | Y93: 0.0436711592742046;0.051181123470062;0.0613711445667025 | Z93: 0.0436711592742046;0.051181123470062;0.0613711445667025 | AA93: 63 | AB93: 949
A94: Unsec Std - EPNI 36 Mo | B94: 36 | C94: sfy | D94: SFY | E94: 0.02 | F94: 0.0125 | G94: epni | H94: 2e-05 | I94: 0.15 | J94: 0.9125 | K94: TRUE | L94: =T94*1.3 -> 0 | M94: 0 | N94: =V94*1.3 -> 0.016569643 | O94: 0.016569643 | P94: =R94*1.15 -> 0.2461 | Q94: 1 | R94: 0.214 | S94: 0.214 | T94: 0 | U94: 0 | V94: 0.01274588 | W94: 0.01274588 | X94: 0.06469489 | Y94: 0 | Z94: 0 | AA94: 36 | AB94: 0
A95: Unsec Std - EPNI 60 Mo | B95: 60 | C95: sfy | D95: SFY | E95: 0.02 | F95: 0.0125 | G95: epni | H95: 2e-05 | I95: 0.15 | J95: 0.8775 | K95: TRUE | L95: =T95*1.3 -> 0 | M95: 0 | N95: =V95*1.3 -> 0.019882122 | O95: 0.019882122 | P95: =R95*1.15 -> 0.15985 | Q95: 1 | R95: 0.139 | S95: 0.139 | T95: 0 | U95: 0 | V95: 0.01529394 | W95: 0.01529394 | X95: 0.053756467 | Y95: 0 | Z95: 0 | AA95: 60 | AB95: 0
A96: NINP - 24 Mo - 1795 | B96: 24 | C96: sfy | D96: SFY | E96: 0.02 | F96: 0.0125 | G96: ninp | H96: 2e-05 | I96: 0.15 | J96: 0.9025 | K96: TRUE | L96: 0.02423907 | M96: 0.02423907 | N96: 0.02423907 | O96: 0.02423907 | P96: 0.42 | Q96: 1 | R96: 0.5 | S96: 0.5 | T96: 0.0080796899 | U96: 0.0080796899 | V96: 0.0080796899 | W96: 0.0080796899 | X96: 0 | Y96: 0.03026823033909381;0.035600135982233924;0.026489949813011334;0.027871365927849452;0.023758661217038617;0.02579220684816405;0.02122293126725122;0.02963254821613322;0.02956574553420408;0.030828750865728068;0.03816737063940657;0.03083240379326952;0.030895518718847242;0.028723292961372972;0.03267629733463203;0.021093038244786633;0.02773711623100624;0.03709754739997532;0.035807390962314;0.03580337130789098;0.036391389180009115;0.06385361902820341;0.08651239257215569;0.09697872561542253 | Z96: 0.03026823033909381;0.035600135982233924;0.026489949813011334;0.027871365927849452;0.023758661217038617;0.02579220684816405;0.02122293126725122;0.02963254821613322;0.02956574553420408;0.030828750865728068;0.03816737063940657;0.03083240379326952;0.030895518718847242;0.028723292961372972;0.03267629733463203;0.021093038244786633;0.02773711623100624;0.03709754739997532;0.035807390962314;0.03580337130789098;0.036391389180009115;0.06385361902820341;0.08651239257215569;0.09697872561542253 | AA96: 96 | AB96: 1795
A97: NINP - 18 Mo - 1599 | B97: 18 | C97: sfy | D97: SFY | E97: 0.02 | F97: 0.0125 | G97: ninp | H97: 2e-05 | I97: 0.15 | J97: 0.9225 | K97: TRUE | L97: 0.017 | M97: 0.017 | N97: 0.017 | O97: 0.017 | P97: 0.45 | Q97: 1 | R97: 0.5 | S97: 0.5 | T97: 0.0088277518 | U97: 0.0088277518 | V97: 0.0088277518 | W97: 0.0088277518 | X97: 0.041811669 | Y97: 0.039703346185265796;0.03635715882991378;0.03470970928411711;0.03548269171460937;0.037439795816501246;0.03973788749506501;0.034907694810767734;0.03588535592699753;0.040163946994567414;0.03618278424779669;0.04106291086725734;0.04379840670389578;0.0442750123745728;0.043314271123342955;0.048749252320648015;0.06360233170335709;0.11510571512637802;0.1943217284749463 | Z97: 0.039703346185265796;0.03635715882991378;0.03470970928411711;0.03548269171460937;0.037439795816501246;0.03973788749506501;0.034907694810767734;0.03588535592699753;0.040163946994567414;0.03618278424779669;0.04106291086725734;0.04379840670389578;0.0442750123745728;0.043314271123342955;0.048749252320648015;0.06360233170335709;0.11510571512637802;0.1943217284749463 | AA97: 84 | AB97: 1599

Sheet SFY-CPR
A1: Mth | B1: NINP3 | C1: NINP6 | D1: NINP12 | E1: NINP18 | F1: NINP24 | G1: NINP10 | H1: NINP14 | I1: NINP20 | J1: NINP4316 | K1: NINP4398 | L1: NINP4302 | M1: NINP4602 | N1: NINP4321 | O1: NINP4301 | P1: NINP4626 | Q1: NINP4332 | R1: NINP4312 | S1: NINP4632 | T1: NINP4612 | U1: NINP41232 | V1: NINP41207 | W1: NINP899/63 | X1: NINP1099/63 | Y1: NINP1199/63 | Z1: NINP1399/63 | AA1: NINP699/186 | AB1: NINP1099/186 | AC1: NINP1199/186 | AD1: NINP1399/186 | AE1: NINP899/132 | AF1: NINP1099/132 | AG1: NINP1199/132 | AH1: NINP1399/132 | AI1: NINP849-63 | AJ1: NINP1049-63 | AK1: NINP1149-63a | AL1: NINP1349-63 | AM1: NINP649-186 | AN1: NINP1049-186 | AO1: NINP1149-186a | AP1: NINP1349-186 | AQ1: NINP849-132 | AR1: NINP1049-132 | AS1: NINP1149-132a | AT1: NINP1349-132 | AU1: NINP949-63 | AV1: NINP1149-63 | AW1: NINP1249-63 | AX1: NINP1449-63 | AY1: NINP749-186 | AZ1: NINP1149-186 | BA1: NINP1249-186 | BB1: NINP1449-186 | BC1: NINP949-132 | BD1: NINP1149-132 | BE1: NINP1249-132 | BF1: NINP1449-132 | BG1: NINP649-132 | BH1: NINP1149-128 | BI1: NINP1349-128 | BJ1: NINP4396 | BK1: NINP4687 | BL1: NINP4213 | BM1: NINP4813 | BN1: NINP4013 | BO1: NINP4331 | BP1: NINP4337 | BQ1: NINP4342 | BR1: NINP4348 | BS1: NINP4355 | BT1: NINP4306 | BU1: NINP4313 | BV1: NINP4319 | BW1: NINP4325 | BX1: NINP4333 | BY1: NINP12n | BZ1: NINP18n | CA1: WP18n | CB1: WP24n | CC1: NINP849-183 | CD1: NINP1195-132 | CE1: WP6 | CF1: WP12 | CG1: WP18 | CH1: WP24 | CI1: WP10 | CJ1: WP14 | CK1: WP20
A2: 1 | B2: 0.33366367 | C2: 0.12881709 | D2: 0.06763335 | E2: 0.039703346 | F2: 0.03026823 | G2: 0.09 | H2: 0.045 | I2: 0.03 | J2: 0.050200338 | K2: 0.052132744 | L2: 0.028671159 | M2: 0.048984914 | N2: 0.045242224 | O2: 0.033671159 | P2: 0.067214363 | Q2: 0.047410486 | R2: 0.043671159 | S2: 0.067214363 | T2: 0.067214363 | U2: 0.047272958 | V2: 0.047272958 | W2: 0.043671159 | X2: 0.043671159 | Y2: 0.043671159 | Z2: 0.043671159 | AA2: 0.048984914 | AB2: 0.048984914 | AC2: 0.048984914 | AD2: 0.048984914 | AE2: 0.034087798 | AF2: 0.034087798 | AG2: 0.034087798 | AH2: 0.034087798 | AI2: 0.043671159 | AJ2: 0.043671159 | AK2: 0.043671159 | AL2: 0.043671159 | AM2: 0.048984914 | AN2: 0.048984914 | AO2: 0.048984914 | AP2: 0.048984914 | AQ2: 0.034087798 | AR2: 0.034087798 | AS2: 0.034087798 | AT2: 0.034087798 | AU2: 0.043671159 | AV2: 0.043671159 | AW2: 0.043671159 | AX2: 0.043671159 | AY2: 0.048984914 | AZ2: 0.048984914 | BA2: 0.048984914 | BB2: 0.048984914 | BC2: 0.034087798 | BD2: 0.034087798 | BE2: 0.034087798 | BF2: 0.034087798 | BG2: 0.034087798 | BH2: 0.051131697 | BI2: 0.051131697 | BJ2: 0.043671159 | BK2: 0.048984914 | BL2: 0.034087798 | BM2: 0.04 | BN2: 0.036 | BO2: 0.043671159 | BP2: 0.043671159 | BQ2: 0.043671159 | BR2: 0.043671159 | BS2: 0.043671159 | BT2: 0.043671159 | BU2: 0.043671159 | BV2: 0.043671159 | BW2: 0.043671159 | BX2: 0.043671159 | BY2: 0.064439053 | BZ2: 0.037828172 | CA2: 0.061498594 | CB2: 0.041451802 | CC2: 0.043671159 | CD2: 0.047272958 | CE2: 0.1895542 | CF2: 0.09742644 | CG2: 0.064594797 | CH2: 0.04353873 | CI2: 0.11 | CJ2: 0.057 | CK2: 0.055
A3: 2 | B3: 0.27123217 | C3: 0.10904923 | D3: 0.053375652 | E3: 0.036357159 | F3: 0.035600136 | G3: 0.06 | H3: 0.045 | I3: 0.03 | J3: 0.051770625 | K3: 0.053114819 | L3: 0.036181123 | M3: 0.042803016 | N3: 0.055332981 | O3: 0.041181123 | P3: 0.058731908 | Q3: 0.055563488 | R3: 0.051181123 | S3: 0.058731908 | T3: 0.058731908 | U3: 0.040400081 | V3: 0.040400081 | W3: 0.051181123 | X3: 0.051181123 | Y3: 0.051181123 | Z3: 0.051181123 | AA3: 0.042803016 | AB3: 0.042803016 | AC3: 0.042803016 | AD3: 0.042803016 | AE3: 0.029131872 | AF3: 0.029131872 | AG3: 0.029131872 | AH3: 0.029131872 | AI3: 0.051181123 | AJ3: 0.051181123 | AK3: 0.051181123 | AL3: 0.051181123 | AM3: 0.042803016 | AN3: 0.042803016 | AO3: 0.042803016 | AP3: 0.042803016 | AQ3: 0.029131872 | AR3: 0.029131872 | AS3: 0.029131872 | AT3: 0.029131872 | AU3: 0.051181123 | AV3: 0.051181123 | AW3: 0.051181123 | AX3: 0.051181123 | AY3: 0.042803016 | AZ3: 0.042803016 | BA3: 0.042803016 | BB3: 0.042803016 | BC3: 0.029131872 | BD3: 0.029131872 | BE3: 0.029131872 | BF3: 0.029131872 | BG3: 0.029131872 | BH3: 0.043697808 | BI3: 0.043697808 | BJ3: 0.051181123 | BK3: 0.042803016 | BL3: 0.029131872 | BM3: 0.04 | BN3: 0.036 | BO3: 0.051181123 | BP3: 0.051181123 | BQ3: 0.051181123 | BR3: 0.051181123 | BS3: 0.051181123 | BT3: 0.051181123 | BU3: 0.051181123 | BV3: 0.051181123 | BW3: 0.051181123 | BX3: 0.051181123 | BY3: 0.05085474 | BZ3: 0.034640024 | CA3: 0.043545474 | CB3: 0.028026264 | CC3: 0.051181123 | CD3: 0.040400081 | CE3: 0.12676458 | CF3: 0.067351181 | CG3: 0.045737811 | CH3: 0.029437272 | CI3: 0.07 | CJ3: 0.056 | CK3: 0.054
A4: 3 | B4: 0.37960416 | C4: 0.10644286 | D4: 0.053250045 | E4: 0.034709709 | F4: 0.02648995 | G4: 0.06 | H4: 0.045 | I4: 0.03 | J4: 0.067629037 | K4: 0.064352436 | L4: 0.046371145 | M4: 0.041928722 | N4: 0.069024794 | O4: 0.051371145 | P4: 0.05753225 | Q4: 0.066626026 | R4: 0.061371145 | S4: 0.05753225 | T4: 0.05753225 | U4: 0.040400081 | V4: 0.040400081 | W4: 0.061371145 | X4: 0.061371145 | Y4: 0.061371145 | Z4: 0.061371145 | AA4: 0.041928722 | AB4: 0.041928722 | AC4: 0.041928722 | AD4: 0.041928722 | AE4: 0.029131872 | AF4: 0.029131872 | AG4: 0.029131872 | AH4: 0.029131872 | AI4: 0.061371145 | AJ4: 0.061371145 | AK4: 0.061371145 | AL4: 0.061371145 | AM4: 0.041928722 | AN4: 0.041928722 | AO4: 0.041928722 | AP4: 0.041928722 | AQ4: 0.029131872 | AR4: 0.029131872 | AS4: 0.029131872 | AT4: 0.029131872 | AU4: 0.061371145 | AV4: 0.061371145 | AW4: 0.061371145 | AX4: 0.061371145 | AY4: 0.041928722 | AZ4: 0.041928722 | BA4: 0.041928722 | BB4: 0.041928722 | BC4: 0.029131872 | BD4: 0.029131872 | BE4: 0.029131872 | BF4: 0.029131872 | BG4: 0.029131872 | BH4: 0.043697808 | BI4: 0.043697808 | BJ4: 0.061371145 | BK4: 0.041928722 | BL4: 0.029131872 | BM4: 0.039 | BN4: 0.035 | BO4: 0.061371145 | BP4: 0.061371145 | BQ4: 0.061371145 | BR4: 0.061371145 | BS4: 0.061371145 | BT4: 0.061371145 | BU4: 0.061371145 | BV4: 0.061371145 | BW4: 0.061371145 | BX4: 0.061371145 | BY4: 0.050735066 | BZ4: 0.033070383 | CA4: 0.039774786 | CB4: 0.023879196 | CC4: 0.061371145 | CD4: 0.040400081 | CE4: 0.10935252 | CF4: 0.063170267 | CG4: 0.041777284 | CH4: 0.025081416 | CI4: 0.07 | CJ4: 0.056 | CK4: 0.048
A5: 4 | C5: 0.12017547 | D5: 0.054283117 | E5: 0.035482692 | F5: 0.027871366 | G5: 0.06 | H5: 0.045 | I5: 0.03 | M5: 0.055545991 | P5: 0.076217106 | S5: 0.076217106 | T5: 0.076217106 | U5: 0.035301589 | V5: 0.035301589 | AA5: 0.055545991 | AB5: 0.055545991 | AC5: 0.055545991 | AD5: 0.055545991 | AE5: 0.025455429 | AF5: 0.025455429 | AG5: 0.025455429 | AH5: 0.025455429 | AM5: 0.055545991 | AN5: 0.055545991 | AO5: 0.055545991 | AP5: 0.055545991 | AQ5: 0.025455429 | AR5: 0.025455429 | AS5: 0.025455429 | AT5: 0.025455429 | AY5: 0.055545991 | AZ5: 0.055545991 | BA5: 0.055545991 | BB5: 0.055545991 | BC5: 0.025455429 | BD5: 0.025455429 | BE5: 0.025455429 | BF5: 0.025455429 | BG5: 0.025455429 | BH5: 0.038183144 | BI5: 0.038183144 | BK5: 0.055545991 | BL5: 0.025455429 | BM5: 0.044 | BN5: 0.04 | BY5: 0.051719346 | BZ5: 0.033806858 | CA5: 0.038192667 | CB5: 0.024341818 | CD5: 0.035301589 | CE5: 0.12053361 | CF5: 0.060646889 | CG5: 0.040115511 | CH5: 0.025567329 | CI5: 0.07 | CJ5: 0.056 | CK5: 0.042
A6: 5 | C6: 0.1975722 | D6: 0.054772379 | E6: 0.037439796 | F6: 0.023758661 | G6: 0.06 | H6: 0.045 | I6: 0.03 | M6: 0.088283742 | P6: 0.12113802 | S6: 0.12113802 | T6: 0.12113802 | U6: 0.035301589 | V6: 0.035301589 | AA6: 0.088283742 | AB6: 0.088283742 | AC6: 0.088283742 | AD6: 0.088283742 | AE6: 0.025455429 | AF6: 0.025455429 | AG6: 0.025455429 | AH6: 0.025455429 | AM6: 0.088283742 | AN6: 0.088283742 | AO6: 0.088283742 | AP6: 0.088283742 | AQ6: 0.025455429 | AR6: 0.025455429 | AS6: 0.025455429 | AT6: 0.025455429 | AY6: 0.088283742 | AZ6: 0.088283742 | BA6: 0.088283742 | BB6: 0.088283742 | BC6: 0.025455429 | BD6: 0.025455429 | BE6: 0.025455429 | BF6: 0.025455429 | BG6: 0.025455429 | BH6: 0.038183144 | BI6: 0.038183144 | BK6: 0.088283742 | BL6: 0.025455429 | BM6: 0.05 | BN6: 0.04 | BY6: 0.0521855 | BZ6: 0.035671529 | CA6: 0.03689461 | CB6: 0.023940027 | CD6: 0.035301589 | CE6: 0.14001462 | CF6: 0.061915997 | CG6: 0.038752103 | CH6: 0.02514531 | CI6: 0.07 | CJ6: 0.056 | CK6: 0.032
A7: 6 | C7: 0.27934315 | D7: 0.054244757 | E7: 0.039737887 | F7: 0.025792207 | G7: 0.06 | H7: 0.045 | I7: 0.03 | M7: 0.11665418 | P7: 0.16006635 | S7: 0.16006635 | T7: 0.16006635 | U7: 0.034580519 | V7: 0.034580519 | AA7: 0.11665418 | AB7: 0.11665418 | AC7: 0.11665418 | AD7: 0.11665418 | AE7: 0.024935476 | AF7: 0.024935476 | AG7: 0.024935476 | AH7: 0.024935476 | AM7: 0.11665418 | AN7: 0.11665418 | AO7: 0.11665418 | AP7: 0.11665418 | AQ7: 0.024935476 | AR7: 0.024935476 | AS7: 0.024935476 | AT7: 0.024935476 | AY7: 0.11665418 | AZ7: 0.11665418 | BA7: 0.11665418 | BB7: 0.11665418 | BC7: 0.024935476 | BD7: 0.024935476 | BE7: 0.024935476 | BF7: 0.024935476 | BG7: 0.024935476 | BH7: 0.037403215 | BI7: 0.037403215 | BK7: 0.11665418 | BL7: 0.024935476 | BM7: 0.05 | BN7: 0.044 | BY7: 0.051682798 | BZ7: 0.037861082 | CA7: 0.036372926 | CB7: 0.024371182 | CD7: 0.034580519 | CE7: 0.18382748 | CF7: 0.060026785 | CG7: 0.038204154 | CH7: 0.025598171 | CI7: 0.07 | CJ7: 0.056 | CK7: 0.032
A8: 7 | D8: 0.056489571 | E8: 0.034907695 | F8: 0.021222931 | G8: 0.07 | H8: 0.045 | I8: 0.03 | U8: 0.034580519 | V8: 0.034580519 | AE8: 0.024935476 | AF8: 0.024935476 | AG8: 0.024935476 | AH8: 0.024935476 | AQ8: 0.024935476 | AR8: 0.024935476 | AS8: 0.024935476 | AT8: 0.024935476 | BC8: 0.024935476 | BD8: 0.024935476 | BE8: 0.024935476 | BF8: 0.024935476 | BG8: 0.024935476 | BH8: 0.037403215 | BI8: 0.037403215 | BL8: 0.024935476 | BM8: 0.06 | BN8: 0.044 | BY8: 0.05382159 | BZ8: 0.033259018 | CA8: 0.039268803 | CB8: 0.023149749 | CD8: 0.034580519 | CF8: 0.061692945 | CG8: 0.041245826 | CH8: 0.024315244 | CI8: 0.07 | CJ8: 0.056 | CK8: 0.032
A9: 8 | D9: 0.059411377 | E9: 0.035885356 | F9: 0.029632548 | G9: 0.08 | H9: 0.045 | I9: 0.03 | U9: 0.045811298 | V9: 0.045811298 | AE9: 0.033033817 | AF9: 0.033033817 | AG9: 0.033033817 | AH9: 0.033033817 | AQ9: 0.033033817 | AR9: 0.033033817 | AS9: 0.033033817 | AT9: 0.033033817 | BC9: 0.033033817 | BD9: 0.033033817 | BE9: 0.033033817 | BF9: 0.033033817 | BG9: 0.033033817 | BH9: 0.11596866 | BI9: 0.11596866 | BL9: 0.033033817 | BM9: 0.11 | BN9: 0.044 | BY9: 0.0566054 | BZ9: 0.034190504 | CA9: 0.038258358 | CB9: 0.022225741 | CD9: 0.045811298 | CF9: 0.063714385 | CG9: 0.04018451 | CH9: 0.023344716 | CI9: 0.08 | CJ9: 0.056 | CK9: 0.032
A10: 9 | D10: 0.066709985 | E10: 0.040163947 | F10: 0.029565746 | G10: 0.15 | H10: 0.045 | I10: 0.03 | U10: 0.045811298 | V10: 0.045811298 | AE10: 0.033033817 | AF10: 0.033033817 | AG10: 0.033033817 | AH10: 0.033033817 | AQ10: 0.033033817 | AR10: 0.033033817 | AS10: 0.033033817 | AT10: 0.033033817 | BC10: 0.033033817 | BD10: 0.033033817 | BE10: 0.033033817 | BF10: 0.033033817 | BG10: 0.033033817 | BL10: 0.033033817 | BN10: 0.06 | BY10: 0.063559298 | BZ10: 0.038267019 | CA10: 0.037784305 | CB10: 0.027951725 | CD10: 0.045811298 | CF10: 0.068177468 | CG10: 0.03968659 | CH10: 0.02935898 | CI10: 0.13 | CJ10: 0.057 | CK10: 0.032
A11: 10 | D11: 0.081659324 | E11: 0.036182784 | F11: 0.030828751 | G11: 0.23 | H11: 0.045 | I11: 0.03 | U11: 0.072811606 | V11: 0.072811606 | AE11: 0.052503322 | AF11: 0.052503322 | AG11: 0.052503322 | AH11: 0.052503322 | AQ11: 0.052503322 | AR11: 0.052503322 | AS11: 0.052503322 | AT11: 0.052503322 | BC11: 0.052503322 | BD11: 0.052503322 | BE11: 0.052503322 | BF11: 0.052503322 | BG11: 0.052503322 | BL11: 0.052503322 | BN11: 0.11 | BY11: 0.077802585 | BZ11: 0.034473885 | CA11: 0.039470383 | CB11: 0.024816806 | CD11: 0.072811606 | CF11: 0.085589652 | CG11: 0.041457555 | CH11: 0.02606623 | CI11: 0.16 | CJ11: 0.057 | CK11: 0.032
A12: 11 | D12: 0.14847544 | E12: 0.041062911 | F12: 0.038167371 | H12: 0.05 | I12: 0.03 | U12: 0.10030312 | V12: 0.10030312 | AE12: 0.072327025 | AF12: 0.072327025 | AG12: 0.072327025 | AH12: 0.072327025 | AQ12: 0.072327025 | AR12: 0.072327025 | AS12: 0.072327025 | AT12: 0.072327025 | BC12: 0.072327025 | BD12: 0.072327025 | BE12: 0.072327025 | BF12: 0.072327025 | BG12: 0.072327025 | BL12: 0.072327025 | BY12: 0.141463 | BZ12: 0.039123525 | CA12: 0.040068104 | CB12: 0.023766885 | CD12: 0.10030312 | CF12: 0.12657167 | CG12: 0.042085369 | CH12: 0.024963451 | CJ12: 0.057 | CK12: 0.032
A13: 12 | D13: 0.220095 | E13: 0.043798407 | F13: 0.030832404 | H13: 0.07 | I13: 0.03 | U13: 0.16082534 | V13: 0.16082534 | AE13: 0.11596866 | AF13: 0.11596866 | AG13: 0.11596866 | AH13: 0.11596866 | AQ13: 0.11596866 | AR13: 0.11596866 | AS13: 0.11596866 | AT13: 0.11596866 | BC13: 0.11596866 | BD13: 0.11596866 | BE13: 0.11596866 | BF13: 0.11596866 | BG13: 0.11596866 | BL13: 0.11596866 | BY13: 0.2097 | BZ13: 0.041729825 | CA13: 0.039653623 | CB13: 0.027194926 | CD13: 0.16082534 | CF13: 0.15501632 | CG13: 0.041650021 | CH13: 0.028564079 | CJ13: 0.058 | CK13: 0.032
A14: 13 | E14: 0.044275012 | F14: 0.030895519 | H14: 0.13 | I14: 0.03 | BZ14: 0.04218392 | CA14: 0.041587882 | CB14: 0.027466483 | CG14: 0.043681662 | CH14: 0.028849308 | CJ14: 0.098 | CK14: 0.032
A15: 14 | E15: 0.043314271 | F15: 0.028723293 | H15: 0.2 | I15: 0.03 | BZ15: 0.041268555 | CA15: 0.043048771 | CB15: 0.027301686 | CG15: 0.0452161 | CH15: 0.028676214 | CJ15: 0.125 | CK15: 0.032
A16: 15 | E16: 0.048749252 | F16: 0.032676297 | I16: 0.03 | BZ16: 0.046446844 | CA16: 0.049761672 | CB16: 0.029818524 | CG16: 0.052266969 | CH16: 0.031319764 | CK16: 0.032
A17: 16 | E17: 0.063602332 | F17: 0.021093038 | I17: 0.03 | BZ17: 0.060598418 | CA17: 0.061216191 | CB17: 0.027664467 | CG17: 0.064298175 | CH17: 0.02905726 | CK17: 0.032
A18: 17 | E18: 0.11510572 | F18: 0.027737116 | I18: 0.03 | BZ18: 0.10966932 | CA18: 0.099021288 | CB18: 0.027989778 | CG18: 0.10400661 | CH18: 0.029398949 | CK18: 0.032
A19: 18 | E19: 0.19432173 | F19: 0.037097547 | I19: 0.04 | BZ19: 0.18514399 | CA19: 0.12380584 | CB19: 0.029991663 | CG19: 0.13003896 | CH19: 0.031501621 | CK19: 0.067
A20: 19 | F20: 0.035807391 | I20: 0.14 | CB20: 0.036818572 | CH20: 0.038672236 | CK20: 0.098
A21: 20 | F21: 0.035803371 | I21: 0.19 | CB21: 0.04447365 | CH21: 0.046712716 | CK21: 0.125
A22: 21 | F22: 0.036391389 | CB22: 0.045817756 | CH22: 0.048124493
A23: 22 | F23: 0.063853619 | CB23: 0.066279674 | CH23: 0.069616584
A24: 23 | F24: 0.086512393 | CB24: 0.097478301 | CH24: 0.10238593
A25: 24 | F25: 0.096978726 | CB25: 0.12462941 | CH25: 0.13090399
B26: =_xlfn.CONCAT(B2,";",B3,";",B4,IF(ISBLANK(B5),"",";"),B5,IF(ISBLANK(B6),"",";"),B6,IF(ISBLANK(B7),"",";"),B7,IF(ISBLANK(B8),"",";"),B8,IF(ISBLANK(B9),"",";"),B9,IF(ISBLANK(B10),"",";"),B10,IF(ISBLANK(B11),"",";"),B11,IF(ISBLANK(B12),"",";"),B12,IF(ISBLANK(B13),"",";"),B13,IF(ISBLANK(B14),"",";"),B14,IF(ISBLANK(B15),"",";"),B15,IF(ISBLANK(B16),"",";"),B16,IF(ISBLANK(B17),"",";"),B17,IF(ISBLANK(B18),"",";"),B18,IF(ISBLANK(B19),"",";"),B19,IF(ISBLANK(B20),"",";"),B20,IF(ISBLANK(B21),"",";"),B21,IF(ISBLANK(B22),"",";"),B22,IF(ISBLANK(B23),"",";"),B23,IF(ISBLANK(B24),"",";"),B24,IF(ISBLANK(B25),"",";"),B25) -> 0.333663669422478;0.27123217065051;0.379604159927013 | C26: =_xlfn.CONCAT(C2,";",C3,";",C4,IF(ISBLANK(C5),"",";"),C5,IF(ISBLANK(C6),"",";"),C6,IF(ISBLANK(C7),"",";"),C7,IF(ISBLANK(C8),"",";"),C8,IF(ISBLANK(C9),"",";"),C9,IF(ISBLANK(C10),"",";"),C10,IF(ISBLANK(C11),"",";"),C11,IF(ISBLANK(C12),"",";"),C12,IF(ISBLANK(C13),"",";"),C13,IF(ISBLANK(C14),"",";"),C14,IF(ISBLANK(C15),"",";"),C15,IF(ISBLANK(C16),"",";"),C16,IF(ISBLANK(C17),"",";"),C17,IF(ISBLANK(C18),"",";"),C18,IF(ISBLANK(C19),"",";"),C19,IF(ISBLANK(C20),"",";"),C20,IF(ISBLANK(C21),"",";"),C21,IF(ISBLANK(C22),"",";"),C22,IF(ISBLANK(C23),"",";"),C23,IF(ISBLANK(C24),"",";"),C24,IF(ISBLANK(C25),"",";"),C25) -> 0.128817089271534;0.10904922611393;0.106442864313677;0.120175472098005;0.197572195306553;0.279343152896301 | D26: =_xlfn.CONCAT(D2,";",D3,";",D4,IF(ISBLANK(D5),"",";"),D5,IF(ISBLANK(D6),"",";"),D6,IF(ISBLANK(D7),"",";"),D7,IF(ISBLANK(D8),"",";"),D8,IF(ISBLANK(D9),"",";"),D9,IF(ISBLANK(D10),"",";"),D10,IF(ISBLANK(D11),"",";"),D11,IF(ISBLANK(D12),"",";"),D12,IF(ISBLANK(D13),"",";"),D13,IF(ISBLANK(D14),"",";"),D14,IF(ISBLANK(D15),"",";"),D15,IF(ISBLANK(D16),"",";"),D16,IF(ISBLANK(D17),"",";"),D17,IF(ISBLANK(D18),"",";"),D18,IF(ISBLANK(D19),"",";"),D19,IF(ISBLANK(D20),"",";"),D20,IF(ISBLANK(D21),"",";"),D21,IF(ISBLANK(D22),"",";"),D22,IF(ISBLANK(D23),"",";"),D23,IF(ISBLANK(D24),"",";"),D24,IF(ISBLANK(D25),"",";"),D25) -> 0.0676333498793084;0.0533756521010278;0.0532500454780047;0.0542831166094344;0.0547723788788143;0.0542447568131707;0.0564895709616642;0.0594113771367509;0.0667099854605115;0.0816593237270766;0.148475440070047;0.22009500288419 | E26: =_xlfn.CONCAT(E2,";",E3,";",E4,IF(ISBLANK(E5),"",";"),E5,IF(ISBLANK(E6),"",";"),E6,IF(ISBLANK(E7),"",";"),E7,IF(ISBLANK(E8),"",";"),E8,IF(ISBLANK(E9),"",";"),E9,IF(ISBLANK(E10),"",";"),E10,IF(ISBLANK(E11),"",";"),E11,IF(ISBLANK(E12),"",";"),E12,IF(ISBLANK(E13),"",";"),E13,IF(ISBLANK(E14),"",";"),E14,IF(ISBLANK(E15),"",";"),E15,IF(ISBLANK(E16),"",";"),E16,IF(ISBLANK(E17),"",";"),E17,IF(ISBLANK(E18),"",";"),E18,IF(ISBLANK(E19),"",";"),E19,IF(ISBLANK(E20),"",";"),E20,IF(ISBLANK(E21),"",";"),E21,IF(ISBLANK(E22),"",";"),E22,IF(ISBLANK(E23),"",";"),E23,IF(ISBLANK(E24),"",";"),E24,IF(ISBLANK(E25),"",";"),E25) -> 0.0397033461852658;0.0363571588299138;0.0347097092841171;0.0354826917146094;0.0374397958165012;0.039737887495065;0.0349076948107677;0.0358853559269975;0.0401639469945674;0.0361827842477967;0.0410629108672573;0.0437984067038958;0.0442750123745728;0.043314271123343;0.048749252320648;0.0636023317033571;0.115105715126378;0.194321728474946 | F26: =_xlfn.CONCAT(F2,";",F3,";",F4,IF(ISBLANK(F5),"",";"),F5,IF(ISBLANK(F6),"",";"),F6,IF(ISBLANK(F7),"",";"),F7,IF(ISBLANK(F8),"",";"),F8,IF(ISBLANK(F9),"",";"),F9,IF(ISBLANK(F10),"",";"),F10,IF(ISBLANK(F11),"",";"),F11,IF(ISBLANK(F12),"",";"),F12,IF(ISBLANK(F13),"",";"),F13,IF(ISBLANK(F14),"",";"),F14,IF(ISBLANK(F15),"",";"),F15,IF(ISBLANK(F16),"",";"),F16,IF(ISBLANK(F17),"",";"),F17,IF(ISBLANK(F18),"",";"),F18,IF(ISBLANK(F19),"",";"),F19,IF(ISBLANK(F20),"",";"),F20,IF(ISBLANK(F21),"",";"),F21,IF(ISBLANK(F22),"",";"),F22,IF(ISBLANK(F23),"",";"),F23,IF(ISBLANK(F24),"",";"),F24,IF(ISBLANK(F25),"",";"),F25) -> 0.0302682303390938;0.0356001359822339;0.0264899498130113;0.0278713659278495;0.0237586612170386;0.0257922068481641;0.0212229312672512;0.0296325482161332;0.0295657455342041;0.0308287508657281;0.0381673706394066;0.0308324037932695;0.0308955187188472;0.028723292961373;0.032676297334632;0.0210930382447866;0.0277371162310062;0.0370975473999753;0.035807390962314;0.035803371307891;0.0363913891800091;0.0638536190282034;0.0865123925721557;0.0969787256154225 | G26: =_xlfn.CONCAT(G2,";",G3,";",G4,IF(ISBLANK(G5),"",";"),G5,IF(ISBLANK(G6),"",";"),G6,IF(ISBLANK(G7),"",";"),G7,IF(ISBLANK(G8),"",";"),G8,IF(ISBLANK(G9),"",";"),G9,IF(ISBLANK(G10),"",";"),G10,IF(ISBLANK(G11),"",";"),G11,IF(ISBLANK(G12),"",";"),G12,IF(ISBLANK(G13),"",";"),G13,IF(ISBLANK(G14),"",";"),G14,IF(ISBLANK(G15),"",";"),G15,IF(ISBLANK(G16),"",";"),G16,IF(ISBLANK(G17),"",";"),G17,IF(ISBLANK(G18),"",";"),G18,IF(ISBLANK(G19),"",";"),G19,IF(ISBLANK(G20),"",";"),G20,IF(ISBLANK(G21),"",";"),G21,IF(ISBLANK(G22),"",";"),G22,IF(ISBLANK(G23),"",";"),G23,IF(ISBLANK(G24),"",";"),G24,IF(ISBLANK(G25),"",";"),G25) -> 0.09;0.06;0.06;0.06;0.06;0.06;0.07;0.08;0.15;0.23 | H26: =_xlfn.CONCAT(H2,";",H3,";",H4,IF(ISBLANK(H5),"",";"),H5,IF(ISBLANK(H6),"",";"),H6,IF(ISBLANK(H7),"",";"),H7,IF(ISBLANK(H8),"",";"),H8,IF(ISBLANK(H9),"",";"),H9,IF(ISBLANK(H10),"",";"),H10,IF(ISBLANK(H11),"",";"),H11,IF(ISBLANK(H12),"",";"),H12,IF(ISBLANK(H13),"",";"),H13,IF(ISBLANK(H14),"",";"),H14,IF(ISBLANK(H15),"",";"),H15,IF(ISBLANK(H16),"",";"),H16,IF(ISBLANK(H17),"",";"),H17,IF(ISBLANK(H18),"",";"),H18,IF(ISBLANK(H19),"",";"),H19,IF(ISBLANK(H20),"",";"),H20,IF(ISBLANK(H21),"",";"),H21,IF(ISBLANK(H22),"",";"),H22,IF(ISBLANK(H23),"",";"),H23,IF(ISBLANK(H24),"",";"),H24,IF(ISBLANK(H25),"",";"),H25) -> 0.045;0.045;0.045;0.045;0.045;0.045;0.045;0.045;0.045;0.045;0.05;0.07;0.13;0.2 | I26: =_xlfn.CONCAT(I2,";",I3,";",I4,IF(ISBLANK(I5),"",";"),I5,IF(ISBLANK(I6),"",";"),I6,IF(ISBLANK(I7),"",";"),I7,IF(ISBLANK(I8),"",";"),I8,IF(ISBLANK(I9),"",";"),I9,IF(ISBLANK(I10),"",";"),I10,IF(ISBLANK(I11),"",";"),I11,IF(ISBLANK(I12),"",";"),I12,IF(ISBLANK(I13),"",";"),I13,IF(ISBLANK(I14),"",";"),I14,IF(ISBLANK(I15),"",";"),I15,IF(ISBLANK(I16),"",";"),I16,IF(ISBLANK(I17),"",";"),I17,IF(ISBLANK(I18),"",";"),I18,IF(ISBLANK(I19),"",";"),I19,IF(ISBLANK(I20),"",";"),I20,IF(ISBLANK(I21),"",";"),I21,IF(ISBLANK(I22),"",";"),I22,IF(ISBLANK(I23),"",";"),I23,IF(ISBLANK(I24),"",";"),I24,IF(ISBLANK(I25),"",";"),I25) -> 0.03;0.03;0.03;0.03;0.03;0.03;0.03;0.03;0.03;0.03;0.03;0.03;0.03;0.03;0.03;0.03;0.03;0.04;0.14;0.19 | ... CK26: =_xlfn.CONCAT(CK2,";",CK3,";",CK4,IF(ISBLANK(CK5),"",";"),CK5,IF(ISBLANK(CK6),"",";"),CK6,IF(ISBLANK(CK7),"",";"),CK7,IF(ISBLANK(CK8),"",";"),CK8,IF(ISBLANK(CK9),"",";"),CK9,IF(ISBLANK(CK10),"",";"),CK10,IF(ISBLANK(CK11),"",";"),CK11,IF(ISBLANK(CK12),"",";"),CK12,IF(ISBLANK(CK13),"",";"),CK13,IF(ISBLANK(CK14),"",";"),CK14,IF(ISBLANK(CK15),"",";"),CK15,IF(ISBLANK(CK16),"",";"),CK16,IF(ISBLANK(CK17),"",";"),CK17,IF(ISBLANK(CK18),"",";"),CK18,IF(ISBLANK(CK19),"",";"),CK19,IF(ISBLANK(CK20),"",";"),CK20,IF(ISBLANK(CK21),"",";"),CK21,IF(ISBLANK(CK22),"",";"),CK22,IF(ISBLANK(CK23),"",";"),CK23,IF(ISBLANK(CK24),"",";"),CK24,IF(ISBLANK(CK25),"",";"),CK25) -> 0.055;0.054;0.048;0.042;0.032;0.032;0.032;0.032;0.032;0.032;0.032;0.032;0.032;0.032;0.032;0.032;0.032;0.067;0.098;0.125

Sheet SFC-Models-SFY
A1: Loan Product Variables | C1: Term of Loan in Mths (total) | D1: Avg Loan Size $'s | E1: Loan Interest Rate | F1: CDR - Promotion Period Only | G1: Constant Prepay Rate | H1: Servicing Fees | I1: Late Fees% UPB/Mth | J1: Default Recovery % | K1: Promotional Period Term | L1: Promo Period Prepayment | M1: SFC Selling Price | N1: SFC Loan Margin | O1: SFC Purchase Price | P1: Merchant Discount | Q1: CDR No Promo or Post Promo | R1: Single Pool Net Loan Yield
A2: NINP899/63 | B2: Unsec Std - 899 / 63 | C2: 63 | D2: 9084.7488 | E2: 0.0899 | F2: 0.0096455382 | G2: 0.23 | H2: 0 | I2: 2e-05 | J2: 0.15 | K2: 3 | L2: 0.15622343 | M2: 0.9975 | N2: 0.0125 | O2: 0.985 | P2: 0.015 | Q2: 0.0096455382 | R2: 0.069668314 | S2: =HLOOKUP(A2,'SFY-CPR'!$B$1:$CK$26,26,FALSE) -> 0.0436711592742046;0.051181123470062;0.0613711445667025
A3: NINP1099/63 | B3: Unsec Std - 1099 / 63 | C3: 63 | D3: 9084.7488 | E3: 0.1099 | F3: 0.02287584 | G3: 0.23 | H3: 0 | I3: 2e-05 | J3: 0.15 | K3: 3 | L3: 0.15622343 | M3: 0.9975 | N3: 0.0125 | O3: 0.985 | P3: 0.015 | Q3: 0.02287584 | R3: 0.074645872 | S3: =HLOOKUP(A3,'SFY-CPR'!$B$1:$CK$26,26,FALSE) -> 0.0436711592742046;0.051181123470062;0.0613711445667025
A4: NINP1199/63 | B4: Unsec Std - 1199 / 63 | C4: 63 | D4: 9084.7488 | E4: 0.1199 | F4: 0.020982 | G4: 0.23 | H4: 0 | I4: 2e-05 | J4: 0.15 | K4: 3 | L4: 0.15622343 | M4: 0.9975 | N4: 0.0125 | O4: 0.985 | P4: 0.015 | Q4: 0.020982 | R4: 0.084693796 | S4: =HLOOKUP(A4,'SFY-CPR'!$B$1:$CK$26,26,FALSE) -> 0.0436711592742046;0.051181123470062;0.0613711445667025
A5: NINP1399/63 | B5: Unsec Std - 1399 / 63 | C5: 63 | D5: 9084.7488 | E5: 0.1399 | F5: 0.04434144 | G5: 0.23 | H5: 0 | I5: 2e-05 | J5: 0.15 | K5: 3 | L5: 0.15622343 | M5: 0.9975 | N5: 0.0125 | O5: 0.985 | P5: 0.015 | Q5: 0.04434144 | R5: 0.080055138 | S5: =HLOOKUP(A5,'SFY-CPR'!$B$1:$CK$26,26,FALSE) -> 0.0436711592742046;0.051181123470062;0.0613711445667025
A6: NINP699/186 | B6: Unsec Std - 699 / 186 | C6: 186 | D6: 9084.7488 | E6: 0.0699 | F6: 0.00942552 | G6: 0.23 | H6: 0 | I6: 2e-05 | J6: 0.15 | K6: 6 | L6: 0.39420057 | M6: 0.985 | N6: 0.0125 | O6: 0.9725 | P6: 0.0275 | Q6: 0.00942552 | R6: 0.054046359 | S6: =HLOOKUP(A6,'SFY-CPR'!$B$1:$CK$26,26,FALSE) -> 0.0489849142849816;0.0428030164624041;0.0419287220074737;0.0555459909257746;0.0882837424238861;0.116654180496246
A7: NINP1099/186 | B7: Unsec Std - 1099 / 186 | C7: 186 | D7: 9084.7488 | E7: 0.1099 | F7: 0.01818804 | G7: 0.23 | H7: 0 | I7: 2e-05 | J7: 0.15 | K7: 6 | L7: 0.39420057 | M7: 0.985 | N7: 0.0125 | O7: 0.9725 | P7: 0.0275 | Q7: 0.01818804 | R7: 0.076803138 | S7: =HLOOKUP(A7,'SFY-CPR'!$B$1:$CK$26,26,FALSE) -> 0.0489849142849816;0.0428030164624041;0.0419287220074737;0.0555459909257746;0.0882837424238861;0.116654180496246
A8: NINP1199/186 | B8: Unsec Std - 1199 / 186 | C8: 186 | D8: 9084.7488 | E8: 0.1199 | F8: 0.0171288 | G8: 0.23 | H8: 0 | I8: 2e-05 | J8: 0.15 | K8: 6 | L8: 0.39420057 | M8: 0.985 | N8: 0.0125 | O8: 0.9725 | P8: 0.0275 | Q8: 0.0171288 | R8: 0.0852633 | S8: =HLOOKUP(A8,'SFY-CPR'!$B$1:$CK$26,26,FALSE) -> 0.0489849142849816;0.0428030164624041;0.0419287220074737;0.0555459909257746;0.0882837424238861;0.116654180496246
A9: NINP1399/186 | B9: Unsec Std - 1399 / 186 | C9: 186 | D9: 9084.7488 | E9: 0.1399 | F9: 0.03702192 | G9: 0.23 | H9: 0 | I9: 2e-05 | J9: 0.15 | K9: 6 | L9: 0.39420057 | M9: 0.985 | N9: 0.0125 | O9: 0.9725 | P9: 0.0275 | Q9: 0.03702192 | R9: 0.081951748 | S9: =HLOOKUP(A9,'SFY-CPR'!$B$1:$CK$26,26,FALSE) -> 0.0489849142849816;0.0428030164624041;0.0419287220074737;0.0555459909257746;0.0882837424238861;0.116654180496246
A10: NINP899/132 | B10: Unsec Std - 899 / 132 | C10: 132 | D10: 9084.7488 | E10: 0.0899 | F10: 0.010758485 | G10: 0.23 | H10: 0 | I10: 2e-05 | J10: 0.15 | K10: 12 | L10: 0.5 | M10: 0.975 | N10: 0.0125 | O10: 0.9625 | P10: 0.0375 | Q10: 0.010758485 | R10: 0.055514016 | S10: =HLOOKUP(A10,'SFY-CPR'!$B$1:$CK$26,26,FALSE) -> 0.034087798153406;0.029131872311023;0.029131872311023;0.025455429050157;0.025455429050157;0.024935476432192;0.024935476432192;0.0330338174243784;0.0330338174243784;0.052503321664899;0.0723270250344311;0.115968664711763
A11: NINP1099/132 | B11: Unsec Std - 1099 / 132 | C11: 132 | D11: 9084.7488 | E11: 0.1099 | F11: 0.02111616 | G11: 0.23 | H11: 0 | I11: 2e-05 | J11: 0.15 | K11: 12 | L11: 0.5 | M11: 0.975 | N11: 0.0125 | O11: 0.9625 | P11: 0.0375 | Q11: 0.02111616 | R11: 0.057446902 | S11: =HLOOKUP(A11,'SFY-CPR'!$B$1:$CK$26,26,FALSE) -> 0.034087798153406;0.029131872311023;0.029131872311023;0.025455429050157;0.025455429050157;0.024935476432192;0.024935476432192;0.0330338174243784;0.0330338174243784;0.052503321664899;0.0723270250344311;0.115968664711763
A12: NINP1199/132 | B12: Unsec Std - 1199 / 132 | C12: 132 | D12: 9084.7488 | E12: 0.1199 | F12: 0.02067 | G12: 0.23 | H12: 0 | I12: 2e-05 | J12: 0.15 | K12: 12 | L12: 0.5 | M12: 0.975 | N12: 0.0125 | O12: 0.9625 | P12: 0.0375 | Q12: 0.02067 | R12: 0.063387707 | S12: =HLOOKUP(A12,'SFY-CPR'!$B$1:$CK$26,26,FALSE) -> 0.034087798153406;0.029131872311023;0.029131872311023;0.025455429050157;0.025455429050157;0.024935476432192;0.024935476432192;0.0330338174243784;0.0330338174243784;0.052503321664899;0.0723270250344311;0.115968664711763
A13: NINP1399/132 | B13: Unsec Std - 1399 / 132 | C13: 132 | D13: 9084.7488 | E13: 0.1399 | F13: 0.04221984 | G13: 0.23 | H13: 0 | I13: 2e-05 | J13: 0.15 | K13: 12 | L13: 0.5 | M13: 0.975 | N13: 0.0125 | O13: 0.9625 | P13: 0.0375 | Q13: 0.04221984 | R13: 0.05451089 | S13: =HLOOKUP(A13,'SFY-CPR'!$B$1:$CK$26,26,FALSE) -> 0.034087798153406;0.029131872311023;0.029131872311023;0.025455429050157;0.025455429050157;0.024935476432192;0.024935476432192;0.0330338174243784;0.0330338174243784;0.052503321664899;0.0723270250344311;0.115968664711763
A14: 899/120 | B14: Unsec Std - 899 / 120 | C14: 120 | D14: 10000 | E14: 0.0899 | G14: 0.12 | H14: 0.02 | I14: 2e-05 | J14: 0.15 | M14: 0.975 | N14: 0.0125 | O14: 0.9625 | P14: 0.0375 | Q14: 0.032 | R14: 0.049643393 | S14: =HLOOKUP(A14,'SFY-CPR'!$B$1:$CK$26,26,FALSE) -> #N/A
A15: 899/180 | B15: Unsec Std - 899 / 180 | C15: 180 | D15: 10000 | E15: 0.0899 | G15: 0.12 | H15: 0.02 | I15: 2e-05 | J15: 0.15 | M15: 0.975 | N15: 0.0125 | O15: 0.9625 | P15: 0.0375 | Q15: 0.032 | R15: 0.048187666 | S15: =HLOOKUP(A15,'SFY-CPR'!$B$1:$CK$26,26,FALSE) -> #N/A
A16: 399-60 | B16: Unsec Std - 399 - 60 | C16: 60 | D16: 10000 | E16: 0.0399 | G16: 0.1 | H16: 0.02 | I16: 2e-05 | J16: 0.15 | M16: 0.9225 | N16: 0.0125 | O16: 0.91 | P16: 0.09 | Q16: 0.032 | R16: 0.03029318 | S16: =HLOOKUP(A16,'SFY-CPR'!$B$1:$CK$26,26,FALSE) -> #N/A
A17: 399-84 | B17: Unsec Std - 399 - 84 | C17: 84 | D17: 10000 | E17: 0.0399 | G17: 0.1 | H17: 0.02 | I17: 2e-05 | J17: 0.15 | M17: 0.9125 | N17: 0.0125 | O17: 0.9 | P17: 0.1 | Q17: 0.032 | R17: 0.025515495 | S17: =HLOOKUP(A17,'SFY-CPR'!$B$1:$CK$26,26,FALSE) -> #N/A
A18: 1440-120 | B18: Unsec Std - 1440 - 120 | C18: 120 | D18: 10000 | E18: 0.144 | G18: 0.163 | H18: 0.02 | I18: 2e-05 | J18: 0.15 | M18: 0.9625 | N18: 0.0125 | O18: 0.95 | P18: 0.05 | Q18: 0.0964 | R18: 0.050693988 | S18: =HLOOKUP(A18,'SFY-CPR'!$B$1:$CK$26,26,FALSE) -> #N/A
A19: 6MBD | B19: 6 Mth BD WPDI | C19: 61 | D19: 5719 | E19: 0.2147 | F19: 0.0964 | G19: 0.2345 | H19: 0.02 | I19: 2e-05 | J19: 0.15 | K19: 6 | L19: 0.2948 | M19: 0.9135 | N19: 0.0125 | O19: 0.901 | P19: 0.099 | Q19: 0.0964 | R19: 0.1578011 | S19: =HLOOKUP(A19,'SFY-CPR'!$B$1:$CK$26,26,FALSE) -> #N/A
A20: 12MBD | B20: 6 Mth BD WPDI 12S | C20: 63 | D20: 6630 | E20: 0.2187 | F20: 0.0964 | G20: 0.239 | H20: 0.02 | I20: 2e-05 | J20: 0.15 | K20: 12 | L20: 0.473 | M20: 0.9135 | N20: 0.0125 | O20: 0.901 | P20: 0.099 | Q20: 0.0964 | R20: 0.12729977 | S20: =HLOOKUP(A20,'SFY-CPR'!$B$1:$CK$26,26,FALSE) -> #N/A
A21: 849-120 | B21: Unsec Std - 849 - 120 | C21: 120 | D21: 10000 | E21: 0.0849 | G21: 0.12 | H21: 0 | I21: 2e-05 | J21: 0.15 | M21: 0.975 | N21: 0.0125 | O21: 0.9625 | P21: 0.0375 | Q21: 0.032 | R21: 0.064864091 | S21: =HLOOKUP(A21,'SFY-CPR'!$B$1:$CK$26,26,FALSE) -> #N/A
A22: 849-180 | B22: Unsec Std - 849 - 180 | C22: 180 | D22: 10000 | E22: 0.0849 | G22: 0.12 | H22: 0 | I22: 2e-05 | J22: 0.15 | M22: 0.975 | N22: 0.0125 | O22: 0.9625 | P22: 0.0375 | Q22: 0.032 | R22: 0.063424106 | S22: =HLOOKUP(A22,'SFY-CPR'!$B$1:$CK$26,26,FALSE) -> #N/A
A23: 155PF | B23: Unsec Std - 1390 - 120 | C23: 120 | D23: 10000 | E23: 0.139 | G23: 0.163 | H23: 0 | I23: 2e-05 | J23: 0.15 | M23: 0.9625 | N23: 0.0125 | O23: 0.95 | P23: 0.05 | Q23: 0.0964 | R23: 0.065834672 | S23: =HLOOKUP(A23,'SFY-CPR'!$B$1:$CK$26,26,FALSE) -> #N/A
A24: NINP849-63 | B24: Unsec Std - 849 - 63 | C24: 63 | D24: 9084.7488 | E24: 0.0849 | F24: 0.0096455382 | G24: 0.23 | H24: 0 | I24: 2e-05 | J24: 0.15 | K24: 3 | L24: 0.15622343 | M24: 0.9975 | N24: 0.0125 | O24: 0.985 | P24: 0.015 | Q24: 0.0096455382 | R24: 0.065451837 | S24: =HLOOKUP(A24,'SFY-CPR'!$B$1:$CK$26,26,FALSE) -> 0.0436711592742046;0.051181123470062;0.0613711445667025
A25: NINP1049-63 | B25: Unsec Std - 1049 - 63 | C25: 63 | D25: 9084.7488 | E25: 0.1049 | F25: 0.02287584 | G25: 0.23 | H25: 0 | I25: 2e-05 | J25: 0.15 | K25: 3 | L25: 0.15622343 | M25: 0.9975 | N25: 0.0125 | O25: 0.985 | P25: 0.015 | Q25: 0.02287584 | R25: 0.070468849 | S25: =HLOOKUP(A25,'SFY-CPR'!$B$1:$CK$26,26,FALSE) -> 0.0436711592742046;0.051181123470062;0.0613711445667025
A26: NINP1349-63 | B26: Unsec Std - 1349 - 63 | C26: 63 | D26: 9084.7488 | E26: 0.1349 | F26: 0.04434144 | G26: 0.23 | H26: 0 | I26: 2e-05 | J26: 0.15 | K26: 3 | L26: 0.15622343 | M26: 0.9975 | N26: 0.0125 | O26: 0.985 | P26: 0.015 | Q26: 0.04434144 | R26: 0.075940043 | S26: =HLOOKUP(A26,'SFY-CPR'!$B$1:$CK$26,26,FALSE) -> 0.0436711592742046;0.051181123470062;0.0613711445667025
A27: NINP649-186 | B27: Unsec Std - 649 - 186 | C27: 186 | D27: 9084.7488 | E27: 0.0649 | F27: 0.00942552 | G27: 0.23 | H27: 0 | I27: 2e-05 | J27: 0.15 | K27: 6 | L27: 0.39420057 | M27: 0.985 | N27: 0.0125 | O27: 0.9725 | P27: 0.0275 | Q27: 0.00942552 | R27: 0.050167019 | S27: =HLOOKUP(A27,'SFY-CPR'!$B$1:$CK$26,26,FALSE) -> 0.0489849142849816;0.0428030164624041;0.0419287220074737;0.0555459909257746;0.0882837424238861;0.116654180496246
A28: NINP1049-186 | B28: Unsec Std - 1049 - 186 | C28: 186 | D28: 9084.7488 | E28: 0.1049 | F28: 0.01818804 | G28: 0.23 | H28: 0 | I28: 2e-05 | J28: 0.15 | K28: 6 | L28: 0.39420057 | M28: 0.985 | N28: 0.0125 | O28: 0.9725 | P28: 0.0275 | Q28: 0.01818804 | R28: 0.073033018 | S28: =HLOOKUP(A28,'SFY-CPR'!$B$1:$CK$26,26,FALSE) -> 0.0489849142849816;0.0428030164624041;0.0419287220074737;0.0555459909257746;0.0882837424238861;0.116654180496246
A29: NINP1149-186a | B29: #N/A | C29: 186 | D29: 9084.7488 | E29: 0.1149 | F29: 0.0171288 | G29: 0.23 | H29: 0 | I29: 2e-05 | J29: 0.15 | K29: 6 | L29: 0.39420057 | M29: 0.985 | N29: 0.0125 | O29: 0.9725 | P29: 0.0275 | Q29: 0.0171288 | R29: 0.081515636 | S29: =HLOOKUP(A29,'SFY-CPR'!$B$1:$CK$26,26,FALSE) -> 0.0489849142849816;0.0428030164624041;0.0419287220074737;0.0555459909257746;0.0882837424238861;0.116654180496246
A30: NINP1349-186 | B30: Unsec Std - 1349 - 186 | C30: 186 | D30: 9084.7488 | E30: 0.1349 | F30: 0.03702192 | G30: 0.23 | H30: 0 | I30: 2e-05 | J30: 0.15 | K30: 6 | L30: 0.39420057 | M30: 0.985 | N30: 0.0125 | O30: 0.9725 | P30: 0.0275 | Q30: 0.03702192 | R30: 0.078291412 | S30: =HLOOKUP(A30,'SFY-CPR'!$B$1:$CK$26,26,FALSE) -> 0.0489849142849816;0.0428030164624041;0.0419287220074737;0.0555459909257746;0.0882837424238861;0.116654180496246
A31: NINP849-132 | B31: Unsec Std - 849 - 132 | C31: 132 | D31: 9084.7488 | E31: 0.0849 | F31: 0.010758485 | G31: 0.23 | H31: 0 | I31: 2e-05 | J31: 0.15 | K31: 12 | L31: 0.5 | M31: 0.975 | N31: 0.0125 | O31: 0.9625 | P31: 0.0375 | Q31: 0.010758485 | R31: 0.052671865 | S31: =HLOOKUP(A31,'SFY-CPR'!$B$1:$CK$26,26,FALSE) -> 0.034087798153406;0.029131872311023;0.029131872311023;0.025455429050157;0.025455429050157;0.024935476432192;0.024935476432192;0.0330338174243784;0.0330338174243784;0.052503321664899;0.0723270250344311;0.115968664711763
A32: NINP1049-132 | B32: Unsec Std - 1049 - 132 | C32: 132 | D32: 9084.7488 | E32: 0.1049 | F32: 0.02111616 | G32: 0.23 | H32: 0 | I32: 2e-05 | J32: 0.15 | K32: 12 | L32: 0.5 | M32: 0.975 | N32: 0.0125 | O32: 0.9625 | P32: 0.0375 | Q32: 0.02111616 | R32: 0.054664883 | S32: =HLOOKUP(A32,'SFY-CPR'!$B$1:$CK$26,26,FALSE) -> 0.034087798153406;0.029131872311023;0.029131872311023;0.025455429050157;0.025455429050157;0.024935476432192;0.024935476432192;0.0330338174243784;0.0330338174243784;0.052503321664899;0.0723270250344311;0.115968664711763
A33: NINP1349-132 | B33: Unsec Std - 1349 - 132 | C33: 132 | D33: 9084.7488 | E33: 0.1349 | F33: 0.04221984 | G33: 0.23 | H33: 0 | I33: 2e-05 | J33: 0.15 | K33: 12 | L33: 0.5 | M33: 0.975 | N33: 0.0125 | O33: 0.9625 | P33: 0.0375 | Q33: 0.04221984 | R33: 0.051833322 | S33: =HLOOKUP(A33,'SFY-CPR'!$B$1:$CK$26,26,FALSE) -> 0.034087798153406;0.029131872311023;0.029131872311023;0.025455429050157;0.025455429050157;0.024935476432192;0.024935476432192;0.0330338174243784;0.0330338174243784;0.052503321664899;0.0723270250344311;0.115968664711763
A34: NINP949-63 | B34: Unsec Std - 949 - 63 | C34: 63 | D34: 9084.7488 | E34: 0.0949 | F34: 0.0052 | G34: 0.23 | H34: 0 | I34: 2e-05 | J34: 0.15 | K34: 3 | L34: 0.15622343 | M34: 0.9975 | N34: 0.0125 | O34: 0.985 | P34: 0.015 | Q34: 0.0096455382 | R34: 0.074458816 | S34: =HLOOKUP(A34,'SFY-CPR'!$B$1:$CK$26,26,FALSE) -> 0.0436711592742046;0.051181123470062;0.0613711445667025
A35: NINP1149-63 | B35: Unsec Std - 1149 - 63 | C35: 63 | D35: 9084.7488 | E35: 0.1149 | F35: 0.0156 | G35: 0.23 | H35: 0 | I35: 2e-05 | J35: 0.15 | K35: 3 | L35: 0.15622343 | M35: 0.9975 | N35: 0.0125 | O35: 0.985 | P35: 0.015 | Q35: 0.02287584 | R35: 0.079787006 | S35: =HLOOKUP(A35,'SFY-CPR'!$B$1:$CK$26,26,FALSE) -> 0.0436711592742046;0.051181123470062;0.0613711445667025
A36: NINP1249-63 | B36: Unsec Std - 1249 - 63 | C36: 63 | D36: 9084.7488 | E36: 0.1249 | F36: 0.0269 | G36: 0.23 | H36: 0 | I36: 2e-05 | J36: 0.15 | K36: 3 | L36: 0.15622343 | M36: 0.9975 | N36: 0.0125 | O36: 0.985 | P36: 0.015 | Q36: 0.020982 | R36: 0.088064199 | S36: =HLOOKUP(A36,'SFY-CPR'!$B$1:$CK$26,26,FALSE) -> 0.0436711592742046;0.051181123470062;0.0613711445667025
A37: NINP1449-63 | B37: Unsec Std - 1449 - 63 | C37: 63 | D37: 9084.7488 | E37: 0.1449 | F37: 0.0418 | G37: 0.23 | H37: 0 | I37: 2e-05 | J37: 0.15 | K37: 3 | L37: 0.15622343 | M37: 0.9975 | N37: 0.0125 | O37: 0.985 | P37: 0.015 | Q37: 0.04434144 | R37: 0.084518154 | S37: =HLOOKUP(A37,'SFY-CPR'!$B$1:$CK$26,26,FALSE) -> 0.0436711592742046;0.051181123470062;0.0613711445667025
A38: NINP749-186 | B38: Unsec Std - 749 - 186 | C38: 186 | D38: 9084.7488 | E38: 0.0749 | F38: 0.0053 | G38: 0.23 | H38: 0 | I38: 2e-05 | J38: 0.15 | K38: 6 | L38: 0.39420057 | M38: 0.985 | N38: 0.0125 | O38: 0.9725 | P38: 0.0275 | Q38: 0.00942552 | R38: 0.058692561 | S38: =HLOOKUP(A38,'SFY-CPR'!$B$1:$CK$26,26,FALSE) -> 0.0489849142849816;0.0428030164624041;0.0419287220074737;0.0555459909257746;0.0882837424238861;0.116654180496246
A39: NINP1149-186 | B39: Unsec Std - 1149 - 186 | C39: 186 | D39: 9084.7488 | E39: 0.1149 | F39: 0.0131 | G39: 0.23 | H39: 0 | I39: 2e-05 | J39: 0.15 | K39: 6 | L39: 0.39420057 | M39: 0.985 | N39: 0.0125 | O39: 0.9725 | P39: 0.0275 | Q39: 0.01818804 | R39: 0.081576783 | S39: =HLOOKUP(A39,'SFY-CPR'!$B$1:$CK$26,26,FALSE) -> 0.0489849142849816;0.0428030164624041;0.0419287220074737;0.0555459909257746;0.0882837424238861;0.116654180496246
A40: NINP1249-186 | B40: Unsec Std - 1249 - 186 | C40: 186 | D40: 9084.7488 | E40: 0.1249 | F40: 0.0244 | G40: 0.23 | H40: 0 | I40: 2e-05 | J40: 0.15 | K40: 6 | L40: 0.39420057 | M40: 0.985 | N40: 0.0125 | O40: 0.9725 | P40: 0.0275 | Q40: 0.0171288 | R40: 0.087522637 | S40: =HLOOKUP(A40,'SFY-CPR'!$B$1:$CK$26,26,FALSE) -> 0.0489849142849816;0.0428030164624041;0.0419287220074737;0.0555459909257746;0.0882837424238861;0.116654180496246
A41: NINP1449-186 | B41: Unsec Std - 1449 - 186 | C41: 186 | D41: 9084.7488 | E41: 0.1449 | F41: 0.0349 | G41: 0.23 | H41: 0 | I41: 2e-05 | J41: 0.15 | K41: 6 | L41: 0.39420057 | M41: 0.985 | N41: 0.0125 | O41: 0.9725 | P41: 0.0275 | Q41: 0.03702192 | R41: 0.086046951 | S41: =HLOOKUP(A41,'SFY-CPR'!$B$1:$CK$26,26,FALSE) -> 0.0489849142849816;0.0428030164624041;0.0419287220074737;0.0555459909257746;0.0882837424238861;0.116654180496246
... A45: NINP1449-132 | B45: Unsec Std - 1449 - 132 | C45: 132 | D45: 9084.7488 | E45: 0.1449 | F45: 0.0398 | G45: 0.23 | H45: 0 | I45: 2e-05 | J45: 0.15 | K45: 12 | L45: 0.5 | M45: 0.975 | N45: 0.0125 | O45: 0.9625 | P45: 0.0375 | Q45: 0.04221984 | R45: 0.058137248 | S45: =HLOOKUP(A45,'SFY-CPR'!$B$1:$CK$26,26,FALSE) -> 0.034087798153406;0.029131872311023;0.029131872311023;0.025455429050157;0.025455429050157;0.024935476432192;0.024935476432192;0.0330338174243784;0.0330338174243784;0.052503321664899;0.0723270250344311;0.115968664711763
A46: 949-120 | B46: Unsec Std - 949 - 120 | C46: 120 | D46: 10000 | E46: 0.0949 | G46: 0.12 | H46: 0 | I46: 2e-05 | J46: 0.15 | M46: 0.975 | N46: 0.0125 | O46: 0.9625 | P46: 0.0375 | Q46: 0.032 | R46: 0.074875194 | S46: =HLOOKUP(A46,'SFY-CPR'!$B$1:$CK$26,26,FALSE) -> #N/A
A47: 1490-120 | B47: Unsec Std - 1490 - 120 | C47: 120 | D47: 10000 | E47: 0.149 | G47: 0.163 | H47: 0 | I47: 2e-05 | J47: 0.15 | M47: 0.9625 | N47: 0.0125 | O47: 0.95 | P47: 0.05 | Q47: 0.0964 | R47: 0.075692744 | S47: =HLOOKUP(A47,'SFY-CPR'!$B$1:$CK$26,26,FALSE) -> #N/A
A48: NINP649-132 | B48: Unsec Std - 649 - 132 | C48: 132 | D48: 9084.7488 | E48: 0.0649 | F48: 0.0058 | G48: 0.23 | H48: 0 | I48: 2e-05 | J48: 0.15 | K48: 12 | L48: 0.5 | M48: 0.975 | N48: 0.0125 | O48: 0.9625 | P48: 0.0375 | Q48: 0.010758485 | R48: 0.043008322 | S48: =HLOOKUP(A48,'SFY-CPR'!$B$1:$CK$26,26,FALSE) -> 0.034087798153406;0.029131872311023;0.029131872311023;0.025455429050157;0.025455429050157;0.024935476432192;0.024935476432192;0.0330338174243784;0.0330338174243784;0.052503321664899;0.0723270250344311;0.115968664711763
A49: NINP1149-128 | B49: #N/A | C49: 128 | D49: 9084.7488 | E49: 0.1149 | F49: 0.0265 | G49: 0.23 | H49: 0 | I49: 2e-05 | J49: 0.15 | K49: 8 | L49: 0.4056687 | M49: 0.975 | N49: 0.0125 | O49: 0.9625 | P49: 0.0375 | Q49: 0.02067 | R49: 0.073948807 | S49: =HLOOKUP(A49,'SFY-CPR'!$B$1:$CK$26,26,FALSE) -> 0.051131697230109;0.0436978084665345;0.0436978084665345;0.0381831435752355;0.0381831435752355;0.037403214648288;0.037403214648288;0.115968664711763
A50: NINP1349-128 | B50: Unsec Std - 1349 - 128 | C50: 128 | D50: 9084.7488 | E50: 0.1149 | F50: 0.0265 | G50: 0.23 | H50: 0 | I50: 2e-05 | J50: 0.15 | K50: 8 | L50: 0.4056687 | M50: 0.975 | N50: 0.0125 | O50: 0.9625 | P50: 0.0375 | Q50: 0.04221984 | R50: 0.060249359 | S50: =HLOOKUP(A50,'SFY-CPR'!$B$1:$CK$26,26,FALSE) -> 0.051131697230109;0.0436978084665345;0.0436978084665345;0.0381831435752355;0.0381831435752355;0.037403214648288;0.037403214648288;0.115968664711763
A51: 36EPNI | B51: Unsec Std - EPNI 36 Mo | C51: 36 | D51: 10226.825 | E51: 0 | G51: 0.214 | H51: 0 | I51: 2e-05 | J51: 0.15 | M51: 0.9125 | N51: 0.0125 | O51: 0.9 | P51: 0.1 | Q51: 0.01274588 | R51: 0.06469489 | S51: =HLOOKUP(A51,'SFY-CPR'!$B$1:$CK$26,26,FALSE) -> #N/A
A52: 60EPNI | B52: Unsec Std - EPNI 60 Mo | C52: 60 | D52: 11934.352 | E52: 0 | G52: 0.139 | H52: 0 | I52: 2e-05 | J52: 0.15 | M52: 0.8775 | N52: 0.0125 | O52: 0.865 | P52: 0.135 | Q52: 0.01529394 | R52: 0.053756467 | S52: =HLOOKUP(A52,'SFY-CPR'!$B$1:$CK$26,26,FALSE) -> #N/A
A53: NINP4331 | B53: #N/A | C53: 123 | D53: 10000 | E53: 0.099 | F53: 0.0099055277 | G53: 0.316 | H53: 0 | I53: 2e-05 | J53: 0.15 | K53: 3 | L53: 0.15622343 | M53: 0.9975 | N53: 0.0125 | O53: 0.985 | P53: 0.015 | Q53: 0.0319 | R53: 0.061287122 | S53: =HLOOKUP(A53,'SFY-CPR'!$B$1:$CK$26,26,FALSE) -> 0.0436711592742046;0.051181123470062;0.0613711445667025
A54: NINP4306 | B54: #N/A | C54: 183 | D54: 10000 | E54: 0.099 | F54: 0.0093474245 | G54: 0.316 | H54: 0 | I54: 2e-05 | J54: 0.15 | K54: 3 | L54: 0.15622343 | M54: 0.985 | N54: 0.0125 | O54: 0.9725 | P54: 0.0275 | Q54: 0.0319 | R54: 0.068588401 | S54: =HLOOKUP(A54,'SFY-CPR'!$B$1:$CK$26,26,FALSE) -> 0.0436711592742046;0.051181123470062;0.0613711445667025
A55: NINP849-183 | B55: #N/A | C55: 183 | D55: 10000 | E55: 0.0849 | F55: 0.0125 | G55: 0.316 | H55: 0 | I55: 2e-05 | J55: 0.15 | K55: 3 | L55: 0.15622343 | M55: 0.9665 | N55: 0.0125 | O55: 0.954 | P55: 0.046 | Q55: 0.032 | R55: 0.065942261 | S55: =HLOOKUP(A55,'SFY-CPR'!$B$1:$CK$26,26,FALSE) -> 0.0436711592742046;0.051181123470062;0.0613711445667025
A56: 1099-120 | B56: Unsec Std - 1099 - 120 | C56: 120 | D56: 10000 | E56: 0.1099 | G56: 0.163 | H56: 0 | I56: 2e-05 | J56: 0.15 | M56: 0.8925 | N56: 0.0125 | O56: 0.88 | P56: 0.12 | Q56: 0.0964 | R56: 0.067758858 | S56: =HLOOKUP(A56,'SFY-CPR'!$B$1:$CK$26,26,FALSE) -> #N/A

Sheet PRIME-CPR
A1: Mth | B1: NINP3 | C1: NINP6 | D1: NINP12 | E1: NINP18 | F1: NINP24 | G1: NINP10 | H1: NINP14 | I1: NINP20 | J1: NINP4316 | K1: NINP4398 | L1: NINP4302 | M1: NINP4602 | N1: NINP4321 | O1: NINP4301 | P1: NINP4626 | Q1: NINP4332 | R1: NINP4312 | S1: NINP4632 | T1: NINP4612 | U1: NINP41232 | V1: NINP41207 | W1: NINP899/63 | X1: NINP1099/63 | Y1: NINP1199/63 | Z1: NINP1399/63 | AA1: NINP699/186 | AB1: NINP1099/186 | AC1: NINP1199/186 | AD1: NINP1399/186 | AE1: NINP899/132 | AF1: NINP1099/132 | AG1: NINP1199/132 | AH1: NINP1399/132 | AI1: NINP849-63 | AJ1: NINP1049-63 | AK1: NINP1149-63a | AL1: NINP1349-63 | AM1: NINP649-186 | AN1: NINP1049-186 | AO1: NINP1149-186a | AP1: NINP1349-186 | AQ1: NINP849-132 | AR1: NINP1049-132 | AS1: NINP1149-132a | AT1: NINP1349-132 | AU1: NINP949-63 | AV1: NINP1149-63 | AW1: NINP1249-63 | AX1: NINP1449-63 | AY1: NINP749-186 | AZ1: NINP1149-186 | BA1: NINP1249-186 | BB1: NINP1449-186 | BC1: NINP949-132 | BD1: NINP1149-132 | BE1: NINP1249-132 | BF1: NINP1449-132 | BG1: NINP649-132 | BH1: NINP1149-128 | BI1: NINP1349-128 | BJ1: NINP4396 | BK1: NINP4687 | BL1: NINP4213 | BM1: NINP4813 | BN1: NINP4013 | BO1: NINP4331 | BP1: NINP4337 | BQ1: NINP4342 | BR1: NINP4348 | BS1: NINP4355 | BT1: NINP4306 | BU1: NINP4313 | BV1: NINP4319 | BW1: NINP4325 | BX1: NINP4333 | BY1: NINP12n | BZ1: NINP18n | CA1: WP18n | CB1: WP24n | CC1: NINP849-183 | CD1: NINP1195-132 | CE1: WP6 | CF1: WP12 | CG1: WP18 | CH1: WP24 | CI1: WP10 | CJ1: WP14 | CK1: WP20
A2: 1 | B2: 0.33366367 | C2: 0.12881709 | D2: 0.06763335 | E2: 0.039703346 | F2: 0.03026823 | G2: 0.09 | H2: 0.045 | I2: 0.03 | J2: 0.050200338 | K2: 0.052132744 | L2: 0.028671159 | M2: 0.048984914 | N2: 0.045242224 | O2: 0.033671159 | P2: 0.067214363 | Q2: 0.047410486 | R2: 0.043671159 | S2: 0.067214363 | T2: 0.067214363 | U2: 0.047272958 | V2: 0.047272958 | W2: 0.043671159 | X2: 0.043671159 | Y2: 0.043671159 | Z2: 0.043671159 | AA2: 0.048984914 | AB2: 0.048984914 | AC2: 0.048984914 | AD2: 0.048984914 | AE2: 0.034087798 | AF2: 0.034087798 | AG2: 0.034087798 | AH2: 0.034087798 | AI2: 0.043671159 | AJ2: 0.043671159 | AK2: 0.043671159 | AL2: 0.043671159 | AM2: 0.048984914 | AN2: 0.048984914 | AO2: 0.048984914 | AP2: 0.048984914 | AQ2: 0.034087798 | AR2: 0.034087798 | AS2: 0.034087798 | AT2: 0.034087798 | AU2: 0.043671159 | AV2: 0.043671159 | AW2: 0.043671159 | AX2: 0.043671159 | AY2: 0.048984914 | AZ2: 0.048984914 | BA2: 0.048984914 | BB2: 0.048984914 | BC2: 0.034087798 | BD2: 0.034087798 | BE2: 0.034087798 | BF2: 0.034087798 | BG2: 0.034087798 | BH2: 0.051131697 | BI2: 0.051131697 | BJ2: 0.043671159 | BK2: 0.048984914 | BL2: 0.034087798 | BM2: 0.04 | BN2: 0.036 | BO2: 0.043671159 | BP2: 0.043671159 | BQ2: 0.043671159 | BR2: 0.043671159 | BS2: 0.043671159 | BT2: 0.043671159 | BU2: 0.043671159 | BV2: 0.043671159 | BW2: 0.043671159 | BX2: 0.043671159 | BY2: 0.064439053 | BZ2: 0.037828172 | CA2: 0.061498594 | CB2: 0.041451802 | CC2: 0.043671159 | CD2: 0.047272958 | CE2: 0.1895542 | CF2: 0.09742644 | CG2: 0.064594797 | CH2: 0.04353873 | CI2: 0.11 | CJ2: 0.057 | CK2: 0.055
A3: 2 | B3: 0.27123217 | C3: 0.10904923 | D3: 0.053375652 | E3: 0.036357159 | F3: 0.035600136 | G3: 0.06 | H3: 0.045 | I3: 0.03 | J3: 0.051770625 | K3: 0.053114819 | L3: 0.036181123 | M3: 0.042803016 | N3: 0.055332981 | O3: 0.041181123 | P3: 0.058731908 | Q3: 0.055563488 | R3: 0.051181123 | S3: 0.058731908 | T3: 0.058731908 | U3: 0.040400081 | V3: 0.040400081 | W3: 0.051181123 | X3: 0.051181123 | Y3: 0.051181123 | Z3: 0.051181123 | AA3: 0.042803016 | AB3: 0.042803016 | AC3: 0.042803016 | AD3: 0.042803016 | AE3: 0.029131872 | AF3: 0.029131872 | AG3: 0.029131872 | AH3: 0.029131872 | AI3: 0.051181123 | AJ3: 0.051181123 | AK3: 0.051181123 | AL3: 0.051181123 | AM3: 0.042803016 | AN3: 0.042803016 | AO3: 0.042803016 | AP3: 0.042803016 | AQ3: 0.029131872 | AR3: 0.029131872 | AS3: 0.029131872 | AT3: 0.029131872 | AU3: 0.051181123 | AV3: 0.051181123 | AW3: 0.051181123 | AX3: 0.051181123 | AY3: 0.042803016 | AZ3: 0.042803016 | BA3: 0.042803016 | BB3: 0.042803016 | BC3: 0.029131872 | BD3: 0.029131872 | BE3: 0.029131872 | BF3: 0.029131872 | BG3: 0.029131872 | BH3: 0.043697808 | BI3: 0.043697808 | BJ3: 0.051181123 | BK3: 0.042803016 | BL3: 0.029131872 | BM3: 0.04 | BN3: 0.036 | BO3: 0.051181123 | BP3: 0.051181123 | BQ3: 0.051181123 | BR3: 0.051181123 | BS3: 0.051181123 | BT3: 0.051181123 | BU3: 0.051181123 | BV3: 0.051181123 | BW3: 0.051181123 | BX3: 0.051181123 | BY3: 0.05085474 | BZ3: 0.034640024 | CA3: 0.043545474 | CB3: 0.028026264 | CC3: 0.051181123 | CD3: 0.040400081 | CE3: 0.12676458 | CF3: 0.067351181 | CG3: 0.045737811 | CH3: 0.029437272 | CI3: 0.07 | CJ3: 0.056 | CK3: 0.054
A4: 3 | B4: 0.37960416 | C4: 0.10644286 | D4: 0.053250045 | E4: 0.034709709 | F4: 0.02648995 | G4: 0.06 | H4: 0.045 | I4: 0.03 | J4: 0.067629037 | K4: 0.064352436 | L4: 0.046371145 | M4: 0.041928722 | N4: 0.069024794 | O4: 0.051371145 | P4: 0.05753225 | Q4: 0.066626026 | R4: 0.061371145 | S4: 0.05753225 | T4: 0.05753225 | U4: 0.040400081 | V4: 0.040400081 | W4: 0.061371145 | X4: 0.061371145 | Y4: 0.061371145 | Z4: 0.061371145 | AA4: 0.041928722 | AB4: 0.041928722 | AC4: 0.041928722 | AD4: 0.041928722 | AE4: 0.029131872 | AF4: 0.029131872 | AG4: 0.029131872 | AH4: 0.029131872 | AI4: 0.061371145 | AJ4: 0.061371145 | AK4: 0.061371145 | AL4: 0.061371145 | AM4: 0.041928722 | AN4: 0.041928722 | AO4: 0.041928722 | AP4: 0.041928722 | AQ4: 0.029131872 | AR4: 0.029131872 | AS4: 0.029131872 | AT4: 0.029131872 | AU4: 0.061371145 | AV4: 0.061371145 | AW4: 0.061371145 | AX4: 0.061371145 | AY4: 0.041928722 | AZ4: 0.041928722 | BA4: 0.041928722 | BB4: 0.041928722 | BC4: 0.029131872 | BD4: 0.029131872 | BE4: 0.029131872 | BF4: 0.029131872 | BG4: 0.029131872 | BH4: 0.043697808 | BI4: 0.043697808 | BJ4: 0.061371145 | BK4: 0.041928722 | BL4: 0.029131872 | BM4: 0.039 | BN4: 0.035 | BO4: 0.061371145 | BP4: 0.061371145 | BQ4: 0.061371145 | BR4: 0.061371145 | BS4: 0.061371145 | BT4: 0.061371145 | BU4: 0.061371145 | BV4: 0.061371145 | BW4: 0.061371145 | BX4: 0.061371145 | BY4: 0.050735066 | BZ4: 0.033070383 | CA4: 0.039774786 | CB4: 0.023879196 | CC4: 0.061371145 | CD4: 0.040400081 | CE4: 0.10935252 | CF4: 0.063170267 | CG4: 0.041777284 | CH4: 0.025081416 | CI4: 0.07 | CJ4: 0.056 | CK4: 0.048
A5: 4 | C5: 0.12017547 | D5: 0.054283117 | E5: 0.035482692 | F5: 0.027871366 | G5: 0.06 | H5: 0.045 | I5: 0.03 | M5: 0.055545991 | P5: 0.076217106 | S5: 0.076217106 | T5: 0.076217106 | U5: 0.035301589 | V5: 0.035301589 | AA5: 0.055545991 | AB5: 0.055545991 | AC5: 0.055545991 | AD5: 0.055545991 | AE5: 0.025455429 | AF5: 0.025455429 | AG5: 0.025455429 | AH5: 0.025455429 | AM5: 0.055545991 | AN5: 0.055545991 | AO5: 0.055545991 | AP5: 0.055545991 | AQ5: 0.025455429 | AR5: 0.025455429 | AS5: 0.025455429 | AT5: 0.025455429 | AY5: 0.055545991 | AZ5: 0.055545991 | BA5: 0.055545991 | BB5: 0.055545991 | BC5: 0.025455429 | BD5: 0.025455429 | BE5: 0.025455429 | BF5: 0.025455429 | BG5: 0.025455429 | BH5: 0.038183144 | BI5: 0.038183144 | BK5: 0.055545991 | BL5: 0.025455429 | BM5: 0.044 | BN5: 0.04 | BY5: 0.051719346 | BZ5: 0.033806858 | CA5: 0.038192667 | CB5: 0.024341818 | CD5: 0.035301589 | CE5: 0.12053361 | CF5: 0.060646889 | CG5: 0.040115511 | CH5: 0.025567329 | CI5: 0.07 | CJ5: 0.056 | CK5: 0.042
A6: 5 | C6: 0.1975722 | D6: 0.054772379 | E6: 0.037439796 | F6: 0.023758661 | G6: 0.06 | H6: 0.045 | I6: 0.03 | M6: 0.088283742 | P6: 0.12113802 | S6: 0.12113802 | T6: 0.12113802 | U6: 0.035301589 | V6: 0.035301589 | AA6: 0.088283742 | AB6: 0.088283742 | AC6: 0.088283742 | AD6: 0.088283742 | AE6: 0.025455429 | AF6: 0.025455429 | AG6: 0.025455429 | AH6: 0.025455429 | AM6: 0.088283742 | AN6: 0.088283742 | AO6: 0.088283742 | AP6: 0.088283742 | AQ6: 0.025455429 | AR6: 0.025455429 | AS6: 0.025455429 | AT6: 0.025455429 | AY6: 0.088283742 | AZ6: 0.088283742 | BA6: 0.088283742 | BB6: 0.088283742 | BC6: 0.025455429 | BD6: 0.025455429 | BE6: 0.025455429 | BF6: 0.025455429 | BG6: 0.025455429 | BH6: 0.038183144 | BI6: 0.038183144 | BK6: 0.088283742 | BL6: 0.025455429 | BM6: 0.05 | BN6: 0.04 | BY6: 0.0521855 | BZ6: 0.035671529 | CA6: 0.03689461 | CB6: 0.023940027 | CD6: 0.035301589 | CE6: 0.14001462 | CF6: 0.061915997 | CG6: 0.038752103 | CH6: 0.02514531 | CI6: 0.07 | CJ6: 0.056 | CK6: 0.032
A7: 6 | C7: 0.27934315 | D7: 0.054244757 | E7: 0.039737887 | F7: 0.025792207 | G7: 0.06 | H7: 0.045 | I7: 0.03 | M7: 0.11665418 | P7: 0.16006635 | S7: 0.16006635 | T7: 0.16006635 | U7: 0.034580519 | V7: 0.034580519 | AA7: 0.11665418 | AB7: 0.11665418 | AC7: 0.11665418 | AD7: 0.11665418 | AE7: 0.024935476 | AF7: 0.024935476 | AG7: 0.024935476 | AH7: 0.024935476 | AM7: 0.11665418 | AN7: 0.11665418 | AO7: 0.11665418 | AP7: 0.11665418 | AQ7: 0.024935476 | AR7: 0.024935476 | AS7: 0.024935476 | AT7: 0.024935476 | AY7: 0.11665418 | AZ7: 0.11665418 | BA7: 0.11665418 | BB7: 0.11665418 | BC7: 0.024935476 | BD7: 0.024935476 | BE7: 0.024935476 | BF7: 0.024935476 | BG7: 0.024935476 | BH7: 0.037403215 | BI7: 0.037403215 | BK7: 0.11665418 | BL7: 0.024935476 | BM7: 0.05 | BN7: 0.044 | BY7: 0.051682798 | BZ7: 0.037861082 | CA7: 0.036372926 | CB7: 0.024371182 | CD7: 0.034580519 | CE7: 0.18382748 | CF7: 0.060026785 | CG7: 0.038204154 | CH7: 0.025598171 | CI7: 0.07 | CJ7: 0.056 | CK7: 0.032
A8: 7 | D8: 0.056489571 | E8: 0.034907695 | F8: 0.021222931 | G8: 0.07 | H8: 0.045 | I8: 0.03 | U8: 0.034580519 | V8: 0.034580519 | AE8: 0.024935476 | AF8: 0.024935476 | AG8: 0.024935476 | AH8: 0.024935476 | AQ8: 0.024935476 | AR8: 0.024935476 | AS8: 0.024935476 | AT8: 0.024935476 | BC8: 0.024935476 | BD8: 0.024935476 | BE8: 0.024935476 | BF8: 0.024935476 | BG8: 0.024935476 | BH8: 0.037403215 | BI8: 0.037403215 | BL8: 0.024935476 | BM8: 0.06 | BN8: 0.044 | BY8: 0.05382159 | BZ8: 0.033259018 | CA8: 0.039268803 | CB8: 0.023149749 | CD8: 0.034580519 | CF8: 0.061692945 | CG8: 0.041245826 | CH8: 0.024315244 | CI8: 0.07 | CJ8: 0.056 | CK8: 0.032
A9: 8 | D9: 0.059411377 | E9: 0.035885356 | F9: 0.029632548 | G9: 0.08 | H9: 0.045 | I9: 0.03 | U9: 0.045811298 | V9: 0.045811298 | AE9: 0.033033817 | AF9: 0.033033817 | AG9: 0.033033817 | AH9: 0.033033817 | AQ9: 0.033033817 | AR9: 0.033033817 | AS9: 0.033033817 | AT9: 0.033033817 | BC9: 0.033033817 | BD9: 0.033033817 | BE9: 0.033033817 | BF9: 0.033033817 | BG9: 0.033033817 | BH9: 0.11596866 | BI9: 0.11596866 | BL9: 0.033033817 | BM9: 0.11 | BN9: 0.044 | BY9: 0.0566054 | BZ9: 0.034190504 | CA9: 0.038258358 | CB9: 0.022225741 | CD9: 0.045811298 | CF9: 0.063714385 | CG9: 0.04018451 | CH9: 0.023344716 | CI9: 0.08 | CJ9: 0.056 | CK9: 0.032
A10: 9 | D10: 0.066709985 | E10: 0.040163947 | F10: 0.029565746 | G10: 0.15 | H10: 0.045 | I10: 0.03 | U10: 0.045811298 | V10: 0.045811298 | AE10: 0.033033817 | AF10: 0.033033817 | AG10: 0.033033817 | AH10: 0.033033817 | AQ10: 0.033033817 | AR10: 0.033033817 | AS10: 0.033033817 | AT10: 0.033033817 | BC10: 0.033033817 | BD10: 0.033033817 | BE10: 0.033033817 | BF10: 0.033033817 | BG10: 0.033033817 | BL10: 0.033033817 | BN10: 0.06 | BY10: 0.063559298 | BZ10: 0.038267019 | CA10: 0.037784305 | CB10: 0.027951725 | CD10: 0.045811298 | CF10: 0.068177468 | CG10: 0.03968659 | CH10: 0.02935898 | CI10: 0.13 | CJ10: 0.057 | CK10: 0.032
A11: 10 | D11: 0.081659324 | E11: 0.036182784 | F11: 0.030828751 | G11: 0.23 | H11: 0.045 | I11: 0.03 | U11: 0.072811606 | V11: 0.072811606 | AE11: 0.052503322 | AF11: 0.052503322 | AG11: 0.052503322 | AH11: 0.052503322 | AQ11: 0.052503322 | AR11: 0.052503322 | AS11: 0.052503322 | AT11: 0.052503322 | BC11: 0.052503322 | BD11: 0.052503322 | BE11: 0.052503322 | BF11: 0.052503322 | BG11: 0.052503322 | BL11: 0.052503322 | BN11: 0.11 | BY11: 0.077802585 | BZ11: 0.034473885 | CA11: 0.039470383 | CB11: 0.024816806 | CD11: 0.072811606 | CF11: 0.085589652 | CG11: 0.041457555 | CH11: 0.02606623 | CI11: 0.16 | CJ11: 0.057 | CK11: 0.032
A12: 11 | D12: 0.14847544 | E12: 0.041062911 | F12: 0.038167371 | H12: 0.05 | I12: 0.03 | U12: 0.10030312 | V12: 0.10030312 | AE12: 0.072327025 | AF12: 0.072327025 | AG12: 0.072327025 | AH12: 0.072327025 | AQ12: 0.072327025 | AR12: 0.072327025 | AS12: 0.072327025 | AT12: 0.072327025 | BC12: 0.072327025 | BD12: 0.072327025 | BE12: 0.072327025 | BF12: 0.072327025 | BG12: 0.072327025 | BL12: 0.072327025 | BY12: 0.141463 | BZ12: 0.039123525 | CA12: 0.040068104 | CB12: 0.023766885 | CD12: 0.10030312 | CF12: 0.12657167 | CG12: 0.042085369 | CH12: 0.024963451 | CJ12: 0.057 | CK12: 0.032
A13: 12 | D13: 0.220095 | E13: 0.043798407 | F13: 0.030832404 | H13: 0.07 | I13: 0.03 | U13: 0.16082534 | V13: 0.16082534 | AE13: 0.11596866 | AF13: 0.11596866 | AG13: 0.11596866 | AH13: 0.11596866 | AQ13: 0.11596866 | AR13: 0.11596866 | AS13: 0.11596866 | AT13: 0.11596866 | BC13: 0.11596866 | BD13: 0.11596866 | BE13: 0.11596866 | BF13: 0.11596866 | BG13: 0.11596866 | BL13: 0.11596866 | BY13: 0.2097 | BZ13: 0.041729825 | CA13: 0.039653623 | CB13: 0.027194926 | CD13: 0.16082534 | CF13: 0.15501632 | CG13: 0.041650021 | CH13: 0.028564079 | CJ13: 0.058 | CK13: 0.032
A14: 13 | E14: 0.044275012 | F14: 0.030895519 | H14: 0.13 | I14: 0.03 | BZ14: 0.04218392 | CA14: 0.041587882 | CB14: 0.027466483 | CG14: 0.043681662 | CH14: 0.028849308 | CJ14: 0.098 | CK14: 0.032
A15: 14 | E15: 0.043314271 | F15: 0.028723293 | H15: 0.2 | I15: 0.03 | BZ15: 0.041268555 | CA15: 0.043048771 | CB15: 0.027301686 | CG15: 0.0452161 | CH15: 0.028676214 | CJ15: 0.125 | CK15: 0.032
A16: 15 | E16: 0.048749252 | F16: 0.032676297 | I16: 0.03 | BZ16: 0.046446844 | CA16: 0.049761672 | CB16: 0.029818524 | CG16: 0.052266969 | CH16: 0.031319764 | CK16: 0.032
A17: 16 | E17: 0.063602332 | F17: 0.021093038 | I17: 0.03 | BZ17: 0.060598418 | CA17: 0.061216191 | CB17: 0.027664467 | CG17: 0.064298175 | CH17: 0.02905726 | CK17: 0.032
A18: 17 | E18: 0.11510572 | F18: 0.027737116 | I18: 0.03 | BZ18: 0.10966932 | CA18: 0.099021288 | CB18: 0.027989778 | CG18: 0.10400661 | CH18: 0.029398949 | CK18: 0.032
A19: 18 | E19: 0.19432173 | F19: 0.037097547 | I19: 0.04 | BZ19: 0.18514399 | CA19: 0.12380584 | CB19: 0.029991663 | CG19: 0.13003896 | CH19: 0.031501621 | CK19: 0.067
A20: 19 | F20: 0.035807391 | I20: 0.14 | CB20: 0.036818572 | CH20: 0.038672236 | CK20: 0.098
A21: 20 | F21: 0.035803371 | I21: 0.19 | CB21: 0.04447365 | CH21: 0.046712716 | CK21: 0.125
A22: 21 | F22: 0.036391389 | CB22: 0.045817756 | CH22: 0.048124493
A23: 22 | F23: 0.063853619 | CB23: 0.066279674 | CH23: 0.069616584
A24: 23 | F24: 0.086512393 | CB24: 0.097478301 | CH24: 0.10238593
A25: 24 | F25: 0.096978726 | CB25: 0.12462941 | CH25: 0.13090399
B26: =_xlfn.CONCAT(B2,";",B3,";",B4,IF(ISBLANK(B5),"",";"),B5,IF(ISBLANK(B6),"",";"),B6,IF(ISBLANK(B7),"",";"),B7,IF(ISBLANK(B8),"",";"),B8,IF(ISBLANK(B9),"",";"),B9,IF(ISBLANK(B10),"",";"),B10,IF(ISBLANK(B11),"",";"),B11,IF(ISBLANK(B12),"",";"),B12,IF(ISBLANK(B13),"",";"),B13,IF(ISBLANK(B14),"",";"),B14,IF(ISBLANK(B15),"",";"),B15,IF(ISBLANK(B16),"",";"),B16,IF(ISBLANK(B17),"",";"),B17,IF(ISBLANK(B18),"",";"),B18,IF(ISBLANK(B19),"",";"),B19,IF(ISBLANK(B20),"",";"),B20,IF(ISBLANK(B21),"",";"),B21,IF(ISBLANK(B22),"",";"),B22,IF(ISBLANK(B23),"",";"),B23,IF(ISBLANK(B24),"",";"),B24,IF(ISBLANK(B25),"",";"),B25) -> 0.333663669422478;0.27123217065051;0.379604159927013 | C26: =_xlfn.CONCAT(C2,";",C3,";",C4,IF(ISBLANK(C5),"",";"),C5,IF(ISBLANK(C6),"",";"),C6,IF(ISBLANK(C7),"",";"),C7,IF(ISBLANK(C8),"",";"),C8,IF(ISBLANK(C9),"",";"),C9,IF(ISBLANK(C10),"",";"),C10,IF(ISBLANK(C11),"",";"),C11,IF(ISBLANK(C12),"",";"),C12,IF(ISBLANK(C13),"",";"),C13,IF(ISBLANK(C14),"",";"),C14,IF(ISBLANK(C15),"",";"),C15,IF(ISBLANK(C16),"",";"),C16,IF(ISBLANK(C17),"",";"),C17,IF(ISBLANK(C18),"",";"),C18,IF(ISBLANK(C19),"",";"),C19,IF(ISBLANK(C20),"",";"),C20,IF(ISBLANK(C21),"",";"),C21,IF(ISBLANK(C22),"",";"),C22,IF(ISBLANK(C23),"",";"),C23,IF(ISBLANK(C24),"",";"),C24,IF(ISBLANK(C25),"",";"),C25) -> 0.128817089271534;0.10904922611393;0.106442864313677;0.120175472098005;0.197572195306553;0.279343152896301 | D26: =_xlfn.CONCAT(D2,";",D3,";",D4,IF(ISBLANK(D5),"",";"),D5,IF(ISBLANK(D6),"",";"),D6,IF(ISBLANK(D7),"",";"),D7,IF(ISBLANK(D8),"",";"),D8,IF(ISBLANK(D9),"",";"),D9,IF(ISBLANK(D10),"",";"),D10,IF(ISBLANK(D11),"",";"),D11,IF(ISBLANK(D12),"",";"),D12,IF(ISBLANK(D13),"",";"),D13,IF(ISBLANK(D14),"",";"),D14,IF(ISBLANK(D15),"",";"),D15,IF(ISBLANK(D16),"",";"),D16,IF(ISBLANK(D17),"",";"),D17,IF(ISBLANK(D18),"",";"),D18,IF(ISBLANK(D19),"",";"),D19,IF(ISBLANK(D20),"",";"),D20,IF(ISBLANK(D21),"",";"),D21,IF(ISBLANK(D22),"",";"),D22,IF(ISBLANK(D23),"",";"),D23,IF(ISBLANK(D24),"",";"),D24,IF(ISBLANK(D25),"",";"),D25) -> 0.0676333498793084;0.0533756521010278;0.0532500454780047;0.0542831166094344;0.0547723788788143;0.0542447568131707;0.0564895709616642;0.0594113771367509;0.0667099854605115;0.0816593237270766;0.148475440070047;0.22009500288419 | E26: =_xlfn.CONCAT(E2,";",E3,";",E4,IF(ISBLANK(E5),"",";"),E5,IF(ISBLANK(E6),"",";"),E6,IF(ISBLANK(E7),"",";"),E7,IF(ISBLANK(E8),"",";"),E8,IF(ISBLANK(E9),"",";"),E9,IF(ISBLANK(E10),"",";"),E10,IF(ISBLANK(E11),"",";"),E11,IF(ISBLANK(E12),"",";"),E12,IF(ISBLANK(E13),"",";"),E13,IF(ISBLANK(E14),"",";"),E14,IF(ISBLANK(E15),"",";"),E15,IF(ISBLANK(E16),"",";"),E16,IF(ISBLANK(E17),"",";"),E17,IF(ISBLANK(E18),"",";"),E18,IF(ISBLANK(E19),"",";"),E19,IF(ISBLANK(E20),"",";"),E20,IF(ISBLANK(E21),"",";"),E21,IF(ISBLANK(E22),"",";"),E22,IF(ISBLANK(E23),"",";"),E23,IF(ISBLANK(E24),"",";"),E24,IF(ISBLANK(E25),"",";"),E25) -> 0.0397033461852658;0.0363571588299138;0.0347097092841171;0.0354826917146094;0.0374397958165012;0.039737887495065;0.0349076948107677;0.0358853559269975;0.0401639469945674;0.0361827842477967;0.0410629108672573;0.0437984067038958;0.0442750123745728;0.043314271123343;0.048749252320648;0.0636023317033571;0.115105715126378;0.194321728474946 | F26: =_xlfn.CONCAT(F2,";",F3,";",F4,IF(ISBLANK(F5),"",";"),F5,IF(ISBLANK(F6),"",";"),F6,IF(ISBLANK(F7),"",";"),F7,IF(ISBLANK(F8),"",";"),F8,IF(ISBLANK(F9),"",";"),F9,IF(ISBLANK(F10),"",";"),F10,IF(ISBLANK(F11),"",";"),F11,IF(ISBLANK(F12),"",";"),F12,IF(ISBLANK(F13),"",";"),F13,IF(ISBLANK(F14),"",";"),F14,IF(ISBLANK(F15),"",";"),F15,IF(ISBLANK(F16),"",";"),F16,IF(ISBLANK(F17),"",";"),F17,IF(ISBLANK(F18),"",";"),F18,IF(ISBLANK(F19),"",";"),F19,IF(ISBLANK(F20),"",";"),F20,IF(ISBLANK(F21),"",";"),F21,IF(ISBLANK(F22),"",";"),F22,IF(ISBLANK(F23),"",";"),F23,IF(ISBLANK(F24),"",";"),F24,IF(ISBLANK(F25),"",";"),F25) -> 0.0302682303390938;0.0356001359822339;0.0264899498130113;0.0278713659278495;0.0237586612170386;0.0257922068481641;0.0212229312672512;0.0296325482161332;0.0295657455342041;0.0308287508657281;0.0381673706394066;0.0308324037932695;0.0308955187188472;0.028723292961373;0.032676297334632;0.0210930382447866;0.0277371162310062;0.0370975473999753;0.035807390962314;0.035803371307891;0.0363913891800091;0.0638536190282034;0.0865123925721557;0.0969787256154225 | G26: =_xlfn.CONCAT(G2,";",G3,";",G4,IF(ISBLANK(G5),"",";"),G5,IF(ISBLANK(G6),"",";"),G6,IF(ISBLANK(G7),"",";"),G7,IF(ISBLANK(G8),"",";"),G8,IF(ISBLANK(G9),"",";"),G9,IF(ISBLANK(G10),"",";"),G10,IF(ISBLANK(G11),"",";"),G11,IF(ISBLANK(G12),"",";"),G12,IF(ISBLANK(G13),"",";"),G13,IF(ISBLANK(G14),"",";"),G14,IF(ISBLANK(G15),"",";"),G15,IF(ISBLANK(G16),"",";"),G16,IF(ISBLANK(G17),"",";"),G17,IF(ISBLANK(G18),"",";"),G18,IF(ISBLANK(G19),"",";"),G19,IF(ISBLANK(G20),"",";"),G20,IF(ISBLANK(G21),"",";"),G21,IF(ISBLANK(G22),"",";"),G22,IF(ISBLANK(G23),"",";"),G23,IF(ISBLANK(G24),"",";"),G24,IF(ISBLANK(G25),"",";"),G25) -> 0.09;0.06;0.06;0.06;0.06;0.06;0.07;0.08;0.15;0.23 | H26: =_xlfn.CONCAT(H2,";",H3,";",H4,IF(ISBLANK(H5),"",";"),H5,IF(ISBLANK(H6),"",";"),H6,IF(ISBLANK(H7),"",";"),H7,IF(ISBLANK(H8),"",";"),H8,IF(ISBLANK(H9),"",";"),H9,IF(ISBLANK(H10),"",";"),H10,IF(ISBLANK(H11),"",";"),H11,IF(ISBLANK(H12),"",";"),H12,IF(ISBLANK(H13),"",";"),H13,IF(ISBLANK(H14),"",";"),H14,IF(ISBLANK(H15),"",";"),H15,IF(ISBLANK(H16),"",";"),H16,IF(ISBLANK(H17),"",";"),H17,IF(ISBLANK(H18),"",";"),H18,IF(ISBLANK(H19),"",";"),H19,IF(ISBLANK(H20),"",";"),H20,IF(ISBLANK(H21),"",";"),H21,IF(ISBLANK(H22),"",";"),H22,IF(ISBLANK(H23),"",";"),H23,IF(ISBLANK(H24),"",";"),H24,IF(ISBLANK(H25),"",";"),H25) -> 0.045;0.045;0.045;0.045;0.045;0.045;0.045;0.045;0.045;0.045;0.05;0.07;0.13;0.2 | I26: =_xlfn.CONCAT(I2,";",I3,";",I4,IF(ISBLANK(I5),"",";"),I5,IF(ISBLANK(I6),"",";"),I6,IF(ISBLANK(I7),"",";"),I7,IF(ISBLANK(I8),"",";"),I8,IF(ISBLANK(I9),"",";"),I9,IF(ISBLANK(I10),"",";"),I10,IF(ISBLANK(I11),"",";"),I11,IF(ISBLANK(I12),"",";"),I12,IF(ISBLANK(I13),"",";"),I13,IF(ISBLANK(I14),"",";"),I14,IF(ISBLANK(I15),"",";"),I15,IF(ISBLANK(I16),"",";"),I16,IF(ISBLANK(I17),"",";"),I17,IF(ISBLANK(I18),"",";"),I18,IF(ISBLANK(I19),"",";"),I19,IF(ISBLANK(I20),"",";"),I20,IF(ISBLANK(I21),"",";"),I21,IF(ISBLANK(I22),"",";"),I22,IF(ISBLANK(I23),"",";"),I23,IF(ISBLANK(I24),"",";"),I24,IF(ISBLANK(I25),"",";"),I25) -> 0.03;0.03;0.03;0.03;0.03;0.03;0.03;0.03;0.03;0.03;0.03;0.03;0.03;0.03;0.03;0.03;0.03;0.04;0.14;0.19 | ... CK26: =_xlfn.CONCAT(CK2,";",CK3,";",CK4,IF(ISBLANK(CK5),"",";"),CK5,IF(ISBLANK(CK6),"",";"),CK6,IF(ISBLANK(CK7),"",";"),CK7,IF(ISBLANK(CK8),"",";"),CK8,IF(ISBLANK(CK9),"",";"),CK9,IF(ISBLANK(CK10),"",";"),CK10,IF(ISBLANK(CK11),"",";"),CK11,IF(ISBLANK(CK12),"",";"),CK12,IF(ISBLANK(CK13),"",";"),CK13,IF(ISBLANK(CK14),"",";"),CK14,IF(ISBLANK(CK15),"",";"),CK15,IF(ISBLANK(CK16),"",";"),CK16,IF(ISBLANK(CK17),"",";"),CK17,IF(ISBLANK(CK18),"",";"),CK18,IF(ISBLANK(CK19),"",";"),CK19,IF(ISBLANK(CK20),"",";"),CK20,IF(ISBLANK(CK21),"",";"),CK21,IF(ISBLANK(CK22),"",";"),CK22,IF(ISBLANK(CK23),"",";"),CK23,IF(ISBLANK(CK24),"",";"),CK24,IF(ISBLANK(CK25),"",";"),CK25) -> 0.055;0.054;0.048;0.042;0.032;0.032;0.032;0.032;0.032;0.032;0.032;0.032;0.032;0.032;0.032;0.032;0.032;0.067;0.098;0.125

Sheet SFC-Models-PRIME
A1: Loan Product Variables | C1: Term of Loan in Mths (total) | D1: Avg Loan Size $'s | E1: Loan Interest Rate | F1: CDR - Promotion Period Only | G1: Constant Prepay Rate | H1: Servicing Fees | I1: Late Fees% UPB/Mth | J1: Default Recovery % | K1: Promotional Period Term | L1: Promo Period Prepayment | M1: SFC Selling Price | N1: SFC Loan Margin | O1: SFC Purchase Price | P1: Merchant Discount | Q1: CDR No Promo or Post Promo | R1: Single Pool Net Loan Yield
A2: NINP899/63 | B2: =VLOOKUP(A2,'SFC-Models-SFY'!$A$2:$B$56,2,FALSE) -> Unsec Std - 899 / 63 | C2: 63 | D2: 9084.7488 | E2: 0.0899 | F2: 0.0041047642 | G2: 0.23 | H2: 0 | I2: 2e-05 | J2: 0.15 | K2: 3 | L2: 0.15622343 | M2: 1.005 | N2: 0.02 | O2: 0.985 | P2: 0.015 | Q2: 0.0041047642 | R2: 0.069972552 | S2: =HLOOKUP(A2,'PRIME-CPR'!$B$1:$CK$26,26,FALSE) -> 0.0436711592742046;0.051181123470062;0.0613711445667025
A3: NINP1099/63 | B3: =VLOOKUP(A3,'SFC-Models-SFY'!$A$2:$B$56,2,FALSE) -> Unsec Std - 1099 / 63 | C3: 63 | D3: 9084.7488 | E3: 0.1099 | F3: 0.01093248 | G3: 0.23 | H3: 0 | I3: 2e-05 | J3: 0.15 | K3: 3 | L3: 0.15622343 | M3: 1.005 | N3: 0.02 | O3: 0.985 | P3: 0.015 | Q3: 0.01093248 | R3: 0.080697011 | S3: =HLOOKUP(A3,'PRIME-CPR'!$B$1:$CK$26,26,FALSE) -> 0.0436711592742046;0.051181123470062;0.0613711445667025
A4: NINP1199/63 | B4: =VLOOKUP(A4,'SFC-Models-SFY'!$A$2:$B$56,2,FALSE) -> Unsec Std - 1199 / 63 | C4: 63 | D4: 9084.7488 | E4: 0.1199 | F4: 0.00943488 | G4: 0.23 | H4: 0 | I4: 2e-05 | J4: 0.15 | K4: 3 | L4: 0.15622343 | M4: 1.005 | N4: 0.02 | O4: 0.985 | P4: 0.015 | Q4: 0.00943488 | R4: 0.090397598 | S4: =HLOOKUP(A4,'PRIME-CPR'!$B$1:$CK$26,26,FALSE) -> 0.0436711592742046;0.051181123470062;0.0613711445667025
A5: NINP1399/63 | B5: =VLOOKUP(A5,'SFC-Models-SFY'!$A$2:$B$56,2,FALSE) -> Unsec Std - 1399 / 63 | C5: 63 | D5: 9084.7488 | E5: 0.1399 | F5: 0.01919243 | G5: 0.23 | H5: 0 | I5: 2e-05 | J5: 0.15 | K5: 3 | L5: 0.15622343 | M5: 1.005 | N5: 0.02 | O5: 0.985 | P5: 0.015 | Q5: 0.01919243 | R5: 0.09825042 | S5: =HLOOKUP(A5,'PRIME-CPR'!$B$1:$CK$26,26,FALSE) -> 0.0436711592742046;0.051181123470062;0.0613711445667025
A6: NINP699/186 | B6: =VLOOKUP(A6,'SFC-Models-SFY'!$A$2:$B$56,2,FALSE) -> Unsec Std - 699 / 186 | C6: 186 | D6: 9084.7488 | E6: 0.0699 | F6: 0.004368 | G6: 0.23 | H6: 0 | I6: 2e-05 | J6: 0.15 | K6: 6 | L6: 0.39420057 | M6: 0.9925 | N6: 0.02 | O6: 0.9725 | P6: 0.0275 | Q6: 0.004368 | R6: 0.054827875 | S6: =HLOOKUP(A6,'PRIME-CPR'!$B$1:$CK$26,26,FALSE) -> 0.0489849142849816;0.0428030164624041;0.0419287220074737;0.0555459909257746;0.0882837424238861;0.116654180496246
A7: NINP1099/186 | B7: =VLOOKUP(A7,'SFC-Models-SFY'!$A$2:$B$56,2,FALSE) -> Unsec Std - 1099 / 186 | C7: 186 | D7: 9084.7488 | E7: 0.1099 | F7: 0.00894504 | G7: 0.23 | H7: 0 | I7: 2e-05 | J7: 0.15 | K7: 6 | L7: 0.39420057 | M7: 0.9925 | N7: 0.02 | O7: 0.9725 | P7: 0.0275 | Q7: 0.00894504 | R7: 0.081311552 | S7: =HLOOKUP(A7,'PRIME-CPR'!$B$1:$CK$26,26,FALSE) -> 0.0489849142849816;0.0428030164624041;0.0419287220074737;0.0555459909257746;0.0882837424238861;0.116654180496246
A8: NINP1199/186 | B8: =VLOOKUP(A8,'SFC-Models-SFY'!$A$2:$B$56,2,FALSE) -> Unsec Std - 1199 / 186 | C8: 186 | D8: 9084.7488 | E8: 0.1199 | F8: 0.00853632 | G8: 0.23 | H8: 0 | I8: 2e-05 | J8: 0.15 | K8: 6 | L8: 0.39420057 | M8: 0.9925 | N8: 0.02 | O8: 0.9725 | P8: 0.0275 | Q8: 0.00853632 | R8: 0.089186274 | S8: =HLOOKUP(A8,'PRIME-CPR'!$B$1:$CK$26,26,FALSE) -> 0.0489849142849816;0.0428030164624041;0.0419287220074737;0.0555459909257746;0.0882837424238861;0.116654180496246
A9: NINP1399/186 | B9: =VLOOKUP(A9,'SFC-Models-SFY'!$A$2:$B$56,2,FALSE) -> Unsec Std - 1399 / 186 | C9: 186 | D9: 9084.7488 | E9: 0.1399 | F9: 0.01576536 | G9: 0.23 | H9: 0 | I9: 2e-05 | J9: 0.15 | K9: 6 | L9: 0.39420057 | M9: 0.9925 | N9: 0.02 | O9: 0.9725 | P9: 0.0275 | Q9: 0.01576536 | R9: 0.097479195 | S9: =HLOOKUP(A9,'PRIME-CPR'!$B$1:$CK$26,26,FALSE) -> 0.0489849142849816;0.0428030164624041;0.0419287220074737;0.0555459909257746;0.0882837424238861;0.116654180496246
A10: NINP899/132 | B10: =VLOOKUP(A10,'SFC-Models-SFY'!$A$2:$B$56,2,FALSE) -> Unsec Std - 899 / 132 | C10: 132 | D10: 9084.7488 | E10: 0.0899 | F10: 0.0046178598 | G10: 0.23 | H10: 0 | I10: 2e-05 | J10: 0.15 | K10: 12 | L10: 0.5 | M10: 0.9825 | N10: 0.02 | O10: 0.9625 | P10: 0.0375 | Q10: 0.0046178598 | R10: 0.057211783 | S10: =HLOOKUP(A10,'PRIME-CPR'!$B$1:$CK$26,26,FALSE) -> 0.034087798153406;0.029131872311023;0.029131872311023;0.025455429050157;0.025455429050157;0.024935476432192;0.024935476432192;0.0330338174243784;0.0330338174243784;0.052503321664899;0.0723270250344311;0.115968664711763
A11: NINP1099/132 | B11: =VLOOKUP(A11,'SFC-Models-SFY'!$A$2:$B$56,2,FALSE) -> Unsec Std - 1099 / 132 | C11: 132 | D11: 9084.7488 | E11: 0.1099 | F11: 0.01003392 | G11: 0.23 | H11: 0 | I11: 2e-05 | J11: 0.15 | K11: 12 | L11: 0.5 | M11: 0.9825 | N11: 0.02 | O11: 0.9625 | P11: 0.0375 | Q11: 0.01003392 | R11: 0.063656481 | S11: =HLOOKUP(A11,'PRIME-CPR'!$B$1:$CK$26,26,FALSE) -> 0.034087798153406;0.029131872311023;0.029131872311023;0.025455429050157;0.025455429050157;0.024935476432192;0.024935476432192;0.0330338174243784;0.0330338174243784;0.052503321664899;0.0723270250344311;0.115968664711763
A12: NINP1199/132 | B12: =VLOOKUP(A12,'SFC-Models-SFY'!$A$2:$B$56,2,FALSE) -> Unsec Std - 1199 / 132 | C12: 132 | D12: 9084.7488 | E12: 0.1199 | F12: 0.00928512 | G12: 0.23 | H12: 0 | I12: 2e-05 | J12: 0.15 | K12: 12 | L12: 0.5 | M12: 0.9825 | N12: 0.02 | O12: 0.9625 | P12: 0.0375 | Q12: 0.00928512 | R12: 0.069913491 | S12: =HLOOKUP(A12,'PRIME-CPR'!$B$1:$CK$26,26,FALSE) -> 0.034087798153406;0.029131872311023;0.029131872311023;0.025455429050157;0.025455429050157;0.024935476432192;0.024935476432192;0.0330338174243784;0.0330338174243784;0.052503321664899;0.0723270250344311;0.115968664711763
A13: NINP1399/132 | B13: =VLOOKUP(A13,'SFC-Models-SFY'!$A$2:$B$56,2,FALSE) -> Unsec Std - 1399 / 132 | C13: 132 | D13: 9084.7488 | E13: 0.1399 | F13: 0.018306625 | G13: 0.23 | H13: 0 | I13: 2e-05 | J13: 0.15 | K13: 12 | L13: 0.5 | M13: 0.9825 | N13: 0.02 | O13: 0.9625 | P13: 0.0375 | Q13: 0.018306625 | R13: 0.072701096 | S13: =HLOOKUP(A13,'PRIME-CPR'!$B$1:$CK$26,26,FALSE) -> 0.034087798153406;0.029131872311023;0.029131872311023;0.025455429050157;0.025455429050157;0.024935476432192;0.024935476432192;0.0330338174243784;0.0330338174243784;0.052503321664899;0.0723270250344311;0.115968664711763
A14: 899/120 | B14: =VLOOKUP(A14,'SFC-Models-SFY'!$A$2:$B$56,2,FALSE) -> Unsec Std - 899 / 120 | C14: 120 | D14: 10000 | E14: 0.0899 | G14: 0.12 | H14: 0.0165 | I14: 2e-05 | J14: 0.15 | M14: 0.9825 | N14: 0.02 | O14: 0.9625 | P14: 0.0375 | Q14: 0.032 | R14: 0.050711555 | S14: =HLOOKUP(A14,'PRIME-CPR'!$B$1:$CK$26,26,FALSE) -> #N/A
A15: 899/180 | B15: =VLOOKUP(A15,'SFC-Models-SFY'!$A$2:$B$56,2,FALSE) -> Unsec Std - 899 / 180 | C15: 180 | D15: 10000 | E15: 0.0899 | G15: 0.12 | H15: 0.0165 | I15: 2e-05 | J15: 0.15 | M15: 0.9825 | N15: 0.02 | O15: 0.9625 | P15: 0.0375 | Q15: 0.032 | R15: 0.049700226 | S15: =HLOOKUP(A15,'PRIME-CPR'!$B$1:$CK$26,26,FALSE) -> #N/A
A16: 399-60 | B16: =VLOOKUP(A16,'SFC-Models-SFY'!$A$2:$B$56,2,FALSE) -> Unsec Std - 399 - 60 | C16: 60 | D16: 10000 | E16: 0.0399 | G16: 0.1 | H16: 0.0165 | I16: 2e-05 | J16: 0.15 | M16: 0.93 | N16: 0.02 | O16: 0.91 | P16: 0.09 | Q16: 0.014 | R16: 0.04576961 | S16: =HLOOKUP(A16,'PRIME-CPR'!$B$1:$CK$26,26,FALSE) -> #N/A
A17: 399-84 | B17: =VLOOKUP(A17,'SFC-Models-SFY'!$A$2:$B$56,2,FALSE) -> Unsec Std - 399 - 84 | C17: 84 | D17: 10000 | E17: 0.0399 | G17: 0.1 | H17: 0.0165 | I17: 2e-05 | J17: 0.15 | M17: 0.92 | N17: 0.02 | O17: 0.9 | P17: 0.1 | Q17: 0.014 | R17: 0.041813838 | S17: =HLOOKUP(A17,'PRIME-CPR'!$B$1:$CK$26,26,FALSE) -> #N/A
A18: 1440-120 | B18: =VLOOKUP(A18,'SFC-Models-SFY'!$A$2:$B$56,2,FALSE) -> Unsec Std - 1440 - 120 | C18: 120 | D18: 10000 | E18: 0.144 | G18: 0.163 | H18: 0.0165 | I18: 2e-05 | J18: 0.15 | M18: 0.97 | N18: 0.02 | O18: 0.95 | P18: 0.05 | Q18: 0.0964 | R18: 0.051116231 | S18: =HLOOKUP(A18,'PRIME-CPR'!$B$1:$CK$26,26,FALSE) -> #N/A
A19: 6MBD | B19: =VLOOKUP(A19,'SFC-Models-SFY'!$A$2:$B$56,2,FALSE) -> 6 Mth BD WPDI | C19: 61 | D19: 5719 | E19: 0.2147 | F19: 0.0964 | G19: 0.2345 | H19: 0.0165 | I19: 2e-05 | J19: 0.15 | K19: 6 | L19: 0.2948 | M19: 0.921 | N19: 0.02 | O19: 0.901 | P19: 0.099 | Q19: 0.0964 | R19: 0.15485002 | S19: =HLOOKUP(A19,'PRIME-CPR'!$B$1:$CK$26,26,FALSE) -> #N/A
A20: 12MBD | B20: =VLOOKUP(A20,'SFC-Models-SFY'!$A$2:$B$56,2,FALSE) -> 6 Mth BD WPDI 12S | C20: 63 | D20: 6630 | E20: 0.2187 | F20: 0.0964 | G20: 0.239 | H20: 0.0165 | I20: 2e-05 | J20: 0.15 | K20: 12 | L20: 0.473 | M20: 0.921 | N20: 0.02 | O20: 0.901 | P20: 0.099 | Q20: 0.0964 | R20: 0.12440401 | S20: =HLOOKUP(A20,'PRIME-CPR'!$B$1:$CK$26,26,FALSE) -> #N/A
A21: 849-120 | B21: =VLOOKUP(A21,'SFC-Models-SFY'!$A$2:$B$56,2,FALSE) -> Unsec Std - 849 - 120 | C21: 120 | D21: 10000 | E21: 0.0849 | G21: 0.12 | H21: 0 | I21: 2e-05 | J21: 0.15 | M21: 0.9825 | N21: 0.02 | O21: 0.9625 | P21: 0.0375 | Q21: 0.028 | R21: 0.065878879 | S21: =HLOOKUP(A21,'PRIME-CPR'!$B$1:$CK$26,26,FALSE) -> #N/A
A22: 849-180 | B22: =VLOOKUP(A22,'SFC-Models-SFY'!$A$2:$B$56,2,FALSE) -> Unsec Std - 849 - 180 | C22: 180 | D22: 10000 | E22: 0.0849 | G22: 0.12 | H22: 0 | I22: 2e-05 | J22: 0.15 | M22: 0.9825 | N22: 0.02 | O22: 0.9625 | P22: 0.0375 | Q22: 0.028 | R22: 0.064873162 | S22: =HLOOKUP(A22,'PRIME-CPR'!$B$1:$CK$26,26,FALSE) -> #N/A
A23: 155PF | B23: =VLOOKUP(A23,'SFC-Models-SFY'!$A$2:$B$56,2,FALSE) -> Unsec Std - 1390 - 120 | C23: 120 | D23: 10000 | E23: 0.139 | G23: 0.163 | H23: 0 | I23: 2e-05 | J23: 0.15 | M23: 0.97 | N23: 0.02 | O23: 0.95 | P23: 0.05 | Q23: 0.0964 | R23: 0.062656791 | S23: =HLOOKUP(A23,'PRIME-CPR'!$B$1:$CK$26,26,FALSE) -> #N/A
A24: NINP849-63 | B24: =VLOOKUP(A24,'SFC-Models-SFY'!$A$2:$B$56,2,FALSE) -> Unsec Std - 849 - 63 | C24: 63 | D24: 9084.7488 | E24: 0.0849 | F24: 0.0041047642 | G24: 0.23 | H24: 0 | I24: 2e-05 | J24: 0.15 | K24: 3 | L24: 0.15622343 | M24: 1.005 | N24: 0.02 | O24: 0.985 | P24: 0.015 | Q24: 0.0041047642 | R24: 0.0657583 | S24: =HLOOKUP(A24,'PRIME-CPR'!$B$1:$CK$26,26,FALSE) -> 0.0436711592742046;0.051181123470062;0.0613711445667025
A25: NINP1049-63 | B25: =VLOOKUP(A25,'SFC-Models-SFY'!$A$2:$B$56,2,FALSE) -> Unsec Std - 1049 - 63 | C25: 63 | D25: 9084.7488 | E25: 0.1049 | F25: 0.01093248 | G25: 0.23 | H25: 0 | I25: 2e-05 | J25: 0.15 | K25: 3 | L25: 0.15622343 | M25: 1.005 | N25: 0.02 | O25: 0.985 | P25: 0.015 | Q25: 0.01093248 | R25: 0.076511354 | S25: =HLOOKUP(A25,'PRIME-CPR'!$B$1:$CK$26,26,FALSE) -> 0.0436711592742046;0.051181123470062;0.0613711445667025
A26: NINP1349-63 | B26: =VLOOKUP(A26,'SFC-Models-SFY'!$A$2:$B$56,2,FALSE) -> Unsec Std - 1349 - 63 | C26: 63 | D26: 9084.7488 | E26: 0.1349 | F26: 0.01919243 | G26: 0.23 | H26: 0 | I26: 2e-05 | J26: 0.15 | K26: 3 | L26: 0.15622343 | M26: 1.005 | N26: 0.02 | O26: 0.985 | P26: 0.015 | Q26: 0.01919243 | R26: 0.09410417 | S26: =HLOOKUP(A26,'PRIME-CPR'!$B$1:$CK$26,26,FALSE) -> 0.0436711592742046;0.051181123470062;0.0613711445667025
A27: NINP649-186 | B27: =VLOOKUP(A27,'SFC-Models-SFY'!$A$2:$B$56,2,FALSE) -> Unsec Std - 649 - 186 | C27: 186 | D27: 9084.7488 | E27: 0.0649 | F27: 0.004368 | G27: 0.23 | H27: 0 | I27: 2e-05 | J27: 0.15 | K27: 6 | L27: 0.39420057 | M27: 0.9925 | N27: 0.02 | O27: 0.9725 | P27: 0.0275 | Q27: 0.004368 | R27: 0.050952089 | S27: =HLOOKUP(A27,'PRIME-CPR'!$B$1:$CK$26,26,FALSE) -> 0.0489849142849816;0.0428030164624041;0.0419287220074737;0.0555459909257746;0.0882837424238861;0.116654180496246
A28: NINP1049-186 | B28: =VLOOKUP(A28,'SFC-Models-SFY'!$A$2:$B$56,2,FALSE) -> Unsec Std - 1049 - 186 | C28: 186 | D28: 9084.7488 | E28: 0.1049 | F28: 0.00894504 | G28: 0.23 | H28: 0 | I28: 2e-05 | J28: 0.15 | K28: 6 | L28: 0.39420057 | M28: 0.9925 | N28: 0.02 | O28: 0.9725 | P28: 0.0275 | Q28: 0.00894504 | R28: 0.07753936 | S28: =HLOOKUP(A28,'PRIME-CPR'!$B$1:$CK$26,26,FALSE) -> 0.0489849142849816;0.0428030164624041;0.0419287220074737;0.0555459909257746;0.0882837424238861;0.116654180496246
A29: NINP1149-186a | B29: =VLOOKUP(A29,'SFC-Models-SFY'!$A$2:$B$56,2,FALSE) -> #N/A | C29: 186 | D29: 9084.7488 | E29: 0.1149 | F29: 0.00853632 | G29: 0.23 | H29: 0 | I29: 2e-05 | J29: 0.15 | K29: 6 | L29: 0.39420057 | M29: 0.9925 | N29: 0.02 | O29: 0.9725 | P29: 0.0275 | Q29: 0.00853632 | R29: 0.085438511 | S29: =HLOOKUP(A29,'PRIME-CPR'!$B$1:$CK$26,26,FALSE) -> 0.0489849142849816;0.0428030164624041;0.0419287220074737;0.0555459909257746;0.0882837424238861;0.116654180496246
A30: NINP1349-186 | B30: =VLOOKUP(A30,'SFC-Models-SFY'!$A$2:$B$56,2,FALSE) -> Unsec Std - 1349 - 186 | C30: 186 | D30: 9084.7488 | E30: 0.1349 | F30: 0.01576536 | G30: 0.23 | H30: 0 | I30: 2e-05 | J30: 0.15 | K30: 6 | L30: 0.39420057 | M30: 0.9925 | N30: 0.02 | O30: 0.9725 | P30: 0.0275 | Q30: 0.01576536 | R30: 0.093795811 | S30: =HLOOKUP(A30,'PRIME-CPR'!$B$1:$CK$26,26,FALSE) -> 0.0489849142849816;0.0428030164624041;0.0419287220074737;0.0555459909257746;0.0882837424238861;0.116654180496246
A31: NINP849-132 | B31: =VLOOKUP(A31,'SFC-Models-SFY'!$A$2:$B$56,2,FALSE) -> Unsec Std - 849 - 132 | C31: 132 | D31: 9084.7488 | E31: 0.0849 | F31: 0.0046178598 | G31: 0.23 | H31: 0 | I31: 2e-05 | J31: 0.15 | K31: 12 | L31: 0.5 | M31: 0.9825 | N31: 0.02 | O31: 0.9625 | P31: 0.0375 | Q31: 0.0046178598 | R31: 0.054357781 | S31: =HLOOKUP(A31,'PRIME-CPR'!$B$1:$CK$26,26,FALSE) -> 0.034087798153406;0.029131872311023;0.029131872311023;0.025455429050157;0.025455429050157;0.024935476432192;0.024935476432192;0.0330338174243784;0.0330338174243784;0.052503321664899;0.0723270250344311;0.115968664711763
A32: NINP1049-132 | B32: =VLOOKUP(A32,'SFC-Models-SFY'!$A$2:$B$56,2,FALSE) -> Unsec Std - 1049 - 132 | C32: 132 | D32: 9084.7488 | E32: 0.1049 | F32: 0.01003392 | G32: 0.23 | H32: 0 | I32: 2e-05 | J32: 0.15 | K32: 12 | L32: 0.5 | M32: 0.9825 | N32: 0.02 | O32: 0.9625 | P32: 0.0375 | Q32: 0.01003392 | R32: 0.060852269 | S32: =HLOOKUP(A32,'PRIME-CPR'!$B$1:$CK$26,26,FALSE) -> 0.034087798153406;0.029131872311023;0.029131872311023;0.025455429050157;0.025455429050157;0.024935476432192;0.024935476432192;0.0330338174243784;0.0330338174243784;0.052503321664899;0.0723270250344311;0.115968664711763
A33: NINP1349-132 | B33: =VLOOKUP(A33,'SFC-Models-SFY'!$A$2:$B$56,2,FALSE) -> Unsec Std - 1349 - 132 | C33: 132 | D33: 9084.7488 | E33: 0.1349 | F33: 0.018306625 | G33: 0.23 | H33: 0 | I33: 2e-05 | J33: 0.15 | K33: 12 | L33: 0.5 | M33: 0.9825 | N33: 0.02 | O33: 0.9625 | P33: 0.0375 | Q33: 0.018306625 | R33: 0.069974011 | S33: =HLOOKUP(A33,'PRIME-CPR'!$B$1:$CK$26,26,FALSE) -> 0.034087798153406;0.029131872311023;0.029131872311023;0.025455429050157;0.025455429050157;0.024935476432192;0.024935476432192;0.0330338174243784;0.0330338174243784;0.052503321664899;0.0723270250344311;0.115968664711763
A34: NINP949-63 | B34: =VLOOKUP(A34,'SFC-Models-SFY'!$A$2:$B$56,2,FALSE) -> Unsec Std - 949 - 63 | C34: 63 | D34: 9084.7488 | E34: 0.0949 | F34: 0.0052 | G34: 0.23 | H34: 0 | I34: 2e-05 | J34: 0.15 | K34: 3 | L34: 0.15622343 | M34: 1.005 | N34: 0.02 | O34: 0.985 | P34: 0.015 | Q34: 0.0041047642 | R34: 0.074040846 | S34: =HLOOKUP(A34,'PRIME-CPR'!$B$1:$CK$26,26,FALSE) -> 0.0436711592742046;0.051181123470062;0.0613711445667025
A35: NINP1149-63 | B35: =VLOOKUP(A35,'SFC-Models-SFY'!$A$2:$B$56,2,FALSE) -> Unsec Std - 1149 - 63 | C35: 63 | D35: 9084.7488 | E35: 0.1149 | F35: 0.0156 | G35: 0.23 | H35: 0 | I35: 2e-05 | J35: 0.15 | K35: 3 | L35: 0.15622343 | M35: 1.005 | N35: 0.02 | O35: 0.985 | P35: 0.015 | Q35: 0.01093248 | R35: 0.08426103 | S35: =HLOOKUP(A35,'PRIME-CPR'!$B$1:$CK$26,26,FALSE) -> 0.0436711592742046;0.051181123470062;0.0613711445667025
... A45: NINP1449-132 | B45: =VLOOKUP(A45,'SFC-Models-SFY'!$A$2:$B$56,2,FALSE) -> Unsec Std - 1449 - 132 | C45: 132 | D45: 9084.7488 | E45: 0.1449 | F45: 0.0398 | G45: 0.23 | H45: 0 | I45: 2e-05 | J45: 0.15 | K45: 12 | L45: 0.5 | M45: 0.9825 | N45: 0.02 | O45: 0.9625 | P45: 0.0375 | Q45: 0.018306625 | R45: 0.067018173 | S45: =HLOOKUP(A45,'PRIME-CPR'!$B$1:$CK$26,26,FALSE) -> 0.034087798153406;0.029131872311023;0.029131872311023;0.025455429050157;0.025455429050157;0.024935476432192;0.024935476432192;0.0330338174243784;0.0330338174243784;0.052503321664899;0.0723270250344311;0.115968664711763
A46: 949-120 | B46: =VLOOKUP(A46,'SFC-Models-SFY'!$A$2:$B$56,2,FALSE) -> Unsec Std - 949 - 120 | C46: 120 | D46: 10000 | E46: 0.0949 | G46: 0.12 | H46: 0 | I46: 2e-05 | J46: 0.15 | M46: 0.9825 | N46: 0.02 | O46: 0.9625 | P46: 0.0375 | Q46: 0.028 | R46: 0.075865399 | S46: =HLOOKUP(A46,'PRIME-CPR'!$B$1:$CK$26,26,FALSE) -> #N/A
A47: 1490-120 | B47: =VLOOKUP(A47,'SFC-Models-SFY'!$A$2:$B$56,2,FALSE) -> Unsec Std - 1490 - 120 | C47: 120 | D47: 10000 | E47: 0.149 | G47: 0.163 | H47: 0 | I47: 2e-05 | J47: 0.15 | M47: 0.97 | N47: 0.02 | O47: 0.95 | P47: 0.05 | Q47: 0.0964 | R47: 0.072466138 | S47: =HLOOKUP(A47,'PRIME-CPR'!$B$1:$CK$26,26,FALSE) -> #N/A
A48: NINP649-132 | B48: =VLOOKUP(A48,'SFC-Models-SFY'!$A$2:$B$56,2,FALSE) -> Unsec Std - 649 - 132 | C48: 132 | D48: 9084.7488 | E48: 0.0649 | F48: 0.0058 | G48: 0.23 | H48: 0 | I48: 2e-05 | J48: 0.15 | K48: 12 | L48: 0.5 | M48: 0.9825 | N48: 0.02 | O48: 0.9625 | P48: 0.0375 | Q48: 0.0046178598 | R48: 0.042425322 | S48: =HLOOKUP(A48,'PRIME-CPR'!$B$1:$CK$26,26,FALSE) -> 0.034087798153406;0.029131872311023;0.029131872311023;0.025455429050157;0.025455429050157;0.024935476432192;0.024935476432192;0.0330338174243784;0.0330338174243784;0.052503321664899;0.0723270250344311;0.115968664711763
A49: NINP1149-128 | B49: =VLOOKUP(A49,'SFC-Models-SFY'!$A$2:$B$56,2,FALSE) -> #N/A | C49: 128 | D49: 9084.7488 | E49: 0.1149 | F49: 0.0265 | G49: 0.23 | H49: 0 | I49: 2e-05 | J49: 0.15 | K49: 8 | L49: 0.4056687 | M49: 0.9825 | N49: 0.02 | O49: 0.9625 | P49: 0.0375 | Q49: 0.00928512 | R49: 0.077195483 | S49: =HLOOKUP(A49,'PRIME-CPR'!$B$1:$CK$26,26,FALSE) -> 0.051131697230109;0.0436978084665345;0.0436978084665345;0.0381831435752355;0.0381831435752355;0.037403214648288;0.037403214648288;0.115968664711763
A50: NINP1349-128 | B50: =VLOOKUP(A50,'SFC-Models-SFY'!$A$2:$B$56,2,FALSE) -> Unsec Std - 1349 - 128 | C50: 128 | D50: 9084.7488 | E50: 0.1149 | F50: 0.0265 | G50: 0.23 | H50: 0 | I50: 2e-05 | J50: 0.15 | K50: 8 | L50: 0.4056687 | M50: 0.9825 | N50: 0.02 | O50: 0.9625 | P50: 0.0375 | Q50: 0.018306625 | R50: 0.071466111 | S50: =HLOOKUP(A50,'PRIME-CPR'!$B$1:$CK$26,26,FALSE) -> 0.051131697230109;0.0436978084665345;0.0436978084665345;0.0381831435752355;0.0381831435752355;0.037403214648288;0.037403214648288;0.115968664711763
A51: 36EPNI | B51: =VLOOKUP(A51,'SFC-Models-SFY'!$A$2:$B$56,2,FALSE) -> Unsec Std - EPNI 36 Mo | C51: 36 | D51: 10226.825 | E51: 0 | G51: 0.214 | H51: 0 | I51: 2e-05 | J51: 0.15 | M51: 0.92 | N51: 0.02 | O51: 0.9 | P51: 0.1 | Q51: 0.011061839 | R51: 0.059255891 | S51: =HLOOKUP(A51,'PRIME-CPR'!$B$1:$CK$26,26,FALSE) -> #N/A
A52: 60EPNI | B52: =VLOOKUP(A52,'SFC-Models-SFY'!$A$2:$B$56,2,FALSE) -> Unsec Std - EPNI 60 Mo | C52: 60 | D52: 11934.352 | E52: 0 | G52: 0.139 | H52: 0 | I52: 2e-05 | J52: 0.15 | M52: 0.885 | N52: 0.02 | O52: 0.865 | P52: 0.135 | Q52: 0.010313211 | R52: 0.05356764 | S52: =HLOOKUP(A52,'PRIME-CPR'!$B$1:$CK$26,26,FALSE) -> #N/A
A53: NINP4331 | B53: =VLOOKUP(A53,'SFC-Models-SFY'!$A$2:$B$56,2,FALSE) -> #N/A | C53: 123 | D53: 10000 | E53: 0.099 | F53: 0.0099055277 | G53: 0.316 | H53: 0 | I53: 2e-05 | J53: 0.15 | K53: 3 | L53: 0.15622343 | M53: 1.005 | N53: 0.02 | O53: 0.985 | P53: 0.015 | Q53: 0.0099055277 | R53: 0.074175803 | S53: =HLOOKUP(A53,'PRIME-CPR'!$B$1:$CK$26,26,FALSE) -> 0.0436711592742046;0.051181123470062;0.0613711445667025
A54: NINP4306 | B54: =VLOOKUP(A54,'SFC-Models-SFY'!$A$2:$B$56,2,FALSE) -> #N/A | C54: 183 | D54: 10000 | E54: 0.099 | F54: 0.0093474245 | G54: 0.316 | H54: 0 | I54: 2e-05 | J54: 0.15 | K54: 3 | L54: 0.15622343 | M54: 0.9925 | N54: 0.02 | O54: 0.9725 | P54: 0.0275 | Q54: 0.0093474245 | R54: 0.082280172 | S54: =HLOOKUP(A54,'PRIME-CPR'!$B$1:$CK$26,26,FALSE) -> 0.0436711592742046;0.051181123470062;0.0613711445667025
A55: NINP849-183 | B55: =VLOOKUP(A55,'SFC-Models-SFY'!$A$2:$B$56,2,FALSE) -> #N/A | C55: 183 | D55: 10000 | E55: 0.0849 | F55: 0.0125 | G55: 0.316 | H55: 0 | I55: 2e-05 | J55: 0.15 | K55: 3 | L55: 0.15622343 | M55: 0.974 | N55: 0.02 | O55: 0.954 | P55: 0.046 | Q55: 0.028 | R55: 0.064987071 | S55: =HLOOKUP(A55,'PRIME-CPR'!$B$1:$CK$26,26,FALSE) -> 0.0436711592742046;0.051181123470062;0.0613711445667025
A56: 1099-120 | B56: =VLOOKUP(A56,'SFC-Models-SFY'!$A$2:$B$56,2,FALSE) -> Unsec Std - 1099 - 120 | C56: 120 | D56: 10000 | E56: 0.1099 | G56: 0.163 | H56: 0 | I56: 2e-05 | J56: 0.15 | M56: 0.9 | N56: 0.02 | O56: 0.88 | P56: 0.12 | Q56: 0.0964 | R56: 0.064286895 | S56: =HLOOKUP(A56,'PRIME-CPR'!$B$1:$CK$26,26,FALSE) -> #N/A
